Workbook

Sheet Bldgs & Rooms
A1: If there are not multiple buildings, do not modify this column | B1: Modify this column to name each "room" or "location" where equipment is located, using the customer's description
A2: Main Bldg.
A3: Main Bldg.
A4: Main Bldg.
A5: Main Bldg.
A6: Main Bldg.
A7: Main Bldg.
A8: Main Bldg.
A9: Main Bldg.
A10: Main Bldg.
A11: Main Bldg.
A12: Main Bldg.
A13: Main Bldg.
... A31: Main Bldg.

Sheet Hours
A1: 600 Volt and below | B1: Full EPM | C1: De-energized Maint. | D1: IR | E1: Ultrasonic | F1: A-F Collection | G1: Pri.Breaker | H1: Sec. Breaker | I1: PwrFact (partial) | J1: PwrFact (xfmr/CB) | K1: Panel Schd. | L1: Oil Sample | M1: Basic EPM
A2: Switchgear - Incoming Main Service (Per Section) | B2: 2 | C2: 3.4833 | D2: 0.5833 | E2: 0.25 | F2: 1.45 | G2: 1 | H2: 0.75 | K2: 1 | M2: =D2+E2 -> 0.8333
A3: Switchgear Insulated Case Breakers (Bus Mounted) | B3: 0.3333 | C3: 4 | D3: 0.1667 | E3: 0.1667 | F3: 0.25 | G3: 0.5 | M3: =D3+E3 -> 0.3334
A4: SwitchGear Drawout Breakers | B4: 0.3333 | C4: 4 | D4: 0.1667 | E4: 0.1 | F4: 0.25 | H4: 0.75 | M4: =D4+E4 -> 0.2667
A5: Distribution Switchboard Multi Cover (Per Section) | B5: 1.1167 | C5: 0.9333 | D5: 0.3333 | E5: 0.25 | F5: 0.8833 | G5: 0.5 | K5: 1 | M5: =D5+E5 -> 0.5833
A6: Switchboard Disconnects | B6: 0.3333 | C6: 0.2667 | D6: 0.1667 | E6: 0.1667 | F6: 0.25 | M6: =D6+E6 -> 0.3334
A7: Switchboard Molded Case Breakers | B7: 0.3333 | C7: 4 | D7: 0.1667 | E7: 0.1667 | F7: 0.25 | G7: 0.5 | M7: =D7+E7 -> 0.3334
A8: Panelboard-Single Cover > 400A (Distribution Panel) | B8: 0.9333 | C8: 0.9333 | D8: 0.3333 | E8: 0.3333 | F8: 0.8833 | G8: 0.5 | K8: 0.75 | M8: =D8+E8 -> 0.6666
A9: Panelboard-Single Cover < 400A (Branch Ckt Panel) | B9: 0.75 | C9: 0.75 | D9: 0.25 | E9: 0.1667 | F9: 0.5833 | K9: 0.5 | M9: =D9+E9 -> 0.4167
A10: Motor Control Center (MCC-Per Vertical Section) | B10: 0.4667 | C10: 0.8167 | D10: 0.1333 | E10: 0.1167 | F10: 0.4667 | K10: 0.75 | M10: =D10+E10 -> 0.25
A11: MCC: Combination Motor Starters | B11: 0.4667 | C11: 0.8167 | D11: 0.1333 | E11: 0.1167 | F11: 0.4667 | G11: 0.5 | K11: 0.75 | M11: =D11+E11 -> 0.25
A12: MCC: Molded Case Breaker | B12: 0.3333 | C12: 4 | D12: 0.1667 | E12: 0.1667 | F12: 0.25 | G12: 0.5 | M12: =D12+E12 -> 0.3334
A13: MCC: Individual Disconnect Switch | B13: 0.3333 | C13: 0.5 | D13: 0.1667 | E13: 0.1 | F13: 0.25 | M13: =D13+E13 -> 0.2667
A14: Motor Control Panel (MCP) | B14: 0.4667 | C14: 0.8167 | D14: 0.1333 | E14: 0.1167 | F14: 0.4667 | K14: 0.75 | M14: =D14+E14 -> 0.25
A15: VFD Motor Control Panel (VFD-MCP) | B15: 0.4667 | C15: 0.8167 | D15: 0.1333 | E15: 0.1167 | F15: 0.4667 | K15: 0.75 | M15: =D15+E15 -> 0.25
A16: Individual Disconnect Switch > 100A | B16: 0.3333 | C16: 0.5 | D16: 0.1667 | E16: 0.1 | F16: 0.25 | G16: 0.5 | M16: =D16+E16 -> 0.2667
A17: Individual Molded Case Breaker > 100A | B17: 0.3333 | C17: 3 | D17: 0.1667 | E17: 0.1 | F17: 0.25 | G17: 0.5 | M17: =D17+E17 -> 0.2667
A18: Individual Combination Motor Starter > 100A | B18: 0.4667 | C18: 1.33 | D18: 0.1667 | E18: 0.1167 | F18: 0.4667 | G18: 0.5 | M18: =D18+E18 -> 0.2834
A19: Oil Filled Transformer - 5kV-15kV Primary - Any Size (Pad Mounted) | B19: 0.5833 | C19: 4 | D19: 0.3333 | E19: 0.25 | F19: 0.5833 | I19: 1 | J19: 1 | L19: 0.5833 | M19: =D19+E19 -> 0.5833
A20: Oil Filled Transformer - > 15kV Primary (Substation Class) | B20: 1.3 | C20: 16 | D20: 0.75 | E20: 0.5 | F20: 1.33 | I20: 1.5 | J20: 1.5 | L20: 0.75 | M20: =D20+E20 -> 1.25
A21: Dry Type Transformer - < 480V Primary - Any Size kVA | B21: 1.0833 | C21: 1.7333 | D21: 0.417 | E21: 0.417 | F21: 1 | I21: 0.75 | J21: 0.75 | M21: =D21+E21 -> 0.834
A22: Power Factor Correction Capacitors | B22: 0.6333 | C22: 8 | D22: 0.25 | E22: 0.2 | F22: 0.5 | M22: =D22+E22 -> 0.45
A23: Lighting Contactor > 100A | B23: 0.4333 | C23: 0.75 | D23: 0.1167 | E23: 0.1 | F23: 0.1667 | M23: =D23+E23 -> 0.2167
A24: Power Distribution Unit (PDU) | B24: 1.2833 | C24: 1.25 | D24: 0.25 | E24: 0.25 | F24: 1.1167 | M24: =D24+E24 -> 0.5
A25: Wire Trough, Gutter, or Large Junction Boxes | B25: 0.3333 | C25: 0.5 | D25: 0.3333 | E25: 0.25 | F25: 0.3333 | M25: =D25+E25 -> 0.5833
A26: Bus Duct - Vertical or Horizontal (Per 10' section) | B26: 0.1167 | C26: 0.75 | D26: 0.0833 | E26: 0.0833 | F26: 0.0833 | M26: =D26+E26 -> 0.1666
A27: Automatic Transfer Switch (ATS) > 100A | B27: 0.6667 | C27: 1.5 | D27: 0.4167 | E27: 0.3333 | F27: 0.5 | M27: =D27+E27 -> 0.75
A28: Manual Transfer Switch (MTS) > 100A | B28: 0.6667 | C28: 1 | D28: 0.4167 | E28: 0.3333 | F28: 0.5 | M28: =D28+E28 -> 0.75
A29: Variable Frequency Drives (VFD) < 50 HP | B29: 0.4667 | C29: 0.8167 | D29: 0.1333 | E29: 0.1167 | F29: 0.467 | M29: =D29+E29 -> 0.25
A30: Variable Frequency Drives (VFD) 51-200 HP | B30: 0.4667 | C30: 0.8167 | D30: 0.1333 | E30: 0.1167 | F30: 0.467 | M30: =D30+E30 -> 0.25
A31: Motors < 50 HP | B31: 0.4333 | C31: 1.1167 | D31: 0.1667 | E31: 0.1 | F31: 0.4333 | M31: =D31+E31 -> 0.2667
A32: Motors 51-200 HP | B32: 0.6 | C32: 1.5 | D32: 0.1667 | E32: 0.1 | F32: 0.4333 | M32: =D32+E32 -> 0.2667
A33: Motors 201-500 HP | B33: 0.8 | C33: 1.75 | D33: 0.1667 | E33: 0.1 | F33: 0.4333 | M33: =D33+E33 -> 0.2667
... A38: Uninterruptible Power Supply (UPS) > 50kVA | B38: 0.75 | C38: 3 | D38: 0.6667 | E38: 0.6667 | F38: 0.75 | M38: =D38+E38 -> 1.3334

Sheet Components Yr 1
A1: Building | B1: Room | C1: 600 Volt and below | D1: Total Counted | E1: Basic EPM | F1: Full EPM | G1: De-Energized | H1: IR | I1: Ultrasonic | J1: A-F Collection | K1: Pri.Breaker | L1: Sec. Breaker | M1: PwrFact (partial) | N1: PwrFact (xfmr/CB) | O1: Panel Schd. | P1: Oil Sample | Q1: ESA | R1: Total Hours | S1: Total pcs. priced
A2: ='Bldgs & Rooms'!$A$2 -> Main Bldg. | B2: ='Bldgs & Rooms'!$B$2 -> 0 | C2: =Hours!$A$2 -> Switchgear - Incoming Main Service (Per Section) | D2: =MAX(E2+F2,G2,H2,I2,J2,K2,L2,M2,N2,O2,P2,Q2) -> 0 | R2: =IF(SUMPRODUCT((E2:Q2)*1)=0,0,E2*INDEX(Hours!M:M,MATCH(C2,Hours!$A:$A,0))+F2*INDEX(Hours!B:B,MATCH(C2,Hours!$A:$A,0))+G2*INDEX(Hours!C:C,MATCH(C2,Hours!$A:$A,0))+H2*INDEX(Hours!D:D,MATCH(C2,Hours!$A:$A,0))+I2*INDEX(Hours!E:E,MATCH(C2,Hours!$A:$A,0))+J2*INDEX(Hours!F:F,MATCH(C2,Hours!$A:$A,0))+K2*INDEX(Hours!G:G,MATCH(C2,Hours!$A:$A,0))+L2*INDEX(Hours!H:H,MATCH(C2,Hours!$A:$A,0))+O2*INDEX(Hours!K:K,MATCH(C2,Hours!$A:$A,0))) -> 0 | S2: =MAX(E2+F2,G2,H2,I2,J2,K2,L2,M2,N2,O2,P2,Q2) -> 0
A3: ='Bldgs & Rooms'!$A$2 -> Main Bldg. | B3: ='Bldgs & Rooms'!$B$2 -> 0 | C3: =Hours!$A$3 -> Switchgear Insulated Case Breakers (Bus Mounted) | D3: =MAX(E3+F3,G3,H3,I3,J3,K3,L3,M3,N3,O3,P3,Q3) -> 0 | R3: =IF(SUMPRODUCT((E3:Q3)*1)=0,0,E3*INDEX(Hours!M:M,MATCH(C3,Hours!$A:$A,0))+F3*INDEX(Hours!B:B,MATCH(C3,Hours!$A:$A,0))+G3*INDEX(Hours!C:C,MATCH(C3,Hours!$A:$A,0))+H3*INDEX(Hours!D:D,MATCH(C3,Hours!$A:$A,0))+I3*INDEX(Hours!E:E,MATCH(C3,Hours!$A:$A,0))+J3*INDEX(Hours!F:F,MATCH(C3,Hours!$A:$A,0))+K3*INDEX(Hours!G:G,MATCH(C3,Hours!$A:$A,0))) -> 0 | S3: =MAX(E3+F3,G3,H3,I3,J3,K3,L3,M3,N3,O3,P3,Q3) -> 0
A4: ='Bldgs & Rooms'!$A$2 -> Main Bldg. | B4: ='Bldgs & Rooms'!$B$2 -> 0 | C4: =Hours!$A$4 -> SwitchGear Drawout Breakers | D4: =MAX(E4+F4,G4,H4,I4,J4,K4,L4,M4,N4,O4,P4,Q4) -> 0 | R4: =IF(SUMPRODUCT((E4:Q4)*1)=0,0,E4*INDEX(Hours!M:M,MATCH(C4,Hours!$A:$A,0))+F4*INDEX(Hours!B:B,MATCH(C4,Hours!$A:$A,0))+G4*INDEX(Hours!C:C,MATCH(C4,Hours!$A:$A,0))+H4*INDEX(Hours!D:D,MATCH(C4,Hours!$A:$A,0))+I4*INDEX(Hours!E:E,MATCH(C4,Hours!$A:$A,0))+J4*INDEX(Hours!F:F,MATCH(C4,Hours!$A:$A,0))+L4*INDEX(Hours!H:H,MATCH(C4,Hours!$A:$A,0))) -> 0 | S4: =MAX(E4+F4,G4,H4,I4,J4,K4,L4,M4,N4,O4,P4,Q4) -> 0
A5: ='Bldgs & Rooms'!$A$2 -> Main Bldg. | B5: ='Bldgs & Rooms'!$B$2 -> 0 | C5: =Hours!$A$5 -> Distribution Switchboard Multi Cover (Per Section) | D5: =MAX(E5+F5,G5,H5,I5,J5,K5,L5,M5,N5,O5,P5,Q5) -> 0 | R5: =IF(SUMPRODUCT((E5:Q5)*1)=0,0,E5*INDEX(Hours!M:M,MATCH(C5,Hours!$A:$A,0))+F5*INDEX(Hours!B:B,MATCH(C5,Hours!$A:$A,0))+G5*INDEX(Hours!C:C,MATCH(C5,Hours!$A:$A,0))+H5*INDEX(Hours!D:D,MATCH(C5,Hours!$A:$A,0))+I5*INDEX(Hours!E:E,MATCH(C5,Hours!$A:$A,0))+J5*INDEX(Hours!F:F,MATCH(C5,Hours!$A:$A,0))+K5*INDEX(Hours!G:G,MATCH(C5,Hours!$A:$A,0))+O5*INDEX(Hours!K:K,MATCH(C5,Hours!$A:$A,0))) -> 0 | S5: =MAX(E5+F5,G5,H5,I5,J5,K5,L5,M5,N5,O5,P5,Q5) -> 0
A6: ='Bldgs & Rooms'!$A$2 -> Main Bldg. | B6: ='Bldgs & Rooms'!$B$2 -> 0 | C6: =Hours!$A$6 -> Switchboard Disconnects | D6: =MAX(E6+F6,G6,H6,I6,J6,K6,L6,M6,N6,O6,P6,Q6) -> 0 | R6: =IF(SUMPRODUCT((E6:Q6)*1)=0,0,E6*INDEX(Hours!M:M,MATCH(C6,Hours!$A:$A,0))+F6*INDEX(Hours!B:B,MATCH(C6,Hours!$A:$A,0))+G6*INDEX(Hours!C:C,MATCH(C6,Hours!$A:$A,0))+H6*INDEX(Hours!D:D,MATCH(C6,Hours!$A:$A,0))+I6*INDEX(Hours!E:E,MATCH(C6,Hours!$A:$A,0))+J6*INDEX(Hours!F:F,MATCH(C6,Hours!$A:$A,0))) -> 0 | S6: =MAX(E6+F6,G6,H6,I6,J6,K6,L6,M6,N6,O6,P6,Q6) -> 0
A7: ='Bldgs & Rooms'!$A$2 -> Main Bldg. | B7: ='Bldgs & Rooms'!$B$2 -> 0 | C7: =Hours!$A$7 -> Switchboard Molded Case Breakers | D7: =MAX(E7+F7,G7,H7,I7,J7,K7,L7,M7,N7,O7,P7,Q7) -> 0 | R7: =IF(SUMPRODUCT((E7:Q7)*1)=0,0,E7*INDEX(Hours!M:M,MATCH(C7,Hours!$A:$A,0))+F7*INDEX(Hours!B:B,MATCH(C7,Hours!$A:$A,0))+G7*INDEX(Hours!C:C,MATCH(C7,Hours!$A:$A,0))+H7*INDEX(Hours!D:D,MATCH(C7,Hours!$A:$A,0))+I7*INDEX(Hours!E:E,MATCH(C7,Hours!$A:$A,0))+J7*INDEX(Hours!F:F,MATCH(C7,Hours!$A:$A,0))+K7*INDEX(Hours!G:G,MATCH(C7,Hours!$A:$A,0))) -> 0 | S7: =MAX(E7+F7,G7,H7,I7,J7,K7,L7,M7,N7,O7,P7,Q7) -> 0
A8: ='Bldgs & Rooms'!$A$2 -> Main Bldg. | B8: ='Bldgs & Rooms'!$B$2 -> 0 | C8: =Hours!$A$8 -> Panelboard-Single Cover > 400A (Distribution Panel) | D8: =MAX(E8+F8,G8,H8,I8,J8,K8,L8,M8,N8,O8,P8,Q8) -> 0 | R8: =IF(SUMPRODUCT((E8:Q8)*1)=0,0,E8*INDEX(Hours!M:M,MATCH(C8,Hours!$A:$A,0))+F8*INDEX(Hours!B:B,MATCH(C8,Hours!$A:$A,0))+G8*INDEX(Hours!C:C,MATCH(C8,Hours!$A:$A,0))+H8*INDEX(Hours!D:D,MATCH(C8,Hours!$A:$A,0))+I8*INDEX(Hours!E:E,MATCH(C8,Hours!$A:$A,0))+J8*INDEX(Hours!F:F,MATCH(C8,Hours!$A:$A,0))+K8*INDEX(Hours!G:G,MATCH(C8,Hours!$A:$A,0))+O8*INDEX(Hours!K:K,MATCH(C8,Hours!$A:$A,0))) -> 0 | S8: =MAX(E8+F8,G8,H8,I8,J8,K8,L8,M8,N8,O8,P8,Q8) -> 0
A9: ='Bldgs & Rooms'!$A$2 -> Main Bldg. | B9: ='Bldgs & Rooms'!$B$2 -> 0 | C9: =Hours!$A$9 -> Panelboard-Single Cover < 400A (Branch Ckt Panel) | D9: =MAX(E9+F9,G9,H9,I9,J9,K9,L9,M9,N9,O9,P9,Q9) -> 0 | R9: =IF(SUMPRODUCT((E9:Q9)*1)=0,0,E9*INDEX(Hours!M:M,MATCH(C9,Hours!$A:$A,0))+F9*INDEX(Hours!B:B,MATCH(C9,Hours!$A:$A,0))+G9*INDEX(Hours!C:C,MATCH(C9,Hours!$A:$A,0))+H9*INDEX(Hours!D:D,MATCH(C9,Hours!$A:$A,0))+I9*INDEX(Hours!E:E,MATCH(C9,Hours!$A:$A,0))+J9*INDEX(Hours!F:F,MATCH(C9,Hours!$A:$A,0))+O9*INDEX(Hours!K:K,MATCH(C9,Hours!$A:$A,0))) -> 0 | S9: =MAX(E9+F9,G9,H9,I9,J9,K9,L9,M9,N9,O9,P9,Q9) -> 0
A10: ='Bldgs & Rooms'!$A$2 -> Main Bldg. | B10: ='Bldgs & Rooms'!$B$2 -> 0 | C10: =Hours!$A$10 -> Motor Control Center (MCC-Per Vertical Section) | D10: =MAX(E10+F10,G10,H10,I10,J10,K10,L10,M10,N10,O10,P10,Q10) -> 0 | R10: =IF(SUMPRODUCT((E10:Q10)*1)=0,0,E10*INDEX(Hours!M:M,MATCH(C10,Hours!$A:$A,0))+F10*INDEX(Hours!B:B,MATCH(C10,Hours!$A:$A,0))+G10*INDEX(Hours!C:C,MATCH(C10,Hours!$A:$A,0))+H10*INDEX(Hours!D:D,MATCH(C10,Hours!$A:$A,0))+I10*INDEX(Hours!E:E,MATCH(C10,Hours!$A:$A,0))+J10*INDEX(Hours!F:F,MATCH(C10,Hours!$A:$A,0))+O10*INDEX(Hours!K:K,MATCH(C10,Hours!$A:$A,0))) -> 0 | S10: =MAX(E10+F10,G10,H10,I10,J10,K10,L10,M10,N10,O10,P10,Q10) -> 0
A11: ='Bldgs & Rooms'!$A$2 -> Main Bldg. | B11: ='Bldgs & Rooms'!$B$2 -> 0 | C11: =Hours!$A$11 -> MCC: Combination Motor Starters | D11: =MAX(E11+F11,G11,H11,I11,J11,K11,L11,M11,N11,O11,P11,Q11) -> 0 | R11: =IF(SUMPRODUCT((E11:Q11)*1)=0,0,E11*INDEX(Hours!M:M,MATCH(C11,Hours!$A:$A,0))+F11*INDEX(Hours!B:B,MATCH(C11,Hours!$A:$A,0))+G11*INDEX(Hours!C:C,MATCH(C11,Hours!$A:$A,0))+H11*INDEX(Hours!D:D,MATCH(C11,Hours!$A:$A,0))+I11*INDEX(Hours!E:E,MATCH(C11,Hours!$A:$A,0))+J11*INDEX(Hours!F:F,MATCH(C11,Hours!$A:$A,0))+K11*INDEX(Hours!G:G,MATCH(C11,Hours!$A:$A,0))+O11*INDEX(Hours!K:K,MATCH(C11,Hours!$A:$A,0))) -> 0 | S11: =MAX(E11+F11,G11,H11,I11,J11,K11,L11,M11,N11,O11,P11,Q11) -> 0
A12: ='Bldgs & Rooms'!$A$2 -> Main Bldg. | B12: ='Bldgs & Rooms'!$B$2 -> 0 | C12: =Hours!$A$12 -> MCC: Molded Case Breaker | D12: =MAX(E12+F12,G12,H12,I12,J12,K12,L12,M12,N12,O12,P12,Q12) -> 0 | R12: =IF(SUMPRODUCT((E12:Q12)*1)=0,0,E12*INDEX(Hours!M:M,MATCH(C12,Hours!$A:$A,0))+F12*INDEX(Hours!B:B,MATCH(C12,Hours!$A:$A,0))+G12*INDEX(Hours!C:C,MATCH(C12,Hours!$A:$A,0))+H12*INDEX(Hours!D:D,MATCH(C12,Hours!$A:$A,0))+I12*INDEX(Hours!E:E,MATCH(C12,Hours!$A:$A,0))+J12*INDEX(Hours!F:F,MATCH(C12,Hours!$A:$A,0))+K12*INDEX(Hours!G:G,MATCH(C12,Hours!$A:$A,0))) -> 0 | S12: =MAX(E12+F12,G12,H12,I12,J12,K12,L12,M12,N12,O12,P12,Q12) -> 0
A13: ='Bldgs & Rooms'!$A$2 -> Main Bldg. | B13: ='Bldgs & Rooms'!$B$2 -> 0 | C13: =Hours!$A$13 -> MCC: Individual Disconnect Switch | D13: =MAX(E13+F13,G13,H13,I13,J13,K13,L13,M13,N13,O13,P13,Q13) -> 0 | R13: =IF(SUMPRODUCT((E13:Q13)*1)=0,0,E13*INDEX(Hours!M:M,MATCH(C13,Hours!$A:$A,0))+F13*INDEX(Hours!B:B,MATCH(C13,Hours!$A:$A,0))+G13*INDEX(Hours!C:C,MATCH(C13,Hours!$A:$A,0))+H13*INDEX(Hours!D:D,MATCH(C13,Hours!$A:$A,0))+I13*INDEX(Hours!E:E,MATCH(C13,Hours!$A:$A,0))+J13*INDEX(Hours!F:F,MATCH(C13,Hours!$A:$A,0))) -> 0 | S13: =MAX(E13+F13,G13,H13,I13,J13,K13,L13,M13,N13,O13,P13,Q13) -> 0
A14: ='Bldgs & Rooms'!$A$2 -> Main Bldg. | B14: ='Bldgs & Rooms'!$B$2 -> 0 | C14: =Hours!$A$14 -> Motor Control Panel (MCP) | D14: =MAX(E14+F14,G14,H14,I14,J14,K14,L14,M14,N14,O14,P14,Q14) -> 0 | R14: =IF(SUMPRODUCT((E14:Q14)*1)=0,0,E14*INDEX(Hours!M:M,MATCH(C14,Hours!$A:$A,0))+F14*INDEX(Hours!B:B,MATCH(C14,Hours!$A:$A,0))+G14*INDEX(Hours!C:C,MATCH(C14,Hours!$A:$A,0))+H14*INDEX(Hours!D:D,MATCH(C14,Hours!$A:$A,0))+I14*INDEX(Hours!E:E,MATCH(C14,Hours!$A:$A,0))+J14*INDEX(Hours!F:F,MATCH(C14,Hours!$A:$A,0))+O14*INDEX(Hours!K:K,MATCH(C14,Hours!$A:$A,0))) -> 0 | S14: =MAX(E14+F14,G14,H14,I14,J14,K14,L14,M14,N14,O14,P14,Q14) -> 0
A15: ='Bldgs & Rooms'!$A$2 -> Main Bldg. | B15: ='Bldgs & Rooms'!$B$2 -> 0 | C15: =Hours!$A$15 -> VFD Motor Control Panel (VFD-MCP) | D15: =MAX(E15+F15,G15,H15,I15,J15,K15,L15,M15,N15,O15,P15,Q15) -> 0 | R15: =IF(SUMPRODUCT((E15:Q15)*1)=0,0,E15*INDEX(Hours!M:M,MATCH(C15,Hours!$A:$A,0))+F15*INDEX(Hours!B:B,MATCH(C15,Hours!$A:$A,0))+G15*INDEX(Hours!C:C,MATCH(C15,Hours!$A:$A,0))+H15*INDEX(Hours!D:D,MATCH(C15,Hours!$A:$A,0))+I15*INDEX(Hours!E:E,MATCH(C15,Hours!$A:$A,0))+J15*INDEX(Hours!F:F,MATCH(C15,Hours!$A:$A,0))+O15*INDEX(Hours!K:K,MATCH(C15,Hours!$A:$A,0))) -> 0 | S15: =MAX(E15+F15,G15,H15,I15,J15,K15,L15,M15,N15,O15,P15,Q15) -> 0
A16: ='Bldgs & Rooms'!$A$2 -> Main Bldg. | B16: ='Bldgs & Rooms'!$B$2 -> 0 | C16: =Hours!$A$16 -> Individual Disconnect Switch > 100A | D16: =MAX(E16+F16,G16,H16,I16,J16,K16,L16,M16,N16,O16,P16,Q16) -> 0 | R16: =IF(SUMPRODUCT((E16:Q16)*1)=0,0,E16*INDEX(Hours!M:M,MATCH(C16,Hours!$A:$A,0))+F16*INDEX(Hours!B:B,MATCH(C16,Hours!$A:$A,0))+G16*INDEX(Hours!C:C,MATCH(C16,Hours!$A:$A,0))+H16*INDEX(Hours!D:D,MATCH(C16,Hours!$A:$A,0))+I16*INDEX(Hours!E:E,MATCH(C16,Hours!$A:$A,0))+J16*INDEX(Hours!F:F,MATCH(C16,Hours!$A:$A,0))+K16*INDEX(Hours!G:G,MATCH(C16,Hours!$A:$A,0))) -> 0 | S16: =MAX(E16+F16,G16,H16,I16,J16,K16,L16,M16,N16,O16,P16,Q16) -> 0
A17: ='Bldgs & Rooms'!$A$2 -> Main Bldg. | B17: ='Bldgs & Rooms'!$B$2 -> 0 | C17: =Hours!$A$17 -> Individual Molded Case Breaker > 100A | D17: =MAX(E17+F17,G17,H17,I17,J17,K17,L17,M17,N17,O17,P17,Q17) -> 0 | R17: =IF(SUMPRODUCT((E17:Q17)*1)=0,0,E17*INDEX(Hours!M:M,MATCH(C17,Hours!$A:$A,0))+F17*INDEX(Hours!B:B,MATCH(C17,Hours!$A:$A,0))+G17*INDEX(Hours!C:C,MATCH(C17,Hours!$A:$A,0))+H17*INDEX(Hours!D:D,MATCH(C17,Hours!$A:$A,0))+I17*INDEX(Hours!E:E,MATCH(C17,Hours!$A:$A,0))+J17*INDEX(Hours!F:F,MATCH(C17,Hours!$A:$A,0))+K17*INDEX(Hours!G:G,MATCH(C17,Hours!$A:$A,0))) -> 0 | S17: =MAX(E17+F17,G17,H17,I17,J17,K17,L17,M17,N17,O17,P17,Q17) -> 0
A18: ='Bldgs & Rooms'!$A$2 -> Main Bldg. | B18: ='Bldgs & Rooms'!$B$2 -> 0 | C18: =Hours!$A$18 -> Individual Combination Motor Starter > 100A | D18: =MAX(E18+F18,G18,H18,I18,J18,K18,L18,M18,N18,O18,P18,Q18) -> 0 | R18: =IF(SUMPRODUCT((E18:Q18)*1)=0,0,E18*INDEX(Hours!M:M,MATCH(C18,Hours!$A:$A,0))+F18*INDEX(Hours!B:B,MATCH(C18,Hours!$A:$A,0))+G18*INDEX(Hours!C:C,MATCH(C18,Hours!$A:$A,0))+H18*INDEX(Hours!D:D,MATCH(C18,Hours!$A:$A,0))+I18*INDEX(Hours!E:E,MATCH(C18,Hours!$A:$A,0))+J18*INDEX(Hours!F:F,MATCH(C18,Hours!$A:$A,0))+K18*INDEX(Hours!G:G,MATCH(C18,Hours!$A:$A,0))) -> 0 | S18: =MAX(E18+F18,G18,H18,I18,J18,K18,L18,M18,N18,O18,P18,Q18) -> 0
A19: ='Bldgs & Rooms'!$A$2 -> Main Bldg. | B19: ='Bldgs & Rooms'!$B$2 -> 0 | C19: =Hours!$A$19 -> Oil Filled Transformer - 5kV-15kV Primary - Any Size (Pad Mounted) | D19: =MAX(E19+F19,G19,H19,I19,J19,K19,L19,M19,N19,O19,P19,Q19) -> 0 | R19: =IF(SUMPRODUCT((E19:Q19)*1)=0,0,E19*INDEX(Hours!M:M,MATCH(C19,Hours!$A:$A,0))+F19*INDEX(Hours!B:B,MATCH(C19,Hours!$A:$A,0))+G19*INDEX(Hours!C:C,MATCH(C19,Hours!$A:$A,0))+H19*INDEX(Hours!D:D,MATCH(C19,Hours!$A:$A,0))+I19*INDEX(Hours!E:E,MATCH(C19,Hours!$A:$A,0))+J19*INDEX(Hours!F:F,MATCH(C19,Hours!$A:$A,0))+M19*INDEX(Hours!I:I,MATCH(C19,Hours!$A:$A,0))+N19*INDEX(Hours!J:J,MATCH(C19,Hours!$A:$A,0))+P19*INDEX(Hours!L:L,MATCH(C19,Hours!$A:$A,0))) -> 0 | S19: =MAX(E19+F19,G19,H19,I19,J19,K19,L19,M19,N19,O19,P19,Q19) -> 0
A20: ='Bldgs & Rooms'!$A$2 -> Main Bldg. | B20: ='Bldgs & Rooms'!$B$2 -> 0 | C20: =Hours!$A$20 -> Oil Filled Transformer - > 15kV Primary (Substation Class) | D20: =MAX(E20+F20,G20,H20,I20,J20,K20,L20,M20,N20,O20,P20,Q20) -> 0 | R20: =IF(SUMPRODUCT((E20:Q20)*1)=0,0,E20*INDEX(Hours!M:M,MATCH(C20,Hours!$A:$A,0))+F20*INDEX(Hours!B:B,MATCH(C20,Hours!$A:$A,0))+G20*INDEX(Hours!C:C,MATCH(C20,Hours!$A:$A,0))+H20*INDEX(Hours!D:D,MATCH(C20,Hours!$A:$A,0))+I20*INDEX(Hours!E:E,MATCH(C20,Hours!$A:$A,0))+J20*INDEX(Hours!F:F,MATCH(C20,Hours!$A:$A,0))+M20*INDEX(Hours!I:I,MATCH(C20,Hours!$A:$A,0))+N20*INDEX(Hours!J:J,MATCH(C20,Hours!$A:$A,0))+P20*INDEX(Hours!L:L,MATCH(C20,Hours!$A:$A,0))) -> 0 | S20: =MAX(E20+F20,G20,H20,I20,J20,K20,L20,M20,N20,O20,P20,Q20) -> 0
A21: ='Bldgs & Rooms'!$A$2 -> Main Bldg. | B21: ='Bldgs & Rooms'!$B$2 -> 0 | C21: =Hours!$A$21 -> Dry Type Transformer - < 480V Primary - Any Size kVA | D21: =MAX(E21+F21,G21,H21,I21,J21,K21,L21,M21,N21,O21,P21,Q21) -> 0 | R21: =IF(SUMPRODUCT((E21:Q21)*1)=0,0,E21*INDEX(Hours!M:M,MATCH(C21,Hours!$A:$A,0))+F21*INDEX(Hours!B:B,MATCH(C21,Hours!$A:$A,0))+G21*INDEX(Hours!C:C,MATCH(C21,Hours!$A:$A,0))+H21*INDEX(Hours!D:D,MATCH(C21,Hours!$A:$A,0))+I21*INDEX(Hours!E:E,MATCH(C21,Hours!$A:$A,0))+J21*INDEX(Hours!F:F,MATCH(C21,Hours!$A:$A,0))+M21*INDEX(Hours!I:I,MATCH(C21,Hours!$A:$A,0))+N21*INDEX(Hours!J:J,MATCH(C21,Hours!$A:$A,0))) -> 0 | S21: =MAX(E21+F21,G21,H21,I21,J21,K21,L21,M21,N21,O21,P21,Q21) -> 0
A22: ='Bldgs & Rooms'!$A$2 -> Main Bldg. | B22: ='Bldgs & Rooms'!$B$2 -> 0 | C22: =Hours!$A$22 -> Power Factor Correction Capacitors | D22: =MAX(E22+F22,G22,H22,I22,J22,K22,L22,M22,N22,O22,P22,Q22) -> 0 | R22: =IF(SUMPRODUCT((E22:Q22)*1)=0,0,E22*INDEX(Hours!M:M,MATCH(C22,Hours!$A:$A,0))+F22*INDEX(Hours!B:B,MATCH(C22,Hours!$A:$A,0))+G22*INDEX(Hours!C:C,MATCH(C22,Hours!$A:$A,0))+H22*INDEX(Hours!D:D,MATCH(C22,Hours!$A:$A,0))+I22*INDEX(Hours!E:E,MATCH(C22,Hours!$A:$A,0))+J22*INDEX(Hours!F:F,MATCH(C22,Hours!$A:$A,0))) -> 0 | S22: =MAX(E22+F22,G22,H22,I22,J22,K22,L22,M22,N22,O22,P22,Q22) -> 0
A23: ='Bldgs & Rooms'!$A$2 -> Main Bldg. | B23: ='Bldgs & Rooms'!$B$2 -> 0 | C23: =Hours!$A$23 -> Lighting Contactor > 100A | D23: =MAX(E23+F23,G23,H23,I23,J23,K23,L23,M23,N23,O23,P23,Q23) -> 0 | R23: =IF(SUMPRODUCT((E23:Q23)*1)=0,0,E23*INDEX(Hours!M:M,MATCH(C23,Hours!$A:$A,0))+F23*INDEX(Hours!B:B,MATCH(C23,Hours!$A:$A,0))+G23*INDEX(Hours!C:C,MATCH(C23,Hours!$A:$A,0))+H23*INDEX(Hours!D:D,MATCH(C23,Hours!$A:$A,0))+I23*INDEX(Hours!E:E,MATCH(C23,Hours!$A:$A,0))+J23*INDEX(Hours!F:F,MATCH(C23,Hours!$A:$A,0))) -> 0 | S23: =MAX(E23+F23,G23,H23,I23,J23,K23,L23,M23,N23,O23,P23,Q23) -> 0
A24: ='Bldgs & Rooms'!$A$2 -> Main Bldg. | B24: ='Bldgs & Rooms'!$B$2 -> 0 | C24: =Hours!$A$24 -> Power Distribution Unit (PDU) | D24: =MAX(E24+F24,G24,H24,I24,J24,K24,L24,M24,N24,O24,P24,Q24) -> 0 | R24: =IF(SUMPRODUCT((E24:Q24)*1)=0,0,E24*INDEX(Hours!M:M,MATCH(C24,Hours!$A:$A,0))+F24*INDEX(Hours!B:B,MATCH(C24,Hours!$A:$A,0))+G24*INDEX(Hours!C:C,MATCH(C24,Hours!$A:$A,0))+H24*INDEX(Hours!D:D,MATCH(C24,Hours!$A:$A,0))+I24*INDEX(Hours!E:E,MATCH(C24,Hours!$A:$A,0))+J24*INDEX(Hours!F:F,MATCH(C24,Hours!$A:$A,0))) -> 0 | S24: =MAX(E24+F24,G24,H24,I24,J24,K24,L24,M24,N24,O24,P24,Q24) -> 0
A25: ='Bldgs & Rooms'!$A$2 -> Main Bldg. | B25: ='Bldgs & Rooms'!$B$2 -> 0 | C25: =Hours!$A$25 -> Wire Trough, Gutter, or Large Junction Boxes | D25: =MAX(E25+F25,G25,H25,I25,J25,K25,L25,M25,N25,O25,P25,Q25) -> 0 | R25: =IF(SUMPRODUCT((E25:Q25)*1)=0,0,E25*INDEX(Hours!M:M,MATCH(C25,Hours!$A:$A,0))+F25*INDEX(Hours!B:B,MATCH(C25,Hours!$A:$A,0))+G25*INDEX(Hours!C:C,MATCH(C25,Hours!$A:$A,0))+H25*INDEX(Hours!D:D,MATCH(C25,Hours!$A:$A,0))+I25*INDEX(Hours!E:E,MATCH(C25,Hours!$A:$A,0))+J25*INDEX(Hours!F:F,MATCH(C25,Hours!$A:$A,0))) -> 0 | S25: =MAX(E25+F25,G25,H25,I25,J25,K25,L25,M25,N25,O25,P25,Q25) -> 0
A26: ='Bldgs & Rooms'!$A$2 -> Main Bldg. | B26: ='Bldgs & Rooms'!$B$2 -> 0 | C26: =Hours!$A$26 -> Bus Duct - Vertical or Horizontal (Per 10' section) | D26: =MAX(E26+F26,G26,H26,I26,J26,K26,L26,M26,N26,O26,P26,Q26) -> 0 | R26: =IF(SUMPRODUCT((E26:Q26)*1)=0,0,E26*INDEX(Hours!M:M,MATCH(C26,Hours!$A:$A,0))+F26*INDEX(Hours!B:B,MATCH(C26,Hours!$A:$A,0))+G26*INDEX(Hours!C:C,MATCH(C26,Hours!$A:$A,0))+H26*INDEX(Hours!D:D,MATCH(C26,Hours!$A:$A,0))+I26*INDEX(Hours!E:E,MATCH(C26,Hours!$A:$A,0))+J26*INDEX(Hours!F:F,MATCH(C26,Hours!$A:$A,0))) -> 0 | S26: =MAX(E26+F26,G26,H26,I26,J26,K26,L26,M26,N26,O26,P26,Q26) -> 0
A27: ='Bldgs & Rooms'!$A$2 -> Main Bldg. | B27: ='Bldgs & Rooms'!$B$2 -> 0 | C27: =Hours!$A$27 -> Automatic Transfer Switch (ATS) > 100A | D27: =MAX(E27+F27,G27,H27,I27,J27,K27,L27,M27,N27,O27,P27,Q27) -> 0 | R27: =IF(SUMPRODUCT((E27:Q27)*1)=0,0,E27*INDEX(Hours!M:M,MATCH(C27,Hours!$A:$A,0))+F27*INDEX(Hours!B:B,MATCH(C27,Hours!$A:$A,0))+G27*INDEX(Hours!C:C,MATCH(C27,Hours!$A:$A,0))+H27*INDEX(Hours!D:D,MATCH(C27,Hours!$A:$A,0))+I27*INDEX(Hours!E:E,MATCH(C27,Hours!$A:$A,0))+J27*INDEX(Hours!F:F,MATCH(C27,Hours!$A:$A,0))) -> 0 | S27: =MAX(E27+F27,G27,H27,I27,J27,K27,L27,M27,N27,O27,P27,Q27) -> 0
A28: ='Bldgs & Rooms'!$A$2 -> Main Bldg. | B28: ='Bldgs & Rooms'!$B$2 -> 0 | C28: =Hours!$A$28 -> Manual Transfer Switch (MTS) > 100A | D28: =MAX(E28+F28,G28,H28,I28,J28,K28,L28,M28,N28,O28,P28,Q28) -> 0 | R28: =IF(SUMPRODUCT((E28:Q28)*1)=0,0,E28*INDEX(Hours!M:M,MATCH(C28,Hours!$A:$A,0))+F28*INDEX(Hours!B:B,MATCH(C28,Hours!$A:$A,0))+G28*INDEX(Hours!C:C,MATCH(C28,Hours!$A:$A,0))+H28*INDEX(Hours!D:D,MATCH(C28,Hours!$A:$A,0))+I28*INDEX(Hours!E:E,MATCH(C28,Hours!$A:$A,0))+J28*INDEX(Hours!F:F,MATCH(C28,Hours!$A:$A,0))) -> 0 | S28: =MAX(E28+F28,G28,H28,I28,J28,K28,L28,M28,N28,O28,P28,Q28) -> 0
A29: ='Bldgs & Rooms'!$A$2 -> Main Bldg. | B29: ='Bldgs & Rooms'!$B$2 -> 0 | C29: =Hours!$A$29 -> Variable Frequency Drives (VFD) < 50 HP | D29: =MAX(E29+F29,G29,H29,I29,J29,K29,L29,M29,N29,O29,P29,Q29) -> 0 | R29: =IF(SUMPRODUCT((E29:Q29)*1)=0,0,E29*INDEX(Hours!M:M,MATCH(C29,Hours!$A:$A,0))+F29*INDEX(Hours!B:B,MATCH(C29,Hours!$A:$A,0))+G29*INDEX(Hours!C:C,MATCH(C29,Hours!$A:$A,0))+H29*INDEX(Hours!D:D,MATCH(C29,Hours!$A:$A,0))+I29*INDEX(Hours!E:E,MATCH(C29,Hours!$A:$A,0))+J29*INDEX(Hours!F:F,MATCH(C29,Hours!$A:$A,0))) -> 0 | S29: =MAX(E29+F29,G29,H29,I29,J29,K29,L29,M29,N29,O29,P29,Q29) -> 0
A30: ='Bldgs & Rooms'!$A$2 -> Main Bldg. | B30: ='Bldgs & Rooms'!$B$2 -> 0 | C30: =Hours!$A$30 -> Variable Frequency Drives (VFD) 51-200 HP | D30: =MAX(E30+F30,G30,H30,I30,J30,K30,L30,M30,N30,O30,P30,Q30) -> 0 | R30: =IF(SUMPRODUCT((E30:Q30)*1)=0,0,E30*INDEX(Hours!M:M,MATCH(C30,Hours!$A:$A,0))+F30*INDEX(Hours!B:B,MATCH(C30,Hours!$A:$A,0))+G30*INDEX(Hours!C:C,MATCH(C30,Hours!$A:$A,0))+H30*INDEX(Hours!D:D,MATCH(C30,Hours!$A:$A,0))+I30*INDEX(Hours!E:E,MATCH(C30,Hours!$A:$A,0))+J30*INDEX(Hours!F:F,MATCH(C30,Hours!$A:$A,0))) -> 0 | S30: =MAX(E30+F30,G30,H30,I30,J30,K30,L30,M30,N30,O30,P30,Q30) -> 0
A31: ='Bldgs & Rooms'!$A$2 -> Main Bldg. | B31: ='Bldgs & Rooms'!$B$2 -> 0 | C31: =Hours!$A$31 -> Motors < 50 HP | D31: =MAX(E31+F31,G31,H31,I31,J31,K31,L31,M31,N31,O31,P31,Q31) -> 0 | R31: =IF(SUMPRODUCT((E31:Q31)*1)=0,0,E31*INDEX(Hours!M:M,MATCH(C31,Hours!$A:$A,0))+F31*INDEX(Hours!B:B,MATCH(C31,Hours!$A:$A,0))+G31*INDEX(Hours!C:C,MATCH(C31,Hours!$A:$A,0))+H31*INDEX(Hours!D:D,MATCH(C31,Hours!$A:$A,0))+I31*INDEX(Hours!E:E,MATCH(C31,Hours!$A:$A,0))+J31*INDEX(Hours!F:F,MATCH(C31,Hours!$A:$A,0))) -> 0 | S31: =MAX(E31+F31,G31,H31,I31,J31,K31,L31,M31,N31,O31,P31,Q31) -> 0
A32: ='Bldgs & Rooms'!$A$2 -> Main Bldg. | B32: ='Bldgs & Rooms'!$B$2 -> 0 | C32: =Hours!$A$32 -> Motors 51-200 HP | D32: =MAX(E32+F32,G32,H32,I32,J32,K32,L32,M32,N32,O32,P32,Q32) -> 0 | R32: =IF(SUMPRODUCT((E32:Q32)*1)=0,0,E32*INDEX(Hours!M:M,MATCH(C32,Hours!$A:$A,0))+F32*INDEX(Hours!B:B,MATCH(C32,Hours!$A:$A,0))+G32*INDEX(Hours!C:C,MATCH(C32,Hours!$A:$A,0))+H32*INDEX(Hours!D:D,MATCH(C32,Hours!$A:$A,0))+I32*INDEX(Hours!E:E,MATCH(C32,Hours!$A:$A,0))+J32*INDEX(Hours!F:F,MATCH(C32,Hours!$A:$A,0))) -> 0 | S32: =MAX(E32+F32,G32,H32,I32,J32,K32,L32,M32,N32,O32,P32,Q32) -> 0
A33: ='Bldgs & Rooms'!$A$2 -> Main Bldg. | B33: ='Bldgs & Rooms'!$B$2 -> 0 | C33: =Hours!$A$33 -> Motors 201-500 HP | D33: =MAX(E33+F33,G33,H33,I33,J33,K33,L33,M33,N33,O33,P33,Q33) -> 0 | R33: =IF(SUMPRODUCT((E33:Q33)*1)=0,0,E33*INDEX(Hours!M:M,MATCH(C33,Hours!$A:$A,0))+F33*INDEX(Hours!B:B,MATCH(C33,Hours!$A:$A,0))+G33*INDEX(Hours!C:C,MATCH(C33,Hours!$A:$A,0))+H33*INDEX(Hours!D:D,MATCH(C33,Hours!$A:$A,0))+I33*INDEX(Hours!E:E,MATCH(C33,Hours!$A:$A,0))+J33*INDEX(Hours!F:F,MATCH(C33,Hours!$A:$A,0))) -> 0 | S33: =MAX(E33+F33,G33,H33,I33,J33,K33,L33,M33,N33,O33,P33,Q33) -> 0
A34: ='Bldgs & Rooms'!$A$2 -> Main Bldg. | B34: ='Bldgs & Rooms'!$B$2 -> 0 | C34: =Hours!$A$34 -> Compressed Air Equipment | D34: =MAX(E34+F34,G34,H34,I34,J34,K34,L34,M34,N34,O34,P34,Q34) -> 0 | R34: =IF(SUMPRODUCT((E34:Q34)*1)=0,0,E34*INDEX(Hours!M:M,MATCH(C34,Hours!$A:$A,0))+F34*INDEX(Hours!B:B,MATCH(C34,Hours!$A:$A,0))+G34*INDEX(Hours!C:C,MATCH(C34,Hours!$A:$A,0))+H34*INDEX(Hours!D:D,MATCH(C34,Hours!$A:$A,0))+I34*INDEX(Hours!E:E,MATCH(C34,Hours!$A:$A,0))+J34*INDEX(Hours!F:F,MATCH(C34,Hours!$A:$A,0))) -> 0 | S34: =MAX(E34+F34,G34,H34,I34,J34,K34,L34,M34,N34,O34,P34,Q34) -> 0
A35: ='Bldgs & Rooms'!$A$2 -> Main Bldg. | B35: ='Bldgs & Rooms'!$B$2 -> 0 | C35: =Hours!$A$35 -> HVAC Equipment (Large) | D35: =MAX(E35+F35,G35,H35,I35,J35,K35,L35,M35,N35,O35,P35,Q35) -> 0 | R35: =IF(SUMPRODUCT((E35:Q35)*1)=0,0,E35*INDEX(Hours!M:M,MATCH(C35,Hours!$A:$A,0))+F35*INDEX(Hours!B:B,MATCH(C35,Hours!$A:$A,0))+G35*INDEX(Hours!C:C,MATCH(C35,Hours!$A:$A,0))+H35*INDEX(Hours!D:D,MATCH(C35,Hours!$A:$A,0))+I35*INDEX(Hours!E:E,MATCH(C35,Hours!$A:$A,0))+J35*INDEX(Hours!F:F,MATCH(C35,Hours!$A:$A,0))) -> 0 | S35: =MAX(E35+F35,G35,H35,I35,J35,K35,L35,M35,N35,O35,P35,Q35) -> 0
A36: ='Bldgs & Rooms'!$A$2 -> Main Bldg. | B36: ='Bldgs & Rooms'!$B$2 -> 0 | C36: =Hours!$A$36 -> HVAC Equipment (Small) | D36: =MAX(E36+F36,G36,H36,I36,J36,K36,L36,M36,N36,O36,P36,Q36) -> 0 | R36: =IF(SUMPRODUCT((E36:Q36)*1)=0,0,E36*INDEX(Hours!M:M,MATCH(C36,Hours!$A:$A,0))+F36*INDEX(Hours!B:B,MATCH(C36,Hours!$A:$A,0))+G36*INDEX(Hours!C:C,MATCH(C36,Hours!$A:$A,0))+H36*INDEX(Hours!D:D,MATCH(C36,Hours!$A:$A,0))+I36*INDEX(Hours!E:E,MATCH(C36,Hours!$A:$A,0))+J36*INDEX(Hours!F:F,MATCH(C36,Hours!$A:$A,0))) -> 0 | S36: =MAX(E36+F36,G36,H36,I36,J36,K36,L36,M36,N36,O36,P36,Q36) -> 0
A37: ='Bldgs & Rooms'!$A$2 -> Main Bldg. | B37: ='Bldgs & Rooms'!$B$2 -> 0 | C37: =Hours!$A$37 -> Uninterruptible Power Supply (UPS) < 50kVA | D37: =MAX(E37+F37,G37,H37,I37,J37,K37,L37,M37,N37,O37,P37,Q37) -> 0 | R37: =IF(SUMPRODUCT((E37:Q37)*1)=0,0,E37*INDEX(Hours!M:M,MATCH(C37,Hours!$A:$A,0))+F37*INDEX(Hours!B:B,MATCH(C37,Hours!$A:$A,0))+G37*INDEX(Hours!C:C,MATCH(C37,Hours!$A:$A,0))+H37*INDEX(Hours!D:D,MATCH(C37,Hours!$A:$A,0))+I37*INDEX(Hours!E:E,MATCH(C37,Hours!$A:$A,0))+J37*INDEX(Hours!F:F,MATCH(C37,Hours!$A:$A,0))) -> 0 | S37: =MAX(E37+F37,G37,H37,I37,J37,K37,L37,M37,N37,O37,P37,Q37) -> 0
A38: ='Bldgs & Rooms'!$A$2 -> Main Bldg. | B38: ='Bldgs & Rooms'!$B$2 -> 0 | C38: =Hours!$A$38 -> Uninterruptible Power Supply (UPS) > 50kVA | D38: =MAX(E38+F38,G38,H38,I38,J38,K38,L38,M38,N38,O38,P38,Q38) -> 0 | R38: =IF(SUMPRODUCT((E38:Q38)*1)=0,0,E38*INDEX(Hours!M:M,MATCH(C38,Hours!$A:$A,0))+F38*INDEX(Hours!B:B,MATCH(C38,Hours!$A:$A,0))+G38*INDEX(Hours!C:C,MATCH(C38,Hours!$A:$A,0))+H38*INDEX(Hours!D:D,MATCH(C38,Hours!$A:$A,0))+I38*INDEX(Hours!E:E,MATCH(C38,Hours!$A:$A,0))+J38*INDEX(Hours!F:F,MATCH(C38,Hours!$A:$A,0))) -> 0 | S38: =MAX(E38+F38,G38,H38,I38,J38,K38,L38,M38,N38,O38,P38,Q38) -> 0
A39: ='Bldgs & Rooms'!$A$3 -> Main Bldg. | B39: ='Bldgs & Rooms'!$B$3 -> 0 | C39: =Hours!$A$2 -> Switchgear - Incoming Main Service (Per Section) | D39: =MAX(E39+F39,G39,H39,I39,J39,K39,L39,M39,N39,O39,P39,Q39) -> 0 | R39: =IF(SUMPRODUCT((E39:Q39)*1)=0,0,E39*INDEX(Hours!M:M,MATCH(C39,Hours!$A:$A,0))+F39*INDEX(Hours!B:B,MATCH(C39,Hours!$A:$A,0))+G39*INDEX(Hours!C:C,MATCH(C39,Hours!$A:$A,0))+H39*INDEX(Hours!D:D,MATCH(C39,Hours!$A:$A,0))+I39*INDEX(Hours!E:E,MATCH(C39,Hours!$A:$A,0))+J39*INDEX(Hours!F:F,MATCH(C39,Hours!$A:$A,0))+K39*INDEX(Hours!G:G,MATCH(C39,Hours!$A:$A,0))+L39*INDEX(Hours!H:H,MATCH(C39,Hours!$A:$A,0))+O39*INDEX(Hours!K:K,MATCH(C39,Hours!$A:$A,0))) -> 0 | S39: =MAX(E39+F39,G39,H39,I39,J39,K39,L39,M39,N39,O39,P39,Q39) -> 0
A40: ='Bldgs & Rooms'!$A$3 -> Main Bldg. | B40: ='Bldgs & Rooms'!$B$3 -> 0 | C40: =Hours!$A$3 -> Switchgear Insulated Case Breakers (Bus Mounted) | D40: =MAX(E40+F40,G40,H40,I40,J40,K40,L40,M40,N40,O40,P40,Q40) -> 0 | R40: =IF(SUMPRODUCT((E40:Q40)*1)=0,0,E40*INDEX(Hours!M:M,MATCH(C40,Hours!$A:$A,0))+F40*INDEX(Hours!B:B,MATCH(C40,Hours!$A:$A,0))+G40*INDEX(Hours!C:C,MATCH(C40,Hours!$A:$A,0))+H40*INDEX(Hours!D:D,MATCH(C40,Hours!$A:$A,0))+I40*INDEX(Hours!E:E,MATCH(C40,Hours!$A:$A,0))+J40*INDEX(Hours!F:F,MATCH(C40,Hours!$A:$A,0))+K40*INDEX(Hours!G:G,MATCH(C40,Hours!$A:$A,0))) -> 0 | S40: =MAX(E40+F40,G40,H40,I40,J40,K40,L40,M40,N40,O40,P40,Q40) -> 0
A41: ='Bldgs & Rooms'!$A$3 -> Main Bldg. | B41: ='Bldgs & Rooms'!$B$3 -> 0 | C41: =Hours!$A$4 -> SwitchGear Drawout Breakers | D41: =MAX(E41+F41,G41,H41,I41,J41,K41,L41,M41,N41,O41,P41,Q41) -> 0 | R41: =IF(SUMPRODUCT((E41:Q41)*1)=0,0,E41*INDEX(Hours!M:M,MATCH(C41,Hours!$A:$A,0))+F41*INDEX(Hours!B:B,MATCH(C41,Hours!$A:$A,0))+G41*INDEX(Hours!C:C,MATCH(C41,Hours!$A:$A,0))+H41*INDEX(Hours!D:D,MATCH(C41,Hours!$A:$A,0))+I41*INDEX(Hours!E:E,MATCH(C41,Hours!$A:$A,0))+J41*INDEX(Hours!F:F,MATCH(C41,Hours!$A:$A,0))+L41*INDEX(Hours!H:H,MATCH(C41,Hours!$A:$A,0))) -> 0 | S41: =MAX(E41+F41,G41,H41,I41,J41,K41,L41,M41,N41,O41,P41,Q41) -> 0
A42: ='Bldgs & Rooms'!$A$3 -> Main Bldg. | B42: ='Bldgs & Rooms'!$B$3 -> 0 | C42: =Hours!$A$5 -> Distribution Switchboard Multi Cover (Per Section) | D42: =MAX(E42+F42,G42,H42,I42,J42,K42,L42,M42,N42,O42,P42,Q42) -> 0 | R42: =IF(SUMPRODUCT((E42:Q42)*1)=0,0,E42*INDEX(Hours!M:M,MATCH(C42,Hours!$A:$A,0))+F42*INDEX(Hours!B:B,MATCH(C42,Hours!$A:$A,0))+G42*INDEX(Hours!C:C,MATCH(C42,Hours!$A:$A,0))+H42*INDEX(Hours!D:D,MATCH(C42,Hours!$A:$A,0))+I42*INDEX(Hours!E:E,MATCH(C42,Hours!$A:$A,0))+J42*INDEX(Hours!F:F,MATCH(C42,Hours!$A:$A,0))+K42*INDEX(Hours!G:G,MATCH(C42,Hours!$A:$A,0))+O42*INDEX(Hours!K:K,MATCH(C42,Hours!$A:$A,0))) -> 0 | S42: =MAX(E42+F42,G42,H42,I42,J42,K42,L42,M42,N42,O42,P42,Q42) -> 0
A43: ='Bldgs & Rooms'!$A$3 -> Main Bldg. | B43: ='Bldgs & Rooms'!$B$3 -> 0 | C43: =Hours!$A$6 -> Switchboard Disconnects | D43: =MAX(E43+F43,G43,H43,I43,J43,K43,L43,M43,N43,O43,P43,Q43) -> 0 | R43: =IF(SUMPRODUCT((E43:Q43)*1)=0,0,E43*INDEX(Hours!M:M,MATCH(C43,Hours!$A:$A,0))+F43*INDEX(Hours!B:B,MATCH(C43,Hours!$A:$A,0))+G43*INDEX(Hours!C:C,MATCH(C43,Hours!$A:$A,0))+H43*INDEX(Hours!D:D,MATCH(C43,Hours!$A:$A,0))+I43*INDEX(Hours!E:E,MATCH(C43,Hours!$A:$A,0))+J43*INDEX(Hours!F:F,MATCH(C43,Hours!$A:$A,0))) -> 0 | S43: =MAX(E43+F43,G43,H43,I43,J43,K43,L43,M43,N43,O43,P43,Q43) -> 0
A44: ='Bldgs & Rooms'!$A$3 -> Main Bldg. | B44: ='Bldgs & Rooms'!$B$3 -> 0 | C44: =Hours!$A$7 -> Switchboard Molded Case Breakers | D44: =MAX(E44+F44,G44,H44,I44,J44,K44,L44,M44,N44,O44,P44,Q44) -> 0 | R44: =IF(SUMPRODUCT((E44:Q44)*1)=0,0,E44*INDEX(Hours!M:M,MATCH(C44,Hours!$A:$A,0))+F44*INDEX(Hours!B:B,MATCH(C44,Hours!$A:$A,0))+G44*INDEX(Hours!C:C,MATCH(C44,Hours!$A:$A,0))+H44*INDEX(Hours!D:D,MATCH(C44,Hours!$A:$A,0))+I44*INDEX(Hours!E:E,MATCH(C44,Hours!$A:$A,0))+J44*INDEX(Hours!F:F,MATCH(C44,Hours!$A:$A,0))+K44*INDEX(Hours!G:G,MATCH(C44,Hours!$A:$A,0))) -> 0 | S44: =MAX(E44+F44,G44,H44,I44,J44,K44,L44,M44,N44,O44,P44,Q44) -> 0
A45: ='Bldgs & Rooms'!$A$3 -> Main Bldg. | B45: ='Bldgs & Rooms'!$B$3 -> 0 | C45: =Hours!$A$8 -> Panelboard-Single Cover > 400A (Distribution Panel) | D45: =MAX(E45+F45,G45,H45,I45,J45,K45,L45,M45,N45,O45,P45,Q45) -> 0 | R45: =IF(SUMPRODUCT((E45:Q45)*1)=0,0,E45*INDEX(Hours!M:M,MATCH(C45,Hours!$A:$A,0))+F45*INDEX(Hours!B:B,MATCH(C45,Hours!$A:$A,0))+G45*INDEX(Hours!C:C,MATCH(C45,Hours!$A:$A,0))+H45*INDEX(Hours!D:D,MATCH(C45,Hours!$A:$A,0))+I45*INDEX(Hours!E:E,MATCH(C45,Hours!$A:$A,0))+J45*INDEX(Hours!F:F,MATCH(C45,Hours!$A:$A,0))+K45*INDEX(Hours!G:G,MATCH(C45,Hours!$A:$A,0))+O45*INDEX(Hours!K:K,MATCH(C45,Hours!$A:$A,0))) -> 0 | S45: =MAX(E45+F45,G45,H45,I45,J45,K45,L45,M45,N45,O45,P45,Q45) -> 0
A46: ='Bldgs & Rooms'!$A$3 -> Main Bldg. | B46: ='Bldgs & Rooms'!$B$3 -> 0 | C46: =Hours!$A$9 -> Panelboard-Single Cover < 400A (Branch Ckt Panel) | D46: =MAX(E46+F46,G46,H46,I46,J46,K46,L46,M46,N46,O46,P46,Q46) -> 0 | R46: =IF(SUMPRODUCT((E46:Q46)*1)=0,0,E46*INDEX(Hours!M:M,MATCH(C46,Hours!$A:$A,0))+F46*INDEX(Hours!B:B,MATCH(C46,Hours!$A:$A,0))+G46*INDEX(Hours!C:C,MATCH(C46,Hours!$A:$A,0))+H46*INDEX(Hours!D:D,MATCH(C46,Hours!$A:$A,0))+I46*INDEX(Hours!E:E,MATCH(C46,Hours!$A:$A,0))+J46*INDEX(Hours!F:F,MATCH(C46,Hours!$A:$A,0))+O46*INDEX(Hours!K:K,MATCH(C46,Hours!$A:$A,0))) -> 0 | S46: =MAX(E46+F46,G46,H46,I46,J46,K46,L46,M46,N46,O46,P46,Q46) -> 0
A47: ='Bldgs & Rooms'!$A$3 -> Main Bldg. | B47: ='Bldgs & Rooms'!$B$3 -> 0 | C47: =Hours!$A$10 -> Motor Control Center (MCC-Per Vertical Section) | D47: =MAX(E47+F47,G47,H47,I47,J47,K47,L47,M47,N47,O47,P47,Q47) -> 0 | R47: =IF(SUMPRODUCT((E47:Q47)*1)=0,0,E47*INDEX(Hours!M:M,MATCH(C47,Hours!$A:$A,0))+F47*INDEX(Hours!B:B,MATCH(C47,Hours!$A:$A,0))+G47*INDEX(Hours!C:C,MATCH(C47,Hours!$A:$A,0))+H47*INDEX(Hours!D:D,MATCH(C47,Hours!$A:$A,0))+I47*INDEX(Hours!E:E,MATCH(C47,Hours!$A:$A,0))+J47*INDEX(Hours!F:F,MATCH(C47,Hours!$A:$A,0))+O47*INDEX(Hours!K:K,MATCH(C47,Hours!$A:$A,0))) -> 0 | S47: =MAX(E47+F47,G47,H47,I47,J47,K47,L47,M47,N47,O47,P47,Q47) -> 0
A48: ='Bldgs & Rooms'!$A$3 -> Main Bldg. | B48: ='Bldgs & Rooms'!$B$3 -> 0 | C48: =Hours!$A$11 -> MCC: Combination Motor Starters | D48: =MAX(E48+F48,G48,H48,I48,J48,K48,L48,M48,N48,O48,P48,Q48) -> 0 | R48: =IF(SUMPRODUCT((E48:Q48)*1)=0,0,E48*INDEX(Hours!M:M,MATCH(C48,Hours!$A:$A,0))+F48*INDEX(Hours!B:B,MATCH(C48,Hours!$A:$A,0))+G48*INDEX(Hours!C:C,MATCH(C48,Hours!$A:$A,0))+H48*INDEX(Hours!D:D,MATCH(C48,Hours!$A:$A,0))+I48*INDEX(Hours!E:E,MATCH(C48,Hours!$A:$A,0))+J48*INDEX(Hours!F:F,MATCH(C48,Hours!$A:$A,0))+K48*INDEX(Hours!G:G,MATCH(C48,Hours!$A:$A,0))+O48*INDEX(Hours!K:K,MATCH(C48,Hours!$A:$A,0))) -> 0 | S48: =MAX(E48+F48,G48,H48,I48,J48,K48,L48,M48,N48,O48,P48,Q48) -> 0
A49: ='Bldgs & Rooms'!$A$3 -> Main Bldg. | B49: ='Bldgs & Rooms'!$B$3 -> 0 | C49: =Hours!$A$12 -> MCC: Molded Case Breaker | D49: =MAX(E49+F49,G49,H49,I49,J49,K49,L49,M49,N49,O49,P49,Q49) -> 0 | R49: =IF(SUMPRODUCT((E49:Q49)*1)=0,0,E49*INDEX(Hours!M:M,MATCH(C49,Hours!$A:$A,0))+F49*INDEX(Hours!B:B,MATCH(C49,Hours!$A:$A,0))+G49*INDEX(Hours!C:C,MATCH(C49,Hours!$A:$A,0))+H49*INDEX(Hours!D:D,MATCH(C49,Hours!$A:$A,0))+I49*INDEX(Hours!E:E,MATCH(C49,Hours!$A:$A,0))+J49*INDEX(Hours!F:F,MATCH(C49,Hours!$A:$A,0))+K49*INDEX(Hours!G:G,MATCH(C49,Hours!$A:$A,0))) -> 0 | S49: =MAX(E49+F49,G49,H49,I49,J49,K49,L49,M49,N49,O49,P49,Q49) -> 0
A50: ='Bldgs & Rooms'!$A$3 -> Main Bldg. | B50: ='Bldgs & Rooms'!$B$3 -> 0 | C50: =Hours!$A$13 -> MCC: Individual Disconnect Switch | D50: =MAX(E50+F50,G50,H50,I50,J50,K50,L50,M50,N50,O50,P50,Q50) -> 0 | R50: =IF(SUMPRODUCT((E50:Q50)*1)=0,0,E50*INDEX(Hours!M:M,MATCH(C50,Hours!$A:$A,0))+F50*INDEX(Hours!B:B,MATCH(C50,Hours!$A:$A,0))+G50*INDEX(Hours!C:C,MATCH(C50,Hours!$A:$A,0))+H50*INDEX(Hours!D:D,MATCH(C50,Hours!$A:$A,0))+I50*INDEX(Hours!E:E,MATCH(C50,Hours!$A:$A,0))+J50*INDEX(Hours!F:F,MATCH(C50,Hours!$A:$A,0))) -> 0 | S50: =MAX(E50+F50,G50,H50,I50,J50,K50,L50,M50,N50,O50,P50,Q50) -> 0
A51: ='Bldgs & Rooms'!$A$3 -> Main Bldg. | B51: ='Bldgs & Rooms'!$B$3 -> 0 | C51: =Hours!$A$14 -> Motor Control Panel (MCP) | D51: =MAX(E51+F51,G51,H51,I51,J51,K51,L51,M51,N51,O51,P51,Q51) -> 0 | R51: =IF(SUMPRODUCT((E51:Q51)*1)=0,0,E51*INDEX(Hours!M:M,MATCH(C51,Hours!$A:$A,0))+F51*INDEX(Hours!B:B,MATCH(C51,Hours!$A:$A,0))+G51*INDEX(Hours!C:C,MATCH(C51,Hours!$A:$A,0))+H51*INDEX(Hours!D:D,MATCH(C51,Hours!$A:$A,0))+I51*INDEX(Hours!E:E,MATCH(C51,Hours!$A:$A,0))+J51*INDEX(Hours!F:F,MATCH(C51,Hours!$A:$A,0))+O51*INDEX(Hours!K:K,MATCH(C51,Hours!$A:$A,0))) -> 0 | S51: =MAX(E51+F51,G51,H51,I51,J51,K51,L51,M51,N51,O51,P51,Q51) -> 0
A52: ='Bldgs & Rooms'!$A$3 -> Main Bldg. | B52: ='Bldgs & Rooms'!$B$3 -> 0 | C52: =Hours!$A$15 -> VFD Motor Control Panel (VFD-MCP) | D52: =MAX(E52+F52,G52,H52,I52,J52,K52,L52,M52,N52,O52,P52,Q52) -> 0 | R52: =IF(SUMPRODUCT((E52:Q52)*1)=0,0,E52*INDEX(Hours!M:M,MATCH(C52,Hours!$A:$A,0))+F52*INDEX(Hours!B:B,MATCH(C52,Hours!$A:$A,0))+G52*INDEX(Hours!C:C,MATCH(C52,Hours!$A:$A,0))+H52*INDEX(Hours!D:D,MATCH(C52,Hours!$A:$A,0))+I52*INDEX(Hours!E:E,MATCH(C52,Hours!$A:$A,0))+J52*INDEX(Hours!F:F,MATCH(C52,Hours!$A:$A,0))+O52*INDEX(Hours!K:K,MATCH(C52,Hours!$A:$A,0))) -> 0 | S52: =MAX(E52+F52,G52,H52,I52,J52,K52,L52,M52,N52,O52,P52,Q52) -> 0
A53: ='Bldgs & Rooms'!$A$3 -> Main Bldg. | B53: ='Bldgs & Rooms'!$B$3 -> 0 | C53: =Hours!$A$16 -> Individual Disconnect Switch > 100A | D53: =MAX(E53+F53,G53,H53,I53,J53,K53,L53,M53,N53,O53,P53,Q53) -> 0 | R53: =IF(SUMPRODUCT((E53:Q53)*1)=0,0,E53*INDEX(Hours!M:M,MATCH(C53,Hours!$A:$A,0))+F53*INDEX(Hours!B:B,MATCH(C53,Hours!$A:$A,0))+G53*INDEX(Hours!C:C,MATCH(C53,Hours!$A:$A,0))+H53*INDEX(Hours!D:D,MATCH(C53,Hours!$A:$A,0))+I53*INDEX(Hours!E:E,MATCH(C53,Hours!$A:$A,0))+J53*INDEX(Hours!F:F,MATCH(C53,Hours!$A:$A,0))+K53*INDEX(Hours!G:G,MATCH(C53,Hours!$A:$A,0))) -> 0 | S53: =MAX(E53+F53,G53,H53,I53,J53,K53,L53,M53,N53,O53,P53,Q53) -> 0
A54: ='Bldgs & Rooms'!$A$3 -> Main Bldg. | B54: ='Bldgs & Rooms'!$B$3 -> 0 | C54: =Hours!$A$17 -> Individual Molded Case Breaker > 100A | D54: =MAX(E54+F54,G54,H54,I54,J54,K54,L54,M54,N54,O54,P54,Q54) -> 0 | R54: =IF(SUMPRODUCT((E54:Q54)*1)=0,0,E54*INDEX(Hours!M:M,MATCH(C54,Hours!$A:$A,0))+F54*INDEX(Hours!B:B,MATCH(C54,Hours!$A:$A,0))+G54*INDEX(Hours!C:C,MATCH(C54,Hours!$A:$A,0))+H54*INDEX(Hours!D:D,MATCH(C54,Hours!$A:$A,0))+I54*INDEX(Hours!E:E,MATCH(C54,Hours!$A:$A,0))+J54*INDEX(Hours!F:F,MATCH(C54,Hours!$A:$A,0))+K54*INDEX(Hours!G:G,MATCH(C54,Hours!$A:$A,0))) -> 0 | S54: =MAX(E54+F54,G54,H54,I54,J54,K54,L54,M54,N54,O54,P54,Q54) -> 0
A55: ='Bldgs & Rooms'!$A$3 -> Main Bldg. | B55: ='Bldgs & Rooms'!$B$3 -> 0 | C55: =Hours!$A$18 -> Individual Combination Motor Starter > 100A | D55: =MAX(E55+F55,G55,H55,I55,J55,K55,L55,M55,N55,O55,P55,Q55) -> 0 | R55: =IF(SUMPRODUCT((E55:Q55)*1)=0,0,E55*INDEX(Hours!M:M,MATCH(C55,Hours!$A:$A,0))+F55*INDEX(Hours!B:B,MATCH(C55,Hours!$A:$A,0))+G55*INDEX(Hours!C:C,MATCH(C55,Hours!$A:$A,0))+H55*INDEX(Hours!D:D,MATCH(C55,Hours!$A:$A,0))+I55*INDEX(Hours!E:E,MATCH(C55,Hours!$A:$A,0))+J55*INDEX(Hours!F:F,MATCH(C55,Hours!$A:$A,0))+K55*INDEX(Hours!G:G,MATCH(C55,Hours!$A:$A,0))) -> 0 | S55: =MAX(E55+F55,G55,H55,I55,J55,K55,L55,M55,N55,O55,P55,Q55) -> 0
A56: ='Bldgs & Rooms'!$A$3 -> Main Bldg. | B56: ='Bldgs & Rooms'!$B$3 -> 0 | C56: =Hours!$A$19 -> Oil Filled Transformer - 5kV-15kV Primary - Any Size (Pad Mounted) | D56: =MAX(E56+F56,G56,H56,I56,J56,K56,L56,M56,N56,O56,P56,Q56) -> 0 | R56: =IF(SUMPRODUCT((E56:Q56)*1)=0,0,E56*INDEX(Hours!M:M,MATCH(C56,Hours!$A:$A,0))+F56*INDEX(Hours!B:B,MATCH(C56,Hours!$A:$A,0))+G56*INDEX(Hours!C:C,MATCH(C56,Hours!$A:$A,0))+H56*INDEX(Hours!D:D,MATCH(C56,Hours!$A:$A,0))+I56*INDEX(Hours!E:E,MATCH(C56,Hours!$A:$A,0))+J56*INDEX(Hours!F:F,MATCH(C56,Hours!$A:$A,0))+M56*INDEX(Hours!I:I,MATCH(C56,Hours!$A:$A,0))+N56*INDEX(Hours!J:J,MATCH(C56,Hours!$A:$A,0))+P56*INDEX(Hours!L:L,MATCH(C56,Hours!$A:$A,0))) -> 0 | S56: =MAX(E56+F56,G56,H56,I56,J56,K56,L56,M56,N56,O56,P56,Q56) -> 0
A57: ='Bldgs & Rooms'!$A$3 -> Main Bldg. | B57: ='Bldgs & Rooms'!$B$3 -> 0 | C57: =Hours!$A$20 -> Oil Filled Transformer - > 15kV Primary (Substation Class) | D57: =MAX(E57+F57,G57,H57,I57,J57,K57,L57,M57,N57,O57,P57,Q57) -> 0 | R57: =IF(SUMPRODUCT((E57:Q57)*1)=0,0,E57*INDEX(Hours!M:M,MATCH(C57,Hours!$A:$A,0))+F57*INDEX(Hours!B:B,MATCH(C57,Hours!$A:$A,0))+G57*INDEX(Hours!C:C,MATCH(C57,Hours!$A:$A,0))+H57*INDEX(Hours!D:D,MATCH(C57,Hours!$A:$A,0))+I57*INDEX(Hours!E:E,MATCH(C57,Hours!$A:$A,0))+J57*INDEX(Hours!F:F,MATCH(C57,Hours!$A:$A,0))+M57*INDEX(Hours!I:I,MATCH(C57,Hours!$A:$A,0))+N57*INDEX(Hours!J:J,MATCH(C57,Hours!$A:$A,0))+P57*INDEX(Hours!L:L,MATCH(C57,Hours!$A:$A,0))) -> 0 | S57: =MAX(E57+F57,G57,H57,I57,J57,K57,L57,M57,N57,O57,P57,Q57) -> 0
A58: ='Bldgs & Rooms'!$A$3 -> Main Bldg. | B58: ='Bldgs & Rooms'!$B$3 -> 0 | C58: =Hours!$A$21 -> Dry Type Transformer - < 480V Primary - Any Size kVA | D58: =MAX(E58+F58,G58,H58,I58,J58,K58,L58,M58,N58,O58,P58,Q58) -> 0 | R58: =IF(SUMPRODUCT((E58:Q58)*1)=0,0,E58*INDEX(Hours!M:M,MATCH(C58,Hours!$A:$A,0))+F58*INDEX(Hours!B:B,MATCH(C58,Hours!$A:$A,0))+G58*INDEX(Hours!C:C,MATCH(C58,Hours!$A:$A,0))+H58*INDEX(Hours!D:D,MATCH(C58,Hours!$A:$A,0))+I58*INDEX(Hours!E:E,MATCH(C58,Hours!$A:$A,0))+J58*INDEX(Hours!F:F,MATCH(C58,Hours!$A:$A,0))+M58*INDEX(Hours!I:I,MATCH(C58,Hours!$A:$A,0))+N58*INDEX(Hours!J:J,MATCH(C58,Hours!$A:$A,0))) -> 0 | S58: =MAX(E58+F58,G58,H58,I58,J58,K58,L58,M58,N58,O58,P58,Q58) -> 0
A59: ='Bldgs & Rooms'!$A$3 -> Main Bldg. | B59: ='Bldgs & Rooms'!$B$3 -> 0 | C59: =Hours!$A$22 -> Power Factor Correction Capacitors | D59: =MAX(E59+F59,G59,H59,I59,J59,K59,L59,M59,N59,O59,P59,Q59) -> 0 | R59: =IF(SUMPRODUCT((E59:Q59)*1)=0,0,E59*INDEX(Hours!M:M,MATCH(C59,Hours!$A:$A,0))+F59*INDEX(Hours!B:B,MATCH(C59,Hours!$A:$A,0))+G59*INDEX(Hours!C:C,MATCH(C59,Hours!$A:$A,0))+H59*INDEX(Hours!D:D,MATCH(C59,Hours!$A:$A,0))+I59*INDEX(Hours!E:E,MATCH(C59,Hours!$A:$A,0))+J59*INDEX(Hours!F:F,MATCH(C59,Hours!$A:$A,0))) -> 0 | S59: =MAX(E59+F59,G59,H59,I59,J59,K59,L59,M59,N59,O59,P59,Q59) -> 0
A60: ='Bldgs & Rooms'!$A$3 -> Main Bldg. | B60: ='Bldgs & Rooms'!$B$3 -> 0 | C60: =Hours!$A$23 -> Lighting Contactor > 100A | D60: =MAX(E60+F60,G60,H60,I60,J60,K60,L60,M60,N60,O60,P60,Q60) -> 0 | R60: =IF(SUMPRODUCT((E60:Q60)*1)=0,0,E60*INDEX(Hours!M:M,MATCH(C60,Hours!$A:$A,0))+F60*INDEX(Hours!B:B,MATCH(C60,Hours!$A:$A,0))+G60*INDEX(Hours!C:C,MATCH(C60,Hours!$A:$A,0))+H60*INDEX(Hours!D:D,MATCH(C60,Hours!$A:$A,0))+I60*INDEX(Hours!E:E,MATCH(C60,Hours!$A:$A,0))+J60*INDEX(Hours!F:F,MATCH(C60,Hours!$A:$A,0))) -> 0 | S60: =MAX(E60+F60,G60,H60,I60,J60,K60,L60,M60,N60,O60,P60,Q60) -> 0
A61: ='Bldgs & Rooms'!$A$3 -> Main Bldg. | B61: ='Bldgs & Rooms'!$B$3 -> 0 | C61: =Hours!$A$24 -> Power Distribution Unit (PDU) | D61: =MAX(E61+F61,G61,H61,I61,J61,K61,L61,M61,N61,O61,P61,Q61) -> 0 | R61: =IF(SUMPRODUCT((E61:Q61)*1)=0,0,E61*INDEX(Hours!M:M,MATCH(C61,Hours!$A:$A,0))+F61*INDEX(Hours!B:B,MATCH(C61,Hours!$A:$A,0))+G61*INDEX(Hours!C:C,MATCH(C61,Hours!$A:$A,0))+H61*INDEX(Hours!D:D,MATCH(C61,Hours!$A:$A,0))+I61*INDEX(Hours!E:E,MATCH(C61,Hours!$A:$A,0))+J61*INDEX(Hours!F:F,MATCH(C61,Hours!$A:$A,0))) -> 0 | S61: =MAX(E61+F61,G61,H61,I61,J61,K61,L61,M61,N61,O61,P61,Q61) -> 0
A62: ='Bldgs & Rooms'!$A$3 -> Main Bldg. | B62: ='Bldgs & Rooms'!$B$3 -> 0 | C62: =Hours!$A$25 -> Wire Trough, Gutter, or Large Junction Boxes | D62: =MAX(E62+F62,G62,H62,I62,J62,K62,L62,M62,N62,O62,P62,Q62) -> 0 | R62: =IF(SUMPRODUCT((E62:Q62)*1)=0,0,E62*INDEX(Hours!M:M,MATCH(C62,Hours!$A:$A,0))+F62*INDEX(Hours!B:B,MATCH(C62,Hours!$A:$A,0))+G62*INDEX(Hours!C:C,MATCH(C62,Hours!$A:$A,0))+H62*INDEX(Hours!D:D,MATCH(C62,Hours!$A:$A,0))+I62*INDEX(Hours!E:E,MATCH(C62,Hours!$A:$A,0))+J62*INDEX(Hours!F:F,MATCH(C62,Hours!$A:$A,0))) -> 0 | S62: =MAX(E62+F62,G62,H62,I62,J62,K62,L62,M62,N62,O62,P62,Q62) -> 0
A63: ='Bldgs & Rooms'!$A$3 -> Main Bldg. | B63: ='Bldgs & Rooms'!$B$3 -> 0 | C63: =Hours!$A$26 -> Bus Duct - Vertical or Horizontal (Per 10' section) | D63: =MAX(E63+F63,G63,H63,I63,J63,K63,L63,M63,N63,O63,P63,Q63) -> 0 | R63: =IF(SUMPRODUCT((E63:Q63)*1)=0,0,E63*INDEX(Hours!M:M,MATCH(C63,Hours!$A:$A,0))+F63*INDEX(Hours!B:B,MATCH(C63,Hours!$A:$A,0))+G63*INDEX(Hours!C:C,MATCH(C63,Hours!$A:$A,0))+H63*INDEX(Hours!D:D,MATCH(C63,Hours!$A:$A,0))+I63*INDEX(Hours!E:E,MATCH(C63,Hours!$A:$A,0))+J63*INDEX(Hours!F:F,MATCH(C63,Hours!$A:$A,0))) -> 0 | S63: =MAX(E63+F63,G63,H63,I63,J63,K63,L63,M63,N63,O63,P63,Q63) -> 0
A64: ='Bldgs & Rooms'!$A$3 -> Main Bldg. | B64: ='Bldgs & Rooms'!$B$3 -> 0 | C64: =Hours!$A$27 -> Automatic Transfer Switch (ATS) > 100A | D64: =MAX(E64+F64,G64,H64,I64,J64,K64,L64,M64,N64,O64,P64,Q64) -> 0 | R64: =IF(SUMPRODUCT((E64:Q64)*1)=0,0,E64*INDEX(Hours!M:M,MATCH(C64,Hours!$A:$A,0))+F64*INDEX(Hours!B:B,MATCH(C64,Hours!$A:$A,0))+G64*INDEX(Hours!C:C,MATCH(C64,Hours!$A:$A,0))+H64*INDEX(Hours!D:D,MATCH(C64,Hours!$A:$A,0))+I64*INDEX(Hours!E:E,MATCH(C64,Hours!$A:$A,0))+J64*INDEX(Hours!F:F,MATCH(C64,Hours!$A:$A,0))) -> 0 | S64: =MAX(E64+F64,G64,H64,I64,J64,K64,L64,M64,N64,O64,P64,Q64) -> 0
A65: ='Bldgs & Rooms'!$A$3 -> Main Bldg. | B65: ='Bldgs & Rooms'!$B$3 -> 0 | C65: =Hours!$A$28 -> Manual Transfer Switch (MTS) > 100A | D65: =MAX(E65+F65,G65,H65,I65,J65,K65,L65,M65,N65,O65,P65,Q65) -> 0 | R65: =IF(SUMPRODUCT((E65:Q65)*1)=0,0,E65*INDEX(Hours!M:M,MATCH(C65,Hours!$A:$A,0))+F65*INDEX(Hours!B:B,MATCH(C65,Hours!$A:$A,0))+G65*INDEX(Hours!C:C,MATCH(C65,Hours!$A:$A,0))+H65*INDEX(Hours!D:D,MATCH(C65,Hours!$A:$A,0))+I65*INDEX(Hours!E:E,MATCH(C65,Hours!$A:$A,0))+J65*INDEX(Hours!F:F,MATCH(C65,Hours!$A:$A,0))) -> 0 | S65: =MAX(E65+F65,G65,H65,I65,J65,K65,L65,M65,N65,O65,P65,Q65) -> 0
A66: ='Bldgs & Rooms'!$A$3 -> Main Bldg. | B66: ='Bldgs & Rooms'!$B$3 -> 0 | C66: =Hours!$A$29 -> Variable Frequency Drives (VFD) < 50 HP | D66: =MAX(E66+F66,G66,H66,I66,J66,K66,L66,M66,N66,O66,P66,Q66) -> 0 | R66: =IF(SUMPRODUCT((E66:Q66)*1)=0,0,E66*INDEX(Hours!M:M,MATCH(C66,Hours!$A:$A,0))+F66*INDEX(Hours!B:B,MATCH(C66,Hours!$A:$A,0))+G66*INDEX(Hours!C:C,MATCH(C66,Hours!$A:$A,0))+H66*INDEX(Hours!D:D,MATCH(C66,Hours!$A:$A,0))+I66*INDEX(Hours!E:E,MATCH(C66,Hours!$A:$A,0))+J66*INDEX(Hours!F:F,MATCH(C66,Hours!$A:$A,0))) -> 0 | S66: =MAX(E66+F66,G66,H66,I66,J66,K66,L66,M66,N66,O66,P66,Q66) -> 0
A67: ='Bldgs & Rooms'!$A$3 -> Main Bldg. | B67: ='Bldgs & Rooms'!$B$3 -> 0 | C67: =Hours!$A$30 -> Variable Frequency Drives (VFD) 51-200 HP | D67: =MAX(E67+F67,G67,H67,I67,J67,K67,L67,M67,N67,O67,P67,Q67) -> 0 | R67: =IF(SUMPRODUCT((E67:Q67)*1)=0,0,E67*INDEX(Hours!M:M,MATCH(C67,Hours!$A:$A,0))+F67*INDEX(Hours!B:B,MATCH(C67,Hours!$A:$A,0))+G67*INDEX(Hours!C:C,MATCH(C67,Hours!$A:$A,0))+H67*INDEX(Hours!D:D,MATCH(C67,Hours!$A:$A,0))+I67*INDEX(Hours!E:E,MATCH(C67,Hours!$A:$A,0))+J67*INDEX(Hours!F:F,MATCH(C67,Hours!$A:$A,0))) -> 0 | S67: =MAX(E67+F67,G67,H67,I67,J67,K67,L67,M67,N67,O67,P67,Q67) -> 0
A68: ='Bldgs & Rooms'!$A$3 -> Main Bldg. | B68: ='Bldgs & Rooms'!$B$3 -> 0 | C68: =Hours!$A$31 -> Motors < 50 HP | D68: =MAX(E68+F68,G68,H68,I68,J68,K68,L68,M68,N68,O68,P68,Q68) -> 0 | R68: =IF(SUMPRODUCT((E68:Q68)*1)=0,0,E68*INDEX(Hours!M:M,MATCH(C68,Hours!$A:$A,0))+F68*INDEX(Hours!B:B,MATCH(C68,Hours!$A:$A,0))+G68*INDEX(Hours!C:C,MATCH(C68,Hours!$A:$A,0))+H68*INDEX(Hours!D:D,MATCH(C68,Hours!$A:$A,0))+I68*INDEX(Hours!E:E,MATCH(C68,Hours!$A:$A,0))+J68*INDEX(Hours!F:F,MATCH(C68,Hours!$A:$A,0))) -> 0 | S68: =MAX(E68+F68,G68,H68,I68,J68,K68,L68,M68,N68,O68,P68,Q68) -> 0
A69: ='Bldgs & Rooms'!$A$3 -> Main Bldg. | B69: ='Bldgs & Rooms'!$B$3 -> 0 | C69: =Hours!$A$32 -> Motors 51-200 HP | D69: =MAX(E69+F69,G69,H69,I69,J69,K69,L69,M69,N69,O69,P69,Q69) -> 0 | R69: =IF(SUMPRODUCT((E69:Q69)*1)=0,0,E69*INDEX(Hours!M:M,MATCH(C69,Hours!$A:$A,0))+F69*INDEX(Hours!B:B,MATCH(C69,Hours!$A:$A,0))+G69*INDEX(Hours!C:C,MATCH(C69,Hours!$A:$A,0))+H69*INDEX(Hours!D:D,MATCH(C69,Hours!$A:$A,0))+I69*INDEX(Hours!E:E,MATCH(C69,Hours!$A:$A,0))+J69*INDEX(Hours!F:F,MATCH(C69,Hours!$A:$A,0))) -> 0 | S69: =MAX(E69+F69,G69,H69,I69,J69,K69,L69,M69,N69,O69,P69,Q69) -> 0
A70: ='Bldgs & Rooms'!$A$3 -> Main Bldg. | B70: ='Bldgs & Rooms'!$B$3 -> 0 | C70: =Hours!$A$33 -> Motors 201-500 HP | D70: =MAX(E70+F70,G70,H70,I70,J70,K70,L70,M70,N70,O70,P70,Q70) -> 0 | R70: =IF(SUMPRODUCT((E70:Q70)*1)=0,0,E70*INDEX(Hours!M:M,MATCH(C70,Hours!$A:$A,0))+F70*INDEX(Hours!B:B,MATCH(C70,Hours!$A:$A,0))+G70*INDEX(Hours!C:C,MATCH(C70,Hours!$A:$A,0))+H70*INDEX(Hours!D:D,MATCH(C70,Hours!$A:$A,0))+I70*INDEX(Hours!E:E,MATCH(C70,Hours!$A:$A,0))+J70*INDEX(Hours!F:F,MATCH(C70,Hours!$A:$A,0))) -> 0 | S70: =MAX(E70+F70,G70,H70,I70,J70,K70,L70,M70,N70,O70,P70,Q70) -> 0
A71: ='Bldgs & Rooms'!$A$3 -> Main Bldg. | B71: ='Bldgs & Rooms'!$B$3 -> 0 | C71: =Hours!$A$34 -> Compressed Air Equipment | D71: =MAX(E71+F71,G71,H71,I71,J71,K71,L71,M71,N71,O71,P71,Q71) -> 0 | R71: =IF(SUMPRODUCT((E71:Q71)*1)=0,0,E71*INDEX(Hours!M:M,MATCH(C71,Hours!$A:$A,0))+F71*INDEX(Hours!B:B,MATCH(C71,Hours!$A:$A,0))+G71*INDEX(Hours!C:C,MATCH(C71,Hours!$A:$A,0))+H71*INDEX(Hours!D:D,MATCH(C71,Hours!$A:$A,0))+I71*INDEX(Hours!E:E,MATCH(C71,Hours!$A:$A,0))+J71*INDEX(Hours!F:F,MATCH(C71,Hours!$A:$A,0))) -> 0 | S71: =MAX(E71+F71,G71,H71,I71,J71,K71,L71,M71,N71,O71,P71,Q71) -> 0
A72: ='Bldgs & Rooms'!$A$3 -> Main Bldg. | B72: ='Bldgs & Rooms'!$B$3 -> 0 | C72: =Hours!$A$35 -> HVAC Equipment (Large) | D72: =MAX(E72+F72,G72,H72,I72,J72,K72,L72,M72,N72,O72,P72,Q72) -> 0 | R72: =IF(SUMPRODUCT((E72:Q72)*1)=0,0,E72*INDEX(Hours!M:M,MATCH(C72,Hours!$A:$A,0))+F72*INDEX(Hours!B:B,MATCH(C72,Hours!$A:$A,0))+G72*INDEX(Hours!C:C,MATCH(C72,Hours!$A:$A,0))+H72*INDEX(Hours!D:D,MATCH(C72,Hours!$A:$A,0))+I72*INDEX(Hours!E:E,MATCH(C72,Hours!$A:$A,0))+J72*INDEX(Hours!F:F,MATCH(C72,Hours!$A:$A,0))) -> 0 | S72: =MAX(E72+F72,G72,H72,I72,J72,K72,L72,M72,N72,O72,P72,Q72) -> 0
A73: ='Bldgs & Rooms'!$A$3 -> Main Bldg. | B73: ='Bldgs & Rooms'!$B$3 -> 0 | C73: =Hours!$A$36 -> HVAC Equipment (Small) | D73: =MAX(E73+F73,G73,H73,I73,J73,K73,L73,M73,N73,O73,P73,Q73) -> 0 | R73: =IF(SUMPRODUCT((E73:Q73)*1)=0,0,E73*INDEX(Hours!M:M,MATCH(C73,Hours!$A:$A,0))+F73*INDEX(Hours!B:B,MATCH(C73,Hours!$A:$A,0))+G73*INDEX(Hours!C:C,MATCH(C73,Hours!$A:$A,0))+H73*INDEX(Hours!D:D,MATCH(C73,Hours!$A:$A,0))+I73*INDEX(Hours!E:E,MATCH(C73,Hours!$A:$A,0))+J73*INDEX(Hours!F:F,MATCH(C73,Hours!$A:$A,0))) -> 0 | S73: =MAX(E73+F73,G73,H73,I73,J73,K73,L73,M73,N73,O73,P73,Q73) -> 0
A74: ='Bldgs & Rooms'!$A$3 -> Main Bldg. | B74: ='Bldgs & Rooms'!$B$3 -> 0 | C74: =Hours!$A$37 -> Uninterruptible Power Supply (UPS) < 50kVA | D74: =MAX(E74+F74,G74,H74,I74,J74,K74,L74,M74,N74,O74,P74,Q74) -> 0 | R74: =IF(SUMPRODUCT((E74:Q74)*1)=0,0,E74*INDEX(Hours!M:M,MATCH(C74,Hours!$A:$A,0))+F74*INDEX(Hours!B:B,MATCH(C74,Hours!$A:$A,0))+G74*INDEX(Hours!C:C,MATCH(C74,Hours!$A:$A,0))+H74*INDEX(Hours!D:D,MATCH(C74,Hours!$A:$A,0))+I74*INDEX(Hours!E:E,MATCH(C74,Hours!$A:$A,0))+J74*INDEX(Hours!F:F,MATCH(C74,Hours!$A:$A,0))) -> 0 | S74: =MAX(E74+F74,G74,H74,I74,J74,K74,L74,M74,N74,O74,P74,Q74) -> 0
A75: ='Bldgs & Rooms'!$A$3 -> Main Bldg. | B75: ='Bldgs & Rooms'!$B$3 -> 0 | C75: =Hours!$A$38 -> Uninterruptible Power Supply (UPS) > 50kVA | D75: =MAX(E75+F75,G75,H75,I75,J75,K75,L75,M75,N75,O75,P75,Q75) -> 0 | R75: =IF(SUMPRODUCT((E75:Q75)*1)=0,0,E75*INDEX(Hours!M:M,MATCH(C75,Hours!$A:$A,0))+F75*INDEX(Hours!B:B,MATCH(C75,Hours!$A:$A,0))+G75*INDEX(Hours!C:C,MATCH(C75,Hours!$A:$A,0))+H75*INDEX(Hours!D:D,MATCH(C75,Hours!$A:$A,0))+I75*INDEX(Hours!E:E,MATCH(C75,Hours!$A:$A,0))+J75*INDEX(Hours!F:F,MATCH(C75,Hours!$A:$A,0))) -> 0 | S75: =MAX(E75+F75,G75,H75,I75,J75,K75,L75,M75,N75,O75,P75,Q75) -> 0
A76: ='Bldgs & Rooms'!$A$4 -> Main Bldg. | B76: ='Bldgs & Rooms'!$B$4 -> 0 | C76: =Hours!$A$2 -> Switchgear - Incoming Main Service (Per Section) | D76: =MAX(E76+F76,G76,H76,I76,J76,K76,L76,M76,N76,O76,P76,Q76) -> 0 | R76: =IF(SUMPRODUCT((E76:Q76)*1)=0,0,E76*INDEX(Hours!M:M,MATCH(C76,Hours!$A:$A,0))+F76*INDEX(Hours!B:B,MATCH(C76,Hours!$A:$A,0))+G76*INDEX(Hours!C:C,MATCH(C76,Hours!$A:$A,0))+H76*INDEX(Hours!D:D,MATCH(C76,Hours!$A:$A,0))+I76*INDEX(Hours!E:E,MATCH(C76,Hours!$A:$A,0))+J76*INDEX(Hours!F:F,MATCH(C76,Hours!$A:$A,0))+K76*INDEX(Hours!G:G,MATCH(C76,Hours!$A:$A,0))+L76*INDEX(Hours!H:H,MATCH(C76,Hours!$A:$A,0))+O76*INDEX(Hours!K:K,MATCH(C76,Hours!$A:$A,0))) -> 0 | S76: =MAX(E76+F76,G76,H76,I76,J76,K76,L76,M76,N76,O76,P76,Q76) -> 0
A77: ='Bldgs & Rooms'!$A$4 -> Main Bldg. | B77: ='Bldgs & Rooms'!$B$4 -> 0 | C77: =Hours!$A$3 -> Switchgear Insulated Case Breakers (Bus Mounted) | D77: =MAX(E77+F77,G77,H77,I77,J77,K77,L77,M77,N77,O77,P77,Q77) -> 0 | R77: =IF(SUMPRODUCT((E77:Q77)*1)=0,0,E77*INDEX(Hours!M:M,MATCH(C77,Hours!$A:$A,0))+F77*INDEX(Hours!B:B,MATCH(C77,Hours!$A:$A,0))+G77*INDEX(Hours!C:C,MATCH(C77,Hours!$A:$A,0))+H77*INDEX(Hours!D:D,MATCH(C77,Hours!$A:$A,0))+I77*INDEX(Hours!E:E,MATCH(C77,Hours!$A:$A,0))+J77*INDEX(Hours!F:F,MATCH(C77,Hours!$A:$A,0))+K77*INDEX(Hours!G:G,MATCH(C77,Hours!$A:$A,0))) -> 0 | S77: =MAX(E77+F77,G77,H77,I77,J77,K77,L77,M77,N77,O77,P77,Q77) -> 0
A78: ='Bldgs & Rooms'!$A$4 -> Main Bldg. | B78: ='Bldgs & Rooms'!$B$4 -> 0 | C78: =Hours!$A$4 -> SwitchGear Drawout Breakers | D78: =MAX(E78+F78,G78,H78,I78,J78,K78,L78,M78,N78,O78,P78,Q78) -> 0 | R78: =IF(SUMPRODUCT((E78:Q78)*1)=0,0,E78*INDEX(Hours!M:M,MATCH(C78,Hours!$A:$A,0))+F78*INDEX(Hours!B:B,MATCH(C78,Hours!$A:$A,0))+G78*INDEX(Hours!C:C,MATCH(C78,Hours!$A:$A,0))+H78*INDEX(Hours!D:D,MATCH(C78,Hours!$A:$A,0))+I78*INDEX(Hours!E:E,MATCH(C78,Hours!$A:$A,0))+J78*INDEX(Hours!F:F,MATCH(C78,Hours!$A:$A,0))+L78*INDEX(Hours!H:H,MATCH(C78,Hours!$A:$A,0))) -> 0 | S78: =MAX(E78+F78,G78,H78,I78,J78,K78,L78,M78,N78,O78,P78,Q78) -> 0
A79: ='Bldgs & Rooms'!$A$4 -> Main Bldg. | B79: ='Bldgs & Rooms'!$B$4 -> 0 | C79: =Hours!$A$5 -> Distribution Switchboard Multi Cover (Per Section) | D79: =MAX(E79+F79,G79,H79,I79,J79,K79,L79,M79,N79,O79,P79,Q79) -> 0 | R79: =IF(SUMPRODUCT((E79:Q79)*1)=0,0,E79*INDEX(Hours!M:M,MATCH(C79,Hours!$A:$A,0))+F79*INDEX(Hours!B:B,MATCH(C79,Hours!$A:$A,0))+G79*INDEX(Hours!C:C,MATCH(C79,Hours!$A:$A,0))+H79*INDEX(Hours!D:D,MATCH(C79,Hours!$A:$A,0))+I79*INDEX(Hours!E:E,MATCH(C79,Hours!$A:$A,0))+J79*INDEX(Hours!F:F,MATCH(C79,Hours!$A:$A,0))+K79*INDEX(Hours!G:G,MATCH(C79,Hours!$A:$A,0))+O79*INDEX(Hours!K:K,MATCH(C79,Hours!$A:$A,0))) -> 0 | S79: =MAX(E79+F79,G79,H79,I79,J79,K79,L79,M79,N79,O79,P79,Q79) -> 0
A80: ='Bldgs & Rooms'!$A$4 -> Main Bldg. | B80: ='Bldgs & Rooms'!$B$4 -> 0 | C80: =Hours!$A$6 -> Switchboard Disconnects | D80: =MAX(E80+F80,G80,H80,I80,J80,K80,L80,M80,N80,O80,P80,Q80) -> 0 | R80: =IF(SUMPRODUCT((E80:Q80)*1)=0,0,E80*INDEX(Hours!M:M,MATCH(C80,Hours!$A:$A,0))+F80*INDEX(Hours!B:B,MATCH(C80,Hours!$A:$A,0))+G80*INDEX(Hours!C:C,MATCH(C80,Hours!$A:$A,0))+H80*INDEX(Hours!D:D,MATCH(C80,Hours!$A:$A,0))+I80*INDEX(Hours!E:E,MATCH(C80,Hours!$A:$A,0))+J80*INDEX(Hours!F:F,MATCH(C80,Hours!$A:$A,0))) -> 0 | S80: =MAX(E80+F80,G80,H80,I80,J80,K80,L80,M80,N80,O80,P80,Q80) -> 0
A81: ='Bldgs & Rooms'!$A$4 -> Main Bldg. | B81: ='Bldgs & Rooms'!$B$4 -> 0 | C81: =Hours!$A$7 -> Switchboard Molded Case Breakers | D81: =MAX(E81+F81,G81,H81,I81,J81,K81,L81,M81,N81,O81,P81,Q81) -> 0 | R81: =IF(SUMPRODUCT((E81:Q81)*1)=0,0,E81*INDEX(Hours!M:M,MATCH(C81,Hours!$A:$A,0))+F81*INDEX(Hours!B:B,MATCH(C81,Hours!$A:$A,0))+G81*INDEX(Hours!C:C,MATCH(C81,Hours!$A:$A,0))+H81*INDEX(Hours!D:D,MATCH(C81,Hours!$A:$A,0))+I81*INDEX(Hours!E:E,MATCH(C81,Hours!$A:$A,0))+J81*INDEX(Hours!F:F,MATCH(C81,Hours!$A:$A,0))+K81*INDEX(Hours!G:G,MATCH(C81,Hours!$A:$A,0))) -> 0 | S81: =MAX(E81+F81,G81,H81,I81,J81,K81,L81,M81,N81,O81,P81,Q81) -> 0
A82: ='Bldgs & Rooms'!$A$4 -> Main Bldg. | B82: ='Bldgs & Rooms'!$B$4 -> 0 | C82: =Hours!$A$8 -> Panelboard-Single Cover > 400A (Distribution Panel) | D82: =MAX(E82+F82,G82,H82,I82,J82,K82,L82,M82,N82,O82,P82,Q82) -> 0 | R82: =IF(SUMPRODUCT((E82:Q82)*1)=0,0,E82*INDEX(Hours!M:M,MATCH(C82,Hours!$A:$A,0))+F82*INDEX(Hours!B:B,MATCH(C82,Hours!$A:$A,0))+G82*INDEX(Hours!C:C,MATCH(C82,Hours!$A:$A,0))+H82*INDEX(Hours!D:D,MATCH(C82,Hours!$A:$A,0))+I82*INDEX(Hours!E:E,MATCH(C82,Hours!$A:$A,0))+J82*INDEX(Hours!F:F,MATCH(C82,Hours!$A:$A,0))+K82*INDEX(Hours!G:G,MATCH(C82,Hours!$A:$A,0))+O82*INDEX(Hours!K:K,MATCH(C82,Hours!$A:$A,0))) -> 0 | S82: =MAX(E82+F82,G82,H82,I82,J82,K82,L82,M82,N82,O82,P82,Q82) -> 0
A83: ='Bldgs & Rooms'!$A$4 -> Main Bldg. | B83: ='Bldgs & Rooms'!$B$4 -> 0 | C83: =Hours!$A$9 -> Panelboard-Single Cover < 400A (Branch Ckt Panel) | D83: =MAX(E83+F83,G83,H83,I83,J83,K83,L83,M83,N83,O83,P83,Q83) -> 0 | R83: =IF(SUMPRODUCT((E83:Q83)*1)=0,0,E83*INDEX(Hours!M:M,MATCH(C83,Hours!$A:$A,0))+F83*INDEX(Hours!B:B,MATCH(C83,Hours!$A:$A,0))+G83*INDEX(Hours!C:C,MATCH(C83,Hours!$A:$A,0))+H83*INDEX(Hours!D:D,MATCH(C83,Hours!$A:$A,0))+I83*INDEX(Hours!E:E,MATCH(C83,Hours!$A:$A,0))+J83*INDEX(Hours!F:F,MATCH(C83,Hours!$A:$A,0))+O83*INDEX(Hours!K:K,MATCH(C83,Hours!$A:$A,0))) -> 0 | S83: =MAX(E83+F83,G83,H83,I83,J83,K83,L83,M83,N83,O83,P83,Q83) -> 0
A84: ='Bldgs & Rooms'!$A$4 -> Main Bldg. | B84: ='Bldgs & Rooms'!$B$4 -> 0 | C84: =Hours!$A$10 -> Motor Control Center (MCC-Per Vertical Section) | D84: =MAX(E84+F84,G84,H84,I84,J84,K84,L84,M84,N84,O84,P84,Q84) -> 0 | R84: =IF(SUMPRODUCT((E84:Q84)*1)=0,0,E84*INDEX(Hours!M:M,MATCH(C84,Hours!$A:$A,0))+F84*INDEX(Hours!B:B,MATCH(C84,Hours!$A:$A,0))+G84*INDEX(Hours!C:C,MATCH(C84,Hours!$A:$A,0))+H84*INDEX(Hours!D:D,MATCH(C84,Hours!$A:$A,0))+I84*INDEX(Hours!E:E,MATCH(C84,Hours!$A:$A,0))+J84*INDEX(Hours!F:F,MATCH(C84,Hours!$A:$A,0))+O84*INDEX(Hours!K:K,MATCH(C84,Hours!$A:$A,0))) -> 0 | S84: =MAX(E84+F84,G84,H84,I84,J84,K84,L84,M84,N84,O84,P84,Q84) -> 0
A85: ='Bldgs & Rooms'!$A$4 -> Main Bldg. | B85: ='Bldgs & Rooms'!$B$4 -> 0 | C85: =Hours!$A$11 -> MCC: Combination Motor Starters | D85: =MAX(E85+F85,G85,H85,I85,J85,K85,L85,M85,N85,O85,P85,Q85) -> 0 | R85: =IF(SUMPRODUCT((E85:Q85)*1)=0,0,E85*INDEX(Hours!M:M,MATCH(C85,Hours!$A:$A,0))+F85*INDEX(Hours!B:B,MATCH(C85,Hours!$A:$A,0))+G85*INDEX(Hours!C:C,MATCH(C85,Hours!$A:$A,0))+H85*INDEX(Hours!D:D,MATCH(C85,Hours!$A:$A,0))+I85*INDEX(Hours!E:E,MATCH(C85,Hours!$A:$A,0))+J85*INDEX(Hours!F:F,MATCH(C85,Hours!$A:$A,0))+K85*INDEX(Hours!G:G,MATCH(C85,Hours!$A:$A,0))+O85*INDEX(Hours!K:K,MATCH(C85,Hours!$A:$A,0))) -> 0 | S85: =MAX(E85+F85,G85,H85,I85,J85,K85,L85,M85,N85,O85,P85,Q85) -> 0
A86: ='Bldgs & Rooms'!$A$4 -> Main Bldg. | B86: ='Bldgs & Rooms'!$B$4 -> 0 | C86: =Hours!$A$12 -> MCC: Molded Case Breaker | D86: =MAX(E86+F86,G86,H86,I86,J86,K86,L86,M86,N86,O86,P86,Q86) -> 0 | R86: =IF(SUMPRODUCT((E86:Q86)*1)=0,0,E86*INDEX(Hours!M:M,MATCH(C86,Hours!$A:$A,0))+F86*INDEX(Hours!B:B,MATCH(C86,Hours!$A:$A,0))+G86*INDEX(Hours!C:C,MATCH(C86,Hours!$A:$A,0))+H86*INDEX(Hours!D:D,MATCH(C86,Hours!$A:$A,0))+I86*INDEX(Hours!E:E,MATCH(C86,Hours!$A:$A,0))+J86*INDEX(Hours!F:F,MATCH(C86,Hours!$A:$A,0))+K86*INDEX(Hours!G:G,MATCH(C86,Hours!$A:$A,0))) -> 0 | S86: =MAX(E86+F86,G86,H86,I86,J86,K86,L86,M86,N86,O86,P86,Q86) -> 0
A87: ='Bldgs & Rooms'!$A$4 -> Main Bldg. | B87: ='Bldgs & Rooms'!$B$4 -> 0 | C87: =Hours!$A$13 -> MCC: Individual Disconnect Switch | D87: =MAX(E87+F87,G87,H87,I87,J87,K87,L87,M87,N87,O87,P87,Q87) -> 0 | R87: =IF(SUMPRODUCT((E87:Q87)*1)=0,0,E87*INDEX(Hours!M:M,MATCH(C87,Hours!$A:$A,0))+F87*INDEX(Hours!B:B,MATCH(C87,Hours!$A:$A,0))+G87*INDEX(Hours!C:C,MATCH(C87,Hours!$A:$A,0))+H87*INDEX(Hours!D:D,MATCH(C87,Hours!$A:$A,0))+I87*INDEX(Hours!E:E,MATCH(C87,Hours!$A:$A,0))+J87*INDEX(Hours!F:F,MATCH(C87,Hours!$A:$A,0))) -> 0 | S87: =MAX(E87+F87,G87,H87,I87,J87,K87,L87,M87,N87,O87,P87,Q87) -> 0
A88: ='Bldgs & Rooms'!$A$4 -> Main Bldg. | B88: ='Bldgs & Rooms'!$B$4 -> 0 | C88: =Hours!$A$14 -> Motor Control Panel (MCP) | D88: =MAX(E88+F88,G88,H88,I88,J88,K88,L88,M88,N88,O88,P88,Q88) -> 0 | R88: =IF(SUMPRODUCT((E88:Q88)*1)=0,0,E88*INDEX(Hours!M:M,MATCH(C88,Hours!$A:$A,0))+F88*INDEX(Hours!B:B,MATCH(C88,Hours!$A:$A,0))+G88*INDEX(Hours!C:C,MATCH(C88,Hours!$A:$A,0))+H88*INDEX(Hours!D:D,MATCH(C88,Hours!$A:$A,0))+I88*INDEX(Hours!E:E,MATCH(C88,Hours!$A:$A,0))+J88*INDEX(Hours!F:F,MATCH(C88,Hours!$A:$A,0))+O88*INDEX(Hours!K:K,MATCH(C88,Hours!$A:$A,0))) -> 0 | S88: =MAX(E88+F88,G88,H88,I88,J88,K88,L88,M88,N88,O88,P88,Q88) -> 0
A89: ='Bldgs & Rooms'!$A$4 -> Main Bldg. | B89: ='Bldgs & Rooms'!$B$4 -> 0 | C89: =Hours!$A$15 -> VFD Motor Control Panel (VFD-MCP) | D89: =MAX(E89+F89,G89,H89,I89,J89,K89,L89,M89,N89,O89,P89,Q89) -> 0 | R89: =IF(SUMPRODUCT((E89:Q89)*1)=0,0,E89*INDEX(Hours!M:M,MATCH(C89,Hours!$A:$A,0))+F89*INDEX(Hours!B:B,MATCH(C89,Hours!$A:$A,0))+G89*INDEX(Hours!C:C,MATCH(C89,Hours!$A:$A,0))+H89*INDEX(Hours!D:D,MATCH(C89,Hours!$A:$A,0))+I89*INDEX(Hours!E:E,MATCH(C89,Hours!$A:$A,0))+J89*INDEX(Hours!F:F,MATCH(C89,Hours!$A:$A,0))+O89*INDEX(Hours!K:K,MATCH(C89,Hours!$A:$A,0))) -> 0 | S89: =MAX(E89+F89,G89,H89,I89,J89,K89,L89,M89,N89,O89,P89,Q89) -> 0
A90: ='Bldgs & Rooms'!$A$4 -> Main Bldg. | B90: ='Bldgs & Rooms'!$B$4 -> 0 | C90: =Hours!$A$16 -> Individual Disconnect Switch > 100A | D90: =MAX(E90+F90,G90,H90,I90,J90,K90,L90,M90,N90,O90,P90,Q90) -> 0 | R90: =IF(SUMPRODUCT((E90:Q90)*1)=0,0,E90*INDEX(Hours!M:M,MATCH(C90,Hours!$A:$A,0))+F90*INDEX(Hours!B:B,MATCH(C90,Hours!$A:$A,0))+G90*INDEX(Hours!C:C,MATCH(C90,Hours!$A:$A,0))+H90*INDEX(Hours!D:D,MATCH(C90,Hours!$A:$A,0))+I90*INDEX(Hours!E:E,MATCH(C90,Hours!$A:$A,0))+J90*INDEX(Hours!F:F,MATCH(C90,Hours!$A:$A,0))+K90*INDEX(Hours!G:G,MATCH(C90,Hours!$A:$A,0))) -> 0 | S90: =MAX(E90+F90,G90,H90,I90,J90,K90,L90,M90,N90,O90,P90,Q90) -> 0
A91: ='Bldgs & Rooms'!$A$4 -> Main Bldg. | B91: ='Bldgs & Rooms'!$B$4 -> 0 | C91: =Hours!$A$17 -> Individual Molded Case Breaker > 100A | D91: =MAX(E91+F91,G91,H91,I91,J91,K91,L91,M91,N91,O91,P91,Q91) -> 0 | R91: =IF(SUMPRODUCT((E91:Q91)*1)=0,0,E91*INDEX(Hours!M:M,MATCH(C91,Hours!$A:$A,0))+F91*INDEX(Hours!B:B,MATCH(C91,Hours!$A:$A,0))+G91*INDEX(Hours!C:C,MATCH(C91,Hours!$A:$A,0))+H91*INDEX(Hours!D:D,MATCH(C91,Hours!$A:$A,0))+I91*INDEX(Hours!E:E,MATCH(C91,Hours!$A:$A,0))+J91*INDEX(Hours!F:F,MATCH(C91,Hours!$A:$A,0))+K91*INDEX(Hours!G:G,MATCH(C91,Hours!$A:$A,0))) -> 0 | S91: =MAX(E91+F91,G91,H91,I91,J91,K91,L91,M91,N91,O91,P91,Q91) -> 0
A92: ='Bldgs & Rooms'!$A$4 -> Main Bldg. | B92: ='Bldgs & Rooms'!$B$4 -> 0 | C92: =Hours!$A$18 -> Individual Combination Motor Starter > 100A | D92: =MAX(E92+F92,G92,H92,I92,J92,K92,L92,M92,N92,O92,P92,Q92) -> 0 | R92: =IF(SUMPRODUCT((E92:Q92)*1)=0,0,E92*INDEX(Hours!M:M,MATCH(C92,Hours!$A:$A,0))+F92*INDEX(Hours!B:B,MATCH(C92,Hours!$A:$A,0))+G92*INDEX(Hours!C:C,MATCH(C92,Hours!$A:$A,0))+H92*INDEX(Hours!D:D,MATCH(C92,Hours!$A:$A,0))+I92*INDEX(Hours!E:E,MATCH(C92,Hours!$A:$A,0))+J92*INDEX(Hours!F:F,MATCH(C92,Hours!$A:$A,0))+K92*INDEX(Hours!G:G,MATCH(C92,Hours!$A:$A,0))) -> 0 | S92: =MAX(E92+F92,G92,H92,I92,J92,K92,L92,M92,N92,O92,P92,Q92) -> 0
A93: ='Bldgs & Rooms'!$A$4 -> Main Bldg. | B93: ='Bldgs & Rooms'!$B$4 -> 0 | C93: =Hours!$A$19 -> Oil Filled Transformer - 5kV-15kV Primary - Any Size (Pad Mounted) | D93: =MAX(E93+F93,G93,H93,I93,J93,K93,L93,M93,N93,O93,P93,Q93) -> 0 | R93: =IF(SUMPRODUCT((E93:Q93)*1)=0,0,E93*INDEX(Hours!M:M,MATCH(C93,Hours!$A:$A,0))+F93*INDEX(Hours!B:B,MATCH(C93,Hours!$A:$A,0))+G93*INDEX(Hours!C:C,MATCH(C93,Hours!$A:$A,0))+H93*INDEX(Hours!D:D,MATCH(C93,Hours!$A:$A,0))+I93*INDEX(Hours!E:E,MATCH(C93,Hours!$A:$A,0))+J93*INDEX(Hours!F:F,MATCH(C93,Hours!$A:$A,0))+M93*INDEX(Hours!I:I,MATCH(C93,Hours!$A:$A,0))+N93*INDEX(Hours!J:J,MATCH(C93,Hours!$A:$A,0))+P93*INDEX(Hours!L:L,MATCH(C93,Hours!$A:$A,0))) -> 0 | S93: =MAX(E93+F93,G93,H93,I93,J93,K93,L93,M93,N93,O93,P93,Q93) -> 0
A94: ='Bldgs & Rooms'!$A$4 -> Main Bldg. | B94: ='Bldgs & Rooms'!$B$4 -> 0 | C94: =Hours!$A$20 -> Oil Filled Transformer - > 15kV Primary (Substation Class) | D94: =MAX(E94+F94,G94,H94,I94,J94,K94,L94,M94,N94,O94,P94,Q94) -> 0 | R94: =IF(SUMPRODUCT((E94:Q94)*1)=0,0,E94*INDEX(Hours!M:M,MATCH(C94,Hours!$A:$A,0))+F94*INDEX(Hours!B:B,MATCH(C94,Hours!$A:$A,0))+G94*INDEX(Hours!C:C,MATCH(C94,Hours!$A:$A,0))+H94*INDEX(Hours!D:D,MATCH(C94,Hours!$A:$A,0))+I94*INDEX(Hours!E:E,MATCH(C94,Hours!$A:$A,0))+J94*INDEX(Hours!F:F,MATCH(C94,Hours!$A:$A,0))+M94*INDEX(Hours!I:I,MATCH(C94,Hours!$A:$A,0))+N94*INDEX(Hours!J:J,MATCH(C94,Hours!$A:$A,0))+P94*INDEX(Hours!L:L,MATCH(C94,Hours!$A:$A,0))) -> 0 | S94: =MAX(E94+F94,G94,H94,I94,J94,K94,L94,M94,N94,O94,P94,Q94) -> 0
A95: ='Bldgs & Rooms'!$A$4 -> Main Bldg. | B95: ='Bldgs & Rooms'!$B$4 -> 0 | C95: =Hours!$A$21 -> Dry Type Transformer - < 480V Primary - Any Size kVA | D95: =MAX(E95+F95,G95,H95,I95,J95,K95,L95,M95,N95,O95,P95,Q95) -> 0 | R95: =IF(SUMPRODUCT((E95:Q95)*1)=0,0,E95*INDEX(Hours!M:M,MATCH(C95,Hours!$A:$A,0))+F95*INDEX(Hours!B:B,MATCH(C95,Hours!$A:$A,0))+G95*INDEX(Hours!C:C,MATCH(C95,Hours!$A:$A,0))+H95*INDEX(Hours!D:D,MATCH(C95,Hours!$A:$A,0))+I95*INDEX(Hours!E:E,MATCH(C95,Hours!$A:$A,0))+J95*INDEX(Hours!F:F,MATCH(C95,Hours!$A:$A,0))+M95*INDEX(Hours!I:I,MATCH(C95,Hours!$A:$A,0))+N95*INDEX(Hours!J:J,MATCH(C95,Hours!$A:$A,0))) -> 0 | S95: =MAX(E95+F95,G95,H95,I95,J95,K95,L95,M95,N95,O95,P95,Q95) -> 0
A96: ='Bldgs & Rooms'!$A$4 -> Main Bldg. | B96: ='Bldgs & Rooms'!$B$4 -> 0 | C96: =Hours!$A$22 -> Power Factor Correction Capacitors | D96: =MAX(E96+F96,G96,H96,I96,J96,K96,L96,M96,N96,O96,P96,Q96) -> 0 | R96: =IF(SUMPRODUCT((E96:Q96)*1)=0,0,E96*INDEX(Hours!M:M,MATCH(C96,Hours!$A:$A,0))+F96*INDEX(Hours!B:B,MATCH(C96,Hours!$A:$A,0))+G96*INDEX(Hours!C:C,MATCH(C96,Hours!$A:$A,0))+H96*INDEX(Hours!D:D,MATCH(C96,Hours!$A:$A,0))+I96*INDEX(Hours!E:E,MATCH(C96,Hours!$A:$A,0))+J96*INDEX(Hours!F:F,MATCH(C96,Hours!$A:$A,0))) -> 0 | S96: =MAX(E96+F96,G96,H96,I96,J96,K96,L96,M96,N96,O96,P96,Q96) -> 0
A97: ='Bldgs & Rooms'!$A$4 -> Main Bldg. | B97: ='Bldgs & Rooms'!$B$4 -> 0 | C97: =Hours!$A$23 -> Lighting Contactor > 100A | D97: =MAX(E97+F97,G97,H97,I97,J97,K97,L97,M97,N97,O97,P97,Q97) -> 0 | R97: =IF(SUMPRODUCT((E97:Q97)*1)=0,0,E97*INDEX(Hours!M:M,MATCH(C97,Hours!$A:$A,0))+F97*INDEX(Hours!B:B,MATCH(C97,Hours!$A:$A,0))+G97*INDEX(Hours!C:C,MATCH(C97,Hours!$A:$A,0))+H97*INDEX(Hours!D:D,MATCH(C97,Hours!$A:$A,0))+I97*INDEX(Hours!E:E,MATCH(C97,Hours!$A:$A,0))+J97*INDEX(Hours!F:F,MATCH(C97,Hours!$A:$A,0))) -> 0 | S97: =MAX(E97+F97,G97,H97,I97,J97,K97,L97,M97,N97,O97,P97,Q97) -> 0
A98: ='Bldgs & Rooms'!$A$4 -> Main Bldg. | B98: ='Bldgs & Rooms'!$B$4 -> 0 | C98: =Hours!$A$24 -> Power Distribution Unit (PDU) | D98: =MAX(E98+F98,G98,H98,I98,J98,K98,L98,M98,N98,O98,P98,Q98) -> 0 | R98: =IF(SUMPRODUCT((E98:Q98)*1)=0,0,E98*INDEX(Hours!M:M,MATCH(C98,Hours!$A:$A,0))+F98*INDEX(Hours!B:B,MATCH(C98,Hours!$A:$A,0))+G98*INDEX(Hours!C:C,MATCH(C98,Hours!$A:$A,0))+H98*INDEX(Hours!D:D,MATCH(C98,Hours!$A:$A,0))+I98*INDEX(Hours!E:E,MATCH(C98,Hours!$A:$A,0))+J98*INDEX(Hours!F:F,MATCH(C98,Hours!$A:$A,0))) -> 0 | S98: =MAX(E98+F98,G98,H98,I98,J98,K98,L98,M98,N98,O98,P98,Q98) -> 0
A99: ='Bldgs & Rooms'!$A$4 -> Main Bldg. | B99: ='Bldgs & Rooms'!$B$4 -> 0 | C99: =Hours!$A$25 -> Wire Trough, Gutter, or Large Junction Boxes | D99: =MAX(E99+F99,G99,H99,I99,J99,K99,L99,M99,N99,O99,P99,Q99) -> 0 | R99: =IF(SUMPRODUCT((E99:Q99)*1)=0,0,E99*INDEX(Hours!M:M,MATCH(C99,Hours!$A:$A,0))+F99*INDEX(Hours!B:B,MATCH(C99,Hours!$A:$A,0))+G99*INDEX(Hours!C:C,MATCH(C99,Hours!$A:$A,0))+H99*INDEX(Hours!D:D,MATCH(C99,Hours!$A:$A,0))+I99*INDEX(Hours!E:E,MATCH(C99,Hours!$A:$A,0))+J99*INDEX(Hours!F:F,MATCH(C99,Hours!$A:$A,0))) -> 0 | S99: =MAX(E99+F99,G99,H99,I99,J99,K99,L99,M99,N99,O99,P99,Q99) -> 0
A100: ='Bldgs & Rooms'!$A$4 -> Main Bldg. | B100: ='Bldgs & Rooms'!$B$4 -> 0 | C100: =Hours!$A$26 -> Bus Duct - Vertical or Horizontal (Per 10' section) | D100: =MAX(E100+F100,G100,H100,I100,J100,K100,L100,M100,N100,O100,P100,Q100) -> 0 | R100: =IF(SUMPRODUCT((E100:Q100)*1)=0,0,E100*INDEX(Hours!M:M,MATCH(C100,Hours!$A:$A,0))+F100*INDEX(Hours!B:B,MATCH(C100,Hours!$A:$A,0))+G100*INDEX(Hours!C:C,MATCH(C100,Hours!$A:$A,0))+H100*INDEX(Hours!D:D,MATCH(C100,Hours!$A:$A,0))+I100*INDEX(Hours!E:E,MATCH(C100,Hours!$A:$A,0))+J100*INDEX(Hours!F:F,MATCH(C100,Hours!$A:$A,0))) -> 0 | S100: =MAX(E100+F100,G100,H100,I100,J100,K100,L100,M100,N100,O100,P100,Q100) -> 0
...

Sheet Components Yr 2
A1: Building | B1: Room | C1: 600 Volt and below | D1: Total Counted | E1: Basic EPM | F1: Full EPM | G1: De-Energized | H1: IR | I1: Ultrasonic | J1: A-F Collection | K1: Pri.Breaker | L1: Sec. Breaker | M1: PwrFact (partial) | N1: PwrFact (xfmr/CB) | O1: Panel Schd. | P1: Oil Sample | Q1: ESA | R1: Total Hours | S1: Total pcs. priced
A2: ='Bldgs & Rooms'!$A$2 -> Main Bldg. | B2: ='Bldgs & Rooms'!$B$2 -> 0 | C2: =Hours!$A$2 -> Switchgear - Incoming Main Service (Per Section) | D2: =MAX(E2+F2,G2,H2,I2,J2,K2,L2,M2,N2,O2,P2,Q2) -> 0 | E2: =IF('Components Yr 1'!E2=0,0,'Components Yr 1'!E2) -> 0 | F2: =IF('Components Yr 1'!F2=0,0,'Components Yr 1'!F2) -> 0 | G2: =IF('Components Yr 1'!G2=0,0,'Components Yr 1'!G2) -> 0 | H2: =IF('Components Yr 1'!H2=0,0,'Components Yr 1'!H2) -> 0 | I2: =IF('Components Yr 1'!I2=0,0,'Components Yr 1'!I2) -> 0 | J2: =IF('Components Yr 1'!J2=0,0,'Components Yr 1'!J2) -> 0 | K2: =IF('Components Yr 1'!K2=0,0,'Components Yr 1'!K2) -> 0 | L2: =IF('Components Yr 1'!L2=0,0,'Components Yr 1'!L2) -> 0 | O2: =IF('Components Yr 1'!O2=0,0,'Components Yr 1'!O2) -> 0 | R2: =IF(SUMPRODUCT((E2:Q2)*1)=0,0,E2*INDEX(Hours!M:M,MATCH(C2,Hours!$A:$A,0))+F2*INDEX(Hours!B:B,MATCH(C2,Hours!$A:$A,0))+G2*INDEX(Hours!C:C,MATCH(C2,Hours!$A:$A,0))+H2*INDEX(Hours!D:D,MATCH(C2,Hours!$A:$A,0))+I2*INDEX(Hours!E:E,MATCH(C2,Hours!$A:$A,0))+J2*INDEX(Hours!F:F,MATCH(C2,Hours!$A:$A,0))+K2*INDEX(Hours!G:G,MATCH(C2,Hours!$A:$A,0))+L2*INDEX(Hours!H:H,MATCH(C2,Hours!$A:$A,0))+O2*INDEX(Hours!K:K,MATCH(C2,Hours!$A:$A,0))) -> 0 | S2: =MAX(E2+F2,G2,H2,I2,J2,K2,L2,M2,N2,O2,P2,Q2) -> 0
A3: ='Bldgs & Rooms'!$A$2 -> Main Bldg. | B3: ='Bldgs & Rooms'!$B$2 -> 0 | C3: =Hours!$A$3 -> Switchgear Insulated Case Breakers (Bus Mounted) | D3: =MAX(E3+F3,G3,H3,I3,J3,K3,L3,M3,N3,O3,P3,Q3) -> 0 | E3: =IF('Components Yr 1'!E3=0,0,'Components Yr 1'!E3) -> 0 | F3: =IF('Components Yr 1'!F3=0,0,'Components Yr 1'!F3) -> 0 | G3: =IF('Components Yr 1'!G3=0,0,'Components Yr 1'!G3) -> 0 | H3: =IF('Components Yr 1'!H3=0,0,'Components Yr 1'!H3) -> 0 | I3: =IF('Components Yr 1'!I3=0,0,'Components Yr 1'!I3) -> 0 | J3: =IF('Components Yr 1'!J3=0,0,'Components Yr 1'!J3) -> 0 | K3: =IF('Components Yr 1'!K3=0,0,'Components Yr 1'!K3) -> 0 | R3: =IF(SUMPRODUCT((E3:Q3)*1)=0,0,E3*INDEX(Hours!M:M,MATCH(C3,Hours!$A:$A,0))+F3*INDEX(Hours!B:B,MATCH(C3,Hours!$A:$A,0))+G3*INDEX(Hours!C:C,MATCH(C3,Hours!$A:$A,0))+H3*INDEX(Hours!D:D,MATCH(C3,Hours!$A:$A,0))+I3*INDEX(Hours!E:E,MATCH(C3,Hours!$A:$A,0))+J3*INDEX(Hours!F:F,MATCH(C3,Hours!$A:$A,0))+K3*INDEX(Hours!G:G,MATCH(C3,Hours!$A:$A,0))) -> 0 | S3: =MAX(E3+F3,G3,H3,I3,J3,K3,L3,M3,N3,O3,P3,Q3) -> 0
A4: ='Bldgs & Rooms'!$A$2 -> Main Bldg. | B4: ='Bldgs & Rooms'!$B$2 -> 0 | C4: =Hours!$A$4 -> SwitchGear Drawout Breakers | D4: =MAX(E4+F4,G4,H4,I4,J4,K4,L4,M4,N4,O4,P4,Q4) -> 0 | E4: =IF('Components Yr 1'!E4=0,0,'Components Yr 1'!E4) -> 0 | F4: =IF('Components Yr 1'!F4=0,0,'Components Yr 1'!F4) -> 0 | G4: =IF('Components Yr 1'!G4=0,0,'Components Yr 1'!G4) -> 0 | H4: =IF('Components Yr 1'!H4=0,0,'Components Yr 1'!H4) -> 0 | I4: =IF('Components Yr 1'!I4=0,0,'Components Yr 1'!I4) -> 0 | J4: =IF('Components Yr 1'!J4=0,0,'Components Yr 1'!J4) -> 0 | L4: =IF('Components Yr 1'!L4=0,0,'Components Yr 1'!L4) -> 0 | R4: =IF(SUMPRODUCT((E4:Q4)*1)=0,0,E4*INDEX(Hours!M:M,MATCH(C4,Hours!$A:$A,0))+F4*INDEX(Hours!B:B,MATCH(C4,Hours!$A:$A,0))+G4*INDEX(Hours!C:C,MATCH(C4,Hours!$A:$A,0))+H4*INDEX(Hours!D:D,MATCH(C4,Hours!$A:$A,0))+I4*INDEX(Hours!E:E,MATCH(C4,Hours!$A:$A,0))+J4*INDEX(Hours!F:F,MATCH(C4,Hours!$A:$A,0))+L4*INDEX(Hours!H:H,MATCH(C4,Hours!$A:$A,0))) -> 0 | S4: =MAX(E4+F4,G4,H4,I4,J4,K4,L4,M4,N4,O4,P4,Q4) -> 0
A5: ='Bldgs & Rooms'!$A$2 -> Main Bldg. | B5: ='Bldgs & Rooms'!$B$2 -> 0 | C5: =Hours!$A$5 -> Distribution Switchboard Multi Cover (Per Section) | D5: =MAX(E5+F5,G5,H5,I5,J5,K5,L5,M5,N5,O5,P5,Q5) -> 0 | E5: =IF('Components Yr 1'!E5=0,0,'Components Yr 1'!E5) -> 0 | F5: =IF('Components Yr 1'!F5=0,0,'Components Yr 1'!F5) -> 0 | G5: =IF('Components Yr 1'!G5=0,0,'Components Yr 1'!G5) -> 0 | H5: =IF('Components Yr 1'!H5=0,0,'Components Yr 1'!H5) -> 0 | I5: =IF('Components Yr 1'!I5=0,0,'Components Yr 1'!I5) -> 0 | J5: =IF('Components Yr 1'!J5=0,0,'Components Yr 1'!J5) -> 0 | K5: =IF('Components Yr 1'!K5=0,0,'Components Yr 1'!K5) -> 0 | O5: =IF('Components Yr 1'!O5=0,0,'Components Yr 1'!O5) -> 0 | R5: =IF(SUMPRODUCT((E5:Q5)*1)=0,0,E5*INDEX(Hours!M:M,MATCH(C5,Hours!$A:$A,0))+F5*INDEX(Hours!B:B,MATCH(C5,Hours!$A:$A,0))+G5*INDEX(Hours!C:C,MATCH(C5,Hours!$A:$A,0))+H5*INDEX(Hours!D:D,MATCH(C5,Hours!$A:$A,0))+I5*INDEX(Hours!E:E,MATCH(C5,Hours!$A:$A,0))+J5*INDEX(Hours!F:F,MATCH(C5,Hours!$A:$A,0))+K5*INDEX(Hours!G:G,MATCH(C5,Hours!$A:$A,0))+O5*INDEX(Hours!K:K,MATCH(C5,Hours!$A:$A,0))) -> 0 | S5: =MAX(E5+F5,G5,H5,I5,J5,K5,L5,M5,N5,O5,P5,Q5) -> 0
A6: ='Bldgs & Rooms'!$A$2 -> Main Bldg. | B6: ='Bldgs & Rooms'!$B$2 -> 0 | C6: =Hours!$A$6 -> Switchboard Disconnects | D6: =MAX(E6+F6,G6,H6,I6,J6,K6,L6,M6,N6,O6,P6,Q6) -> 0 | E6: =IF('Components Yr 1'!E6=0,0,'Components Yr 1'!E6) -> 0 | F6: =IF('Components Yr 1'!F6=0,0,'Components Yr 1'!F6) -> 0 | G6: =IF('Components Yr 1'!G6=0,0,'Components Yr 1'!G6) -> 0 | H6: =IF('Components Yr 1'!H6=0,0,'Components Yr 1'!H6) -> 0 | I6: =IF('Components Yr 1'!I6=0,0,'Components Yr 1'!I6) -> 0 | J6: =IF('Components Yr 1'!J6=0,0,'Components Yr 1'!J6) -> 0 | R6: =IF(SUMPRODUCT((E6:Q6)*1)=0,0,E6*INDEX(Hours!M:M,MATCH(C6,Hours!$A:$A,0))+F6*INDEX(Hours!B:B,MATCH(C6,Hours!$A:$A,0))+G6*INDEX(Hours!C:C,MATCH(C6,Hours!$A:$A,0))+H6*INDEX(Hours!D:D,MATCH(C6,Hours!$A:$A,0))+I6*INDEX(Hours!E:E,MATCH(C6,Hours!$A:$A,0))+J6*INDEX(Hours!F:F,MATCH(C6,Hours!$A:$A,0))) -> 0 | S6: =MAX(E6+F6,G6,H6,I6,J6,K6,L6,M6,N6,O6,P6,Q6) -> 0
A7: ='Bldgs & Rooms'!$A$2 -> Main Bldg. | B7: ='Bldgs & Rooms'!$B$2 -> 0 | C7: =Hours!$A$7 -> Switchboard Molded Case Breakers | D7: =MAX(E7+F7,G7,H7,I7,J7,K7,L7,M7,N7,O7,P7,Q7) -> 0 | E7: =IF('Components Yr 1'!E7=0,0,'Components Yr 1'!E7) -> 0 | F7: =IF('Components Yr 1'!F7=0,0,'Components Yr 1'!F7) -> 0 | G7: =IF('Components Yr 1'!G7=0,0,'Components Yr 1'!G7) -> 0 | H7: =IF('Components Yr 1'!H7=0,0,'Components Yr 1'!H7) -> 0 | I7: =IF('Components Yr 1'!I7=0,0,'Components Yr 1'!I7) -> 0 | J7: =IF('Components Yr 1'!J7=0,0,'Components Yr 1'!J7) -> 0 | K7: =IF('Components Yr 1'!K7=0,0,'Components Yr 1'!K7) -> 0 | R7: =IF(SUMPRODUCT((E7:Q7)*1)=0,0,E7*INDEX(Hours!M:M,MATCH(C7,Hours!$A:$A,0))+F7*INDEX(Hours!B:B,MATCH(C7,Hours!$A:$A,0))+G7*INDEX(Hours!C:C,MATCH(C7,Hours!$A:$A,0))+H7*INDEX(Hours!D:D,MATCH(C7,Hours!$A:$A,0))+I7*INDEX(Hours!E:E,MATCH(C7,Hours!$A:$A,0))+J7*INDEX(Hours!F:F,MATCH(C7,Hours!$A:$A,0))+K7*INDEX(Hours!G:G,MATCH(C7,Hours!$A:$A,0))) -> 0 | S7: =MAX(E7+F7,G7,H7,I7,J7,K7,L7,M7,N7,O7,P7,Q7) -> 0
A8: ='Bldgs & Rooms'!$A$2 -> Main Bldg. | B8: ='Bldgs & Rooms'!$B$2 -> 0 | C8: =Hours!$A$8 -> Panelboard-Single Cover > 400A (Distribution Panel) | D8: =MAX(E8+F8,G8,H8,I8,J8,K8,L8,M8,N8,O8,P8,Q8) -> 0 | E8: =IF('Components Yr 1'!E8=0,0,'Components Yr 1'!E8) -> 0 | F8: =IF('Components Yr 1'!F8=0,0,'Components Yr 1'!F8) -> 0 | G8: =IF('Components Yr 1'!G8=0,0,'Components Yr 1'!G8) -> 0 | H8: =IF('Components Yr 1'!H8=0,0,'Components Yr 1'!H8) -> 0 | I8: =IF('Components Yr 1'!I8=0,0,'Components Yr 1'!I8) -> 0 | J8: =IF('Components Yr 1'!J8=0,0,'Components Yr 1'!J8) -> 0 | K8: =IF('Components Yr 1'!K8=0,0,'Components Yr 1'!K8) -> 0 | O8: =IF('Components Yr 1'!O8=0,0,'Components Yr 1'!O8) -> 0 | R8: =IF(SUMPRODUCT((E8:Q8)*1)=0,0,E8*INDEX(Hours!M:M,MATCH(C8,Hours!$A:$A,0))+F8*INDEX(Hours!B:B,MATCH(C8,Hours!$A:$A,0))+G8*INDEX(Hours!C:C,MATCH(C8,Hours!$A:$A,0))+H8*INDEX(Hours!D:D,MATCH(C8,Hours!$A:$A,0))+I8*INDEX(Hours!E:E,MATCH(C8,Hours!$A:$A,0))+J8*INDEX(Hours!F:F,MATCH(C8,Hours!$A:$A,0))+K8*INDEX(Hours!G:G,MATCH(C8,Hours!$A:$A,0))+O8*INDEX(Hours!K:K,MATCH(C8,Hours!$A:$A,0))) -> 0 | S8: =MAX(E8+F8,G8,H8,I8,J8,K8,L8,M8,N8,O8,P8,Q8) -> 0
A9: ='Bldgs & Rooms'!$A$2 -> Main Bldg. | B9: ='Bldgs & Rooms'!$B$2 -> 0 | C9: =Hours!$A$9 -> Panelboard-Single Cover < 400A (Branch Ckt Panel) | D9: =MAX(E9+F9,G9,H9,I9,J9,K9,L9,M9,N9,O9,P9,Q9) -> 0 | E9: =IF('Components Yr 1'!E9=0,0,'Components Yr 1'!E9) -> 0 | F9: =IF('Components Yr 1'!F9=0,0,'Components Yr 1'!F9) -> 0 | G9: =IF('Components Yr 1'!G9=0,0,'Components Yr 1'!G9) -> 0 | H9: =IF('Components Yr 1'!H9=0,0,'Components Yr 1'!H9) -> 0 | I9: =IF('Components Yr 1'!I9=0,0,'Components Yr 1'!I9) -> 0 | J9: =IF('Components Yr 1'!J9=0,0,'Components Yr 1'!J9) -> 0 | O9: =IF('Components Yr 1'!O9=0,0,'Components Yr 1'!O9) -> 0 | R9: =IF(SUMPRODUCT((E9:Q9)*1)=0,0,E9*INDEX(Hours!M:M,MATCH(C9,Hours!$A:$A,0))+F9*INDEX(Hours!B:B,MATCH(C9,Hours!$A:$A,0))+G9*INDEX(Hours!C:C,MATCH(C9,Hours!$A:$A,0))+H9*INDEX(Hours!D:D,MATCH(C9,Hours!$A:$A,0))+I9*INDEX(Hours!E:E,MATCH(C9,Hours!$A:$A,0))+J9*INDEX(Hours!F:F,MATCH(C9,Hours!$A:$A,0))+O9*INDEX(Hours!K:K,MATCH(C9,Hours!$A:$A,0))) -> 0 | S9: =MAX(E9+F9,G9,H9,I9,J9,K9,L9,M9,N9,O9,P9,Q9) -> 0
A10: ='Bldgs & Rooms'!$A$2 -> Main Bldg. | B10: ='Bldgs & Rooms'!$B$2 -> 0 | C10: =Hours!$A$10 -> Motor Control Center (MCC-Per Vertical Section) | D10: =MAX(E10+F10,G10,H10,I10,J10,K10,L10,M10,N10,O10,P10,Q10) -> 0 | E10: =IF('Components Yr 1'!E10=0,0,'Components Yr 1'!E10) -> 0 | F10: =IF('Components Yr 1'!F10=0,0,'Components Yr 1'!F10) -> 0 | G10: =IF('Components Yr 1'!G10=0,0,'Components Yr 1'!G10) -> 0 | H10: =IF('Components Yr 1'!H10=0,0,'Components Yr 1'!H10) -> 0 | I10: =IF('Components Yr 1'!I10=0,0,'Components Yr 1'!I10) -> 0 | J10: =IF('Components Yr 1'!J10=0,0,'Components Yr 1'!J10) -> 0 | O10: =IF('Components Yr 1'!O10=0,0,'Components Yr 1'!O10) -> 0 | R10: =IF(SUMPRODUCT((E10:Q10)*1)=0,0,E10*INDEX(Hours!M:M,MATCH(C10,Hours!$A:$A,0))+F10*INDEX(Hours!B:B,MATCH(C10,Hours!$A:$A,0))+G10*INDEX(Hours!C:C,MATCH(C10,Hours!$A:$A,0))+H10*INDEX(Hours!D:D,MATCH(C10,Hours!$A:$A,0))+I10*INDEX(Hours!E:E,MATCH(C10,Hours!$A:$A,0))+J10*INDEX(Hours!F:F,MATCH(C10,Hours!$A:$A,0))+O10*INDEX(Hours!K:K,MATCH(C10,Hours!$A:$A,0))) -> 0 | S10: =MAX(E10+F10,G10,H10,I10,J10,K10,L10,M10,N10,O10,P10,Q10) -> 0
A11: ='Bldgs & Rooms'!$A$2 -> Main Bldg. | B11: ='Bldgs & Rooms'!$B$2 -> 0 | C11: =Hours!$A$11 -> MCC: Combination Motor Starters | D11: =MAX(E11+F11,G11,H11,I11,J11,K11,L11,M11,N11,O11,P11,Q11) -> 0 | E11: =IF('Components Yr 1'!E11=0,0,'Components Yr 1'!E11) -> 0 | F11: =IF('Components Yr 1'!F11=0,0,'Components Yr 1'!F11) -> 0 | G11: =IF('Components Yr 1'!G11=0,0,'Components Yr 1'!G11) -> 0 | H11: =IF('Components Yr 1'!H11=0,0,'Components Yr 1'!H11) -> 0 | I11: =IF('Components Yr 1'!I11=0,0,'Components Yr 1'!I11) -> 0 | J11: =IF('Components Yr 1'!J11=0,0,'Components Yr 1'!J11) -> 0 | K11: =IF('Components Yr 1'!K11=0,0,'Components Yr 1'!K11) -> 0 | O11: =IF('Components Yr 1'!O11=0,0,'Components Yr 1'!O11) -> 0 | R11: =IF(SUMPRODUCT((E11:Q11)*1)=0,0,E11*INDEX(Hours!M:M,MATCH(C11,Hours!$A:$A,0))+F11*INDEX(Hours!B:B,MATCH(C11,Hours!$A:$A,0))+G11*INDEX(Hours!C:C,MATCH(C11,Hours!$A:$A,0))+H11*INDEX(Hours!D:D,MATCH(C11,Hours!$A:$A,0))+I11*INDEX(Hours!E:E,MATCH(C11,Hours!$A:$A,0))+J11*INDEX(Hours!F:F,MATCH(C11,Hours!$A:$A,0))+K11*INDEX(Hours!G:G,MATCH(C11,Hours!$A:$A,0))+O11*INDEX(Hours!K:K,MATCH(C11,Hours!$A:$A,0))) -> 0 | S11: =MAX(E11+F11,G11,H11,I11,J11,K11,L11,M11,N11,O11,P11,Q11) -> 0
A12: ='Bldgs & Rooms'!$A$2 -> Main Bldg. | B12: ='Bldgs & Rooms'!$B$2 -> 0 | C12: =Hours!$A$12 -> MCC: Molded Case Breaker | D12: =MAX(E12+F12,G12,H12,I12,J12,K12,L12,M12,N12,O12,P12,Q12) -> 0 | E12: =IF('Components Yr 1'!E12=0,0,'Components Yr 1'!E12) -> 0 | F12: =IF('Components Yr 1'!F12=0,0,'Components Yr 1'!F12) -> 0 | G12: =IF('Components Yr 1'!G12=0,0,'Components Yr 1'!G12) -> 0 | H12: =IF('Components Yr 1'!H12=0,0,'Components Yr 1'!H12) -> 0 | I12: =IF('Components Yr 1'!I12=0,0,'Components Yr 1'!I12) -> 0 | J12: =IF('Components Yr 1'!J12=0,0,'Components Yr 1'!J12) -> 0 | K12: =IF('Components Yr 1'!K12=0,0,'Components Yr 1'!K12) -> 0 | R12: =IF(SUMPRODUCT((E12:Q12)*1)=0,0,E12*INDEX(Hours!M:M,MATCH(C12,Hours!$A:$A,0))+F12*INDEX(Hours!B:B,MATCH(C12,Hours!$A:$A,0))+G12*INDEX(Hours!C:C,MATCH(C12,Hours!$A:$A,0))+H12*INDEX(Hours!D:D,MATCH(C12,Hours!$A:$A,0))+I12*INDEX(Hours!E:E,MATCH(C12,Hours!$A:$A,0))+J12*INDEX(Hours!F:F,MATCH(C12,Hours!$A:$A,0))+K12*INDEX(Hours!G:G,MATCH(C12,Hours!$A:$A,0))) -> 0 | S12: =MAX(E12+F12,G12,H12,I12,J12,K12,L12,M12,N12,O12,P12,Q12) -> 0
A13: ='Bldgs & Rooms'!$A$2 -> Main Bldg. | B13: ='Bldgs & Rooms'!$B$2 -> 0 | C13: =Hours!$A$13 -> MCC: Individual Disconnect Switch | D13: =MAX(E13+F13,G13,H13,I13,J13,K13,L13,M13,N13,O13,P13,Q13) -> 0 | E13: =IF('Components Yr 1'!E13=0,0,'Components Yr 1'!E13) -> 0 | F13: =IF('Components Yr 1'!F13=0,0,'Components Yr 1'!F13) -> 0 | G13: =IF('Components Yr 1'!G13=0,0,'Components Yr 1'!G13) -> 0 | H13: =IF('Components Yr 1'!H13=0,0,'Components Yr 1'!H13) -> 0 | I13: =IF('Components Yr 1'!I13=0,0,'Components Yr 1'!I13) -> 0 | J13: =IF('Components Yr 1'!J13=0,0,'Components Yr 1'!J13) -> 0 | R13: =IF(SUMPRODUCT((E13:Q13)*1)=0,0,E13*INDEX(Hours!M:M,MATCH(C13,Hours!$A:$A,0))+F13*INDEX(Hours!B:B,MATCH(C13,Hours!$A:$A,0))+G13*INDEX(Hours!C:C,MATCH(C13,Hours!$A:$A,0))+H13*INDEX(Hours!D:D,MATCH(C13,Hours!$A:$A,0))+I13*INDEX(Hours!E:E,MATCH(C13,Hours!$A:$A,0))+J13*INDEX(Hours!F:F,MATCH(C13,Hours!$A:$A,0))) -> 0 | S13: =MAX(E13+F13,G13,H13,I13,J13,K13,L13,M13,N13,O13,P13,Q13) -> 0
A14: ='Bldgs & Rooms'!$A$2 -> Main Bldg. | B14: ='Bldgs & Rooms'!$B$2 -> 0 | C14: =Hours!$A$14 -> Motor Control Panel (MCP) | D14: =MAX(E14+F14,G14,H14,I14,J14,K14,L14,M14,N14,O14,P14,Q14) -> 0 | E14: =IF('Components Yr 1'!E14=0,0,'Components Yr 1'!E14) -> 0 | F14: =IF('Components Yr 1'!F14=0,0,'Components Yr 1'!F14) -> 0 | G14: =IF('Components Yr 1'!G14=0,0,'Components Yr 1'!G14) -> 0 | H14: =IF('Components Yr 1'!H14=0,0,'Components Yr 1'!H14) -> 0 | I14: =IF('Components Yr 1'!I14=0,0,'Components Yr 1'!I14) -> 0 | J14: =IF('Components Yr 1'!J14=0,0,'Components Yr 1'!J14) -> 0 | O14: =IF('Components Yr 1'!O14=0,0,'Components Yr 1'!O14) -> 0 | R14: =IF(SUMPRODUCT((E14:Q14)*1)=0,0,E14*INDEX(Hours!M:M,MATCH(C14,Hours!$A:$A,0))+F14*INDEX(Hours!B:B,MATCH(C14,Hours!$A:$A,0))+G14*INDEX(Hours!C:C,MATCH(C14,Hours!$A:$A,0))+H14*INDEX(Hours!D:D,MATCH(C14,Hours!$A:$A,0))+I14*INDEX(Hours!E:E,MATCH(C14,Hours!$A:$A,0))+J14*INDEX(Hours!F:F,MATCH(C14,Hours!$A:$A,0))+O14*INDEX(Hours!K:K,MATCH(C14,Hours!$A:$A,0))) -> 0 | S14: =MAX(E14+F14,G14,H14,I14,J14,K14,L14,M14,N14,O14,P14,Q14) -> 0
A15: ='Bldgs & Rooms'!$A$2 -> Main Bldg. | B15: ='Bldgs & Rooms'!$B$2 -> 0 | C15: =Hours!$A$15 -> VFD Motor Control Panel (VFD-MCP) | D15: =MAX(E15+F15,G15,H15,I15,J15,K15,L15,M15,N15,O15,P15,Q15) -> 0 | E15: =IF('Components Yr 1'!E15=0,0,'Components Yr 1'!E15) -> 0 | F15: =IF('Components Yr 1'!F15=0,0,'Components Yr 1'!F15) -> 0 | G15: =IF('Components Yr 1'!G15=0,0,'Components Yr 1'!G15) -> 0 | H15: =IF('Components Yr 1'!H15=0,0,'Components Yr 1'!H15) -> 0 | I15: =IF('Components Yr 1'!I15=0,0,'Components Yr 1'!I15) -> 0 | J15: =IF('Components Yr 1'!J15=0,0,'Components Yr 1'!J15) -> 0 | O15: =IF('Components Yr 1'!O15=0,0,'Components Yr 1'!O15) -> 0 | R15: =IF(SUMPRODUCT((E15:Q15)*1)=0,0,E15*INDEX(Hours!M:M,MATCH(C15,Hours!$A:$A,0))+F15*INDEX(Hours!B:B,MATCH(C15,Hours!$A:$A,0))+G15*INDEX(Hours!C:C,MATCH(C15,Hours!$A:$A,0))+H15*INDEX(Hours!D:D,MATCH(C15,Hours!$A:$A,0))+I15*INDEX(Hours!E:E,MATCH(C15,Hours!$A:$A,0))+J15*INDEX(Hours!F:F,MATCH(C15,Hours!$A:$A,0))+O15*INDEX(Hours!K:K,MATCH(C15,Hours!$A:$A,0))) -> 0 | S15: =MAX(E15+F15,G15,H15,I15,J15,K15,L15,M15,N15,O15,P15,Q15) -> 0
A16: ='Bldgs & Rooms'!$A$2 -> Main Bldg. | B16: ='Bldgs & Rooms'!$B$2 -> 0 | C16: =Hours!$A$16 -> Individual Disconnect Switch > 100A | D16: =MAX(E16+F16,G16,H16,I16,J16,K16,L16,M16,N16,O16,P16,Q16) -> 0 | E16: =IF('Components Yr 1'!E16=0,0,'Components Yr 1'!E16) -> 0 | F16: =IF('Components Yr 1'!F16=0,0,'Components Yr 1'!F16) -> 0 | G16: =IF('Components Yr 1'!G16=0,0,'Components Yr 1'!G16) -> 0 | H16: =IF('Components Yr 1'!H16=0,0,'Components Yr 1'!H16) -> 0 | I16: =IF('Components Yr 1'!I16=0,0,'Components Yr 1'!I16) -> 0 | J16: =IF('Components Yr 1'!J16=0,0,'Components Yr 1'!J16) -> 0 | K16: =IF('Components Yr 1'!K16=0,0,'Components Yr 1'!K16) -> 0 | R16: =IF(SUMPRODUCT((E16:Q16)*1)=0,0,E16*INDEX(Hours!M:M,MATCH(C16,Hours!$A:$A,0))+F16*INDEX(Hours!B:B,MATCH(C16,Hours!$A:$A,0))+G16*INDEX(Hours!C:C,MATCH(C16,Hours!$A:$A,0))+H16*INDEX(Hours!D:D,MATCH(C16,Hours!$A:$A,0))+I16*INDEX(Hours!E:E,MATCH(C16,Hours!$A:$A,0))+J16*INDEX(Hours!F:F,MATCH(C16,Hours!$A:$A,0))+K16*INDEX(Hours!G:G,MATCH(C16,Hours!$A:$A,0))) -> 0 | S16: =MAX(E16+F16,G16,H16,I16,J16,K16,L16,M16,N16,O16,P16,Q16) -> 0
A17: ='Bldgs & Rooms'!$A$2 -> Main Bldg. | B17: ='Bldgs & Rooms'!$B$2 -> 0 | C17: =Hours!$A$17 -> Individual Molded Case Breaker > 100A | D17: =MAX(E17+F17,G17,H17,I17,J17,K17,L17,M17,N17,O17,P17,Q17) -> 0 | E17: =IF('Components Yr 1'!E17=0,0,'Components Yr 1'!E17) -> 0 | F17: =IF('Components Yr 1'!F17=0,0,'Components Yr 1'!F17) -> 0 | G17: =IF('Components Yr 1'!G17=0,0,'Components Yr 1'!G17) -> 0 | H17: =IF('Components Yr 1'!H17=0,0,'Components Yr 1'!H17) -> 0 | I17: =IF('Components Yr 1'!I17=0,0,'Components Yr 1'!I17) -> 0 | J17: =IF('Components Yr 1'!J17=0,0,'Components Yr 1'!J17) -> 0 | K17: =IF('Components Yr 1'!K17=0,0,'Components Yr 1'!K17) -> 0 | R17: =IF(SUMPRODUCT((E17:Q17)*1)=0,0,E17*INDEX(Hours!M:M,MATCH(C17,Hours!$A:$A,0))+F17*INDEX(Hours!B:B,MATCH(C17,Hours!$A:$A,0))+G17*INDEX(Hours!C:C,MATCH(C17,Hours!$A:$A,0))+H17*INDEX(Hours!D:D,MATCH(C17,Hours!$A:$A,0))+I17*INDEX(Hours!E:E,MATCH(C17,Hours!$A:$A,0))+J17*INDEX(Hours!F:F,MATCH(C17,Hours!$A:$A,0))+K17*INDEX(Hours!G:G,MATCH(C17,Hours!$A:$A,0))) -> 0 | S17: =MAX(E17+F17,G17,H17,I17,J17,K17,L17,M17,N17,O17,P17,Q17) -> 0
A18: ='Bldgs & Rooms'!$A$2 -> Main Bldg. | B18: ='Bldgs & Rooms'!$B$2 -> 0 | C18: =Hours!$A$18 -> Individual Combination Motor Starter > 100A | D18: =MAX(E18+F18,G18,H18,I18,J18,K18,L18,M18,N18,O18,P18,Q18) -> 0 | E18: =IF('Components Yr 1'!E18=0,0,'Components Yr 1'!E18) -> 0 | F18: =IF('Components Yr 1'!F18=0,0,'Components Yr 1'!F18) -> 0 | G18: =IF('Components Yr 1'!G18=0,0,'Components Yr 1'!G18) -> 0 | H18: =IF('Components Yr 1'!H18=0,0,'Components Yr 1'!H18) -> 0 | I18: =IF('Components Yr 1'!I18=0,0,'Components Yr 1'!I18) -> 0 | J18: =IF('Components Yr 1'!J18=0,0,'Components Yr 1'!J18) -> 0 | K18: =IF('Components Yr 1'!K18=0,0,'Components Yr 1'!K18) -> 0 | R18: =IF(SUMPRODUCT((E18:Q18)*1)=0,0,E18*INDEX(Hours!M:M,MATCH(C18,Hours!$A:$A,0))+F18*INDEX(Hours!B:B,MATCH(C18,Hours!$A:$A,0))+G18*INDEX(Hours!C:C,MATCH(C18,Hours!$A:$A,0))+H18*INDEX(Hours!D:D,MATCH(C18,Hours!$A:$A,0))+I18*INDEX(Hours!E:E,MATCH(C18,Hours!$A:$A,0))+J18*INDEX(Hours!F:F,MATCH(C18,Hours!$A:$A,0))+K18*INDEX(Hours!G:G,MATCH(C18,Hours!$A:$A,0))) -> 0 | S18: =MAX(E18+F18,G18,H18,I18,J18,K18,L18,M18,N18,O18,P18,Q18) -> 0
A19: ='Bldgs & Rooms'!$A$2 -> Main Bldg. | B19: ='Bldgs & Rooms'!$B$2 -> 0 | C19: =Hours!$A$19 -> Oil Filled Transformer - 5kV-15kV Primary - Any Size (Pad Mounted) | D19: =MAX(E19+F19,G19,H19,I19,J19,K19,L19,M19,N19,O19,P19,Q19) -> 0 | E19: =IF('Components Yr 1'!E19=0,0,'Components Yr 1'!E19) -> 0 | F19: =IF('Components Yr 1'!F19=0,0,'Components Yr 1'!F19) -> 0 | G19: =IF('Components Yr 1'!G19=0,0,'Components Yr 1'!G19) -> 0 | H19: =IF('Components Yr 1'!H19=0,0,'Components Yr 1'!H19) -> 0 | I19: =IF('Components Yr 1'!I19=0,0,'Components Yr 1'!I19) -> 0 | J19: =IF('Components Yr 1'!J19=0,0,'Components Yr 1'!J19) -> 0 | M19: =IF('Components Yr 1'!M19=0,0,'Components Yr 1'!M19) -> 0 | N19: =IF('Components Yr 1'!N19=0,0,'Components Yr 1'!N19) -> 0 | P19: =IF('Components Yr 1'!P19=0,0,'Components Yr 1'!P19) -> 0 | R19: =IF(SUMPRODUCT((E19:Q19)*1)=0,0,E19*INDEX(Hours!M:M,MATCH(C19,Hours!$A:$A,0))+F19*INDEX(Hours!B:B,MATCH(C19,Hours!$A:$A,0))+G19*INDEX(Hours!C:C,MATCH(C19,Hours!$A:$A,0))+H19*INDEX(Hours!D:D,MATCH(C19,Hours!$A:$A,0))+I19*INDEX(Hours!E:E,MATCH(C19,Hours!$A:$A,0))+J19*INDEX(Hours!F:F,MATCH(C19,Hours!$A:$A,0))+M19*INDEX(Hours!I:I,MATCH(C19,Hours!$A:$A,0))+N19*INDEX(Hours!J:J,MATCH(C19,Hours!$A:$A,0))+P19*INDEX(Hours!L:L,MATCH(C19,Hours!$A:$A,0))) -> 0 | S19: =MAX(E19+F19,G19,H19,I19,J19,K19,L19,M19,N19,O19,P19,Q19) -> 0
A20: ='Bldgs & Rooms'!$A$2 -> Main Bldg. | B20: ='Bldgs & Rooms'!$B$2 -> 0 | C20: =Hours!$A$20 -> Oil Filled Transformer - > 15kV Primary (Substation Class) | D20: =MAX(E20+F20,G20,H20,I20,J20,K20,L20,M20,N20,O20,P20,Q20) -> 0 | E20: =IF('Components Yr 1'!E20=0,0,'Components Yr 1'!E20) -> 0 | F20: =IF('Components Yr 1'!F20=0,0,'Components Yr 1'!F20) -> 0 | G20: =IF('Components Yr 1'!G20=0,0,'Components Yr 1'!G20) -> 0 | H20: =IF('Components Yr 1'!H20=0,0,'Components Yr 1'!H20) -> 0 | I20: =IF('Components Yr 1'!I20=0,0,'Components Yr 1'!I20) -> 0 | J20: =IF('Components Yr 1'!J20=0,0,'Components Yr 1'!J20) -> 0 | M20: =IF('Components Yr 1'!M20=0,0,'Components Yr 1'!M20) -> 0 | N20: =IF('Components Yr 1'!N20=0,0,'Components Yr 1'!N20) -> 0 | P20: =IF('Components Yr 1'!P20=0,0,'Components Yr 1'!P20) -> 0 | R20: =IF(SUMPRODUCT((E20:Q20)*1)=0,0,E20*INDEX(Hours!M:M,MATCH(C20,Hours!$A:$A,0))+F20*INDEX(Hours!B:B,MATCH(C20,Hours!$A:$A,0))+G20*INDEX(Hours!C:C,MATCH(C20,Hours!$A:$A,0))+H20*INDEX(Hours!D:D,MATCH(C20,Hours!$A:$A,0))+I20*INDEX(Hours!E:E,MATCH(C20,Hours!$A:$A,0))+J20*INDEX(Hours!F:F,MATCH(C20,Hours!$A:$A,0))+M20*INDEX(Hours!I:I,MATCH(C20,Hours!$A:$A,0))+N20*INDEX(Hours!J:J,MATCH(C20,Hours!$A:$A,0))+P20*INDEX(Hours!L:L,MATCH(C20,Hours!$A:$A,0))) -> 0 | S20: =MAX(E20+F20,G20,H20,I20,J20,K20,L20,M20,N20,O20,P20,Q20) -> 0
A21: ='Bldgs & Rooms'!$A$2 -> Main Bldg. | B21: ='Bldgs & Rooms'!$B$2 -> 0 | C21: =Hours!$A$21 -> Dry Type Transformer - < 480V Primary - Any Size kVA | D21: =MAX(E21+F21,G21,H21,I21,J21,K21,L21,M21,N21,O21,P21,Q21) -> 0 | E21: =IF('Components Yr 1'!E21=0,0,'Components Yr 1'!E21) -> 0 | F21: =IF('Components Yr 1'!F21=0,0,'Components Yr 1'!F21) -> 0 | G21: =IF('Components Yr 1'!G21=0,0,'Components Yr 1'!G21) -> 0 | H21: =IF('Components Yr 1'!H21=0,0,'Components Yr 1'!H21) -> 0 | I21: =IF('Components Yr 1'!I21=0,0,'Components Yr 1'!I21) -> 0 | J21: =IF('Components Yr 1'!J21=0,0,'Components Yr 1'!J21) -> 0 | M21: =IF('Components Yr 1'!M21=0,0,'Components Yr 1'!M21) -> 0 | N21: =IF('Components Yr 1'!N21=0,0,'Components Yr 1'!N21) -> 0 | R21: =IF(SUMPRODUCT((E21:Q21)*1)=0,0,E21*INDEX(Hours!M:M,MATCH(C21,Hours!$A:$A,0))+F21*INDEX(Hours!B:B,MATCH(C21,Hours!$A:$A,0))+G21*INDEX(Hours!C:C,MATCH(C21,Hours!$A:$A,0))+H21*INDEX(Hours!D:D,MATCH(C21,Hours!$A:$A,0))+I21*INDEX(Hours!E:E,MATCH(C21,Hours!$A:$A,0))+J21*INDEX(Hours!F:F,MATCH(C21,Hours!$A:$A,0))+M21*INDEX(Hours!I:I,MATCH(C21,Hours!$A:$A,0))+N21*INDEX(Hours!J:J,MATCH(C21,Hours!$A:$A,0))) -> 0 | S21: =MAX(E21+F21,G21,H21,I21,J21,K21,L21,M21,N21,O21,P21,Q21) -> 0
A22: ='Bldgs & Rooms'!$A$2 -> Main Bldg. | B22: ='Bldgs & Rooms'!$B$2 -> 0 | C22: =Hours!$A$22 -> Power Factor Correction Capacitors | D22: =MAX(E22+F22,G22,H22,I22,J22,K22,L22,M22,N22,O22,P22,Q22) -> 0 | E22: =IF('Components Yr 1'!E22=0,0,'Components Yr 1'!E22) -> 0 | F22: =IF('Components Yr 1'!F22=0,0,'Components Yr 1'!F22) -> 0 | G22: =IF('Components Yr 1'!G22=0,0,'Components Yr 1'!G22) -> 0 | H22: =IF('Components Yr 1'!H22=0,0,'Components Yr 1'!H22) -> 0 | I22: =IF('Components Yr 1'!I22=0,0,'Components Yr 1'!I22) -> 0 | J22: =IF('Components Yr 1'!J22=0,0,'Components Yr 1'!J22) -> 0 | R22: =IF(SUMPRODUCT((E22:Q22)*1)=0,0,E22*INDEX(Hours!M:M,MATCH(C22,Hours!$A:$A,0))+F22*INDEX(Hours!B:B,MATCH(C22,Hours!$A:$A,0))+G22*INDEX(Hours!C:C,MATCH(C22,Hours!$A:$A,0))+H22*INDEX(Hours!D:D,MATCH(C22,Hours!$A:$A,0))+I22*INDEX(Hours!E:E,MATCH(C22,Hours!$A:$A,0))+J22*INDEX(Hours!F:F,MATCH(C22,Hours!$A:$A,0))) -> 0 | S22: =MAX(E22+F22,G22,H22,I22,J22,K22,L22,M22,N22,O22,P22,Q22) -> 0
A23: ='Bldgs & Rooms'!$A$2 -> Main Bldg. | B23: ='Bldgs & Rooms'!$B$2 -> 0 | C23: =Hours!$A$23 -> Lighting Contactor > 100A | D23: =MAX(E23+F23,G23,H23,I23,J23,K23,L23,M23,N23,O23,P23,Q23) -> 0 | E23: =IF('Components Yr 1'!E23=0,0,'Components Yr 1'!E23) -> 0 | F23: =IF('Components Yr 1'!F23=0,0,'Components Yr 1'!F23) -> 0 | G23: =IF('Components Yr 1'!G23=0,0,'Components Yr 1'!G23) -> 0 | H23: =IF('Components Yr 1'!H23=0,0,'Components Yr 1'!H23) -> 0 | I23: =IF('Components Yr 1'!I23=0,0,'Components Yr 1'!I23) -> 0 | J23: =IF('Components Yr 1'!J23=0,0,'Components Yr 1'!J23) -> 0 | R23: =IF(SUMPRODUCT((E23:Q23)*1)=0,0,E23*INDEX(Hours!M:M,MATCH(C23,Hours!$A:$A,0))+F23*INDEX(Hours!B:B,MATCH(C23,Hours!$A:$A,0))+G23*INDEX(Hours!C:C,MATCH(C23,Hours!$A:$A,0))+H23*INDEX(Hours!D:D,MATCH(C23,Hours!$A:$A,0))+I23*INDEX(Hours!E:E,MATCH(C23,Hours!$A:$A,0))+J23*INDEX(Hours!F:F,MATCH(C23,Hours!$A:$A,0))) -> 0 | S23: =MAX(E23+F23,G23,H23,I23,J23,K23,L23,M23,N23,O23,P23,Q23) -> 0
A24: ='Bldgs & Rooms'!$A$2 -> Main Bldg. | B24: ='Bldgs & Rooms'!$B$2 -> 0 | C24: =Hours!$A$24 -> Power Distribution Unit (PDU) | D24: =MAX(E24+F24,G24,H24,I24,J24,K24,L24,M24,N24,O24,P24,Q24) -> 0 | E24: =IF('Components Yr 1'!E24=0,0,'Components Yr 1'!E24) -> 0 | F24: =IF('Components Yr 1'!F24=0,0,'Components Yr 1'!F24) -> 0 | G24: =IF('Components Yr 1'!G24=0,0,'Components Yr 1'!G24) -> 0 | H24: =IF('Components Yr 1'!H24=0,0,'Components Yr 1'!H24) -> 0 | I24: =IF('Components Yr 1'!I24=0,0,'Components Yr 1'!I24) -> 0 | J24: =IF('Components Yr 1'!J24=0,0,'Components Yr 1'!J24) -> 0 | R24: =IF(SUMPRODUCT((E24:Q24)*1)=0,0,E24*INDEX(Hours!M:M,MATCH(C24,Hours!$A:$A,0))+F24*INDEX(Hours!B:B,MATCH(C24,Hours!$A:$A,0))+G24*INDEX(Hours!C:C,MATCH(C24,Hours!$A:$A,0))+H24*INDEX(Hours!D:D,MATCH(C24,Hours!$A:$A,0))+I24*INDEX(Hours!E:E,MATCH(C24,Hours!$A:$A,0))+J24*INDEX(Hours!F:F,MATCH(C24,Hours!$A:$A,0))) -> 0 | S24: =MAX(E24+F24,G24,H24,I24,J24,K24,L24,M24,N24,O24,P24,Q24) -> 0
A25: ='Bldgs & Rooms'!$A$2 -> Main Bldg. | B25: ='Bldgs & Rooms'!$B$2 -> 0 | C25: =Hours!$A$25 -> Wire Trough, Gutter, or Large Junction Boxes | D25: =MAX(E25+F25,G25,H25,I25,J25,K25,L25,M25,N25,O25,P25,Q25) -> 0 | E25: =IF('Components Yr 1'!E25=0,0,'Components Yr 1'!E25) -> 0 | F25: =IF('Components Yr 1'!F25=0,0,'Components Yr 1'!F25) -> 0 | G25: =IF('Components Yr 1'!G25=0,0,'Components Yr 1'!G25) -> 0 | H25: =IF('Components Yr 1'!H25=0,0,'Components Yr 1'!H25) -> 0 | I25: =IF('Components Yr 1'!I25=0,0,'Components Yr 1'!I25) -> 0 | J25: =IF('Components Yr 1'!J25=0,0,'Components Yr 1'!J25) -> 0 | R25: =IF(SUMPRODUCT((E25:Q25)*1)=0,0,E25*INDEX(Hours!M:M,MATCH(C25,Hours!$A:$A,0))+F25*INDEX(Hours!B:B,MATCH(C25,Hours!$A:$A,0))+G25*INDEX(Hours!C:C,MATCH(C25,Hours!$A:$A,0))+H25*INDEX(Hours!D:D,MATCH(C25,Hours!$A:$A,0))+I25*INDEX(Hours!E:E,MATCH(C25,Hours!$A:$A,0))+J25*INDEX(Hours!F:F,MATCH(C25,Hours!$A:$A,0))) -> 0 | S25: =MAX(E25+F25,G25,H25,I25,J25,K25,L25,M25,N25,O25,P25,Q25) -> 0
A26: ='Bldgs & Rooms'!$A$2 -> Main Bldg. | B26: ='Bldgs & Rooms'!$B$2 -> 0 | C26: =Hours!$A$26 -> Bus Duct - Vertical or Horizontal (Per 10' section) | D26: =MAX(E26+F26,G26,H26,I26,J26,K26,L26,M26,N26,O26,P26,Q26) -> 0 | E26: =IF('Components Yr 1'!E26=0,0,'Components Yr 1'!E26) -> 0 | F26: =IF('Components Yr 1'!F26=0,0,'Components Yr 1'!F26) -> 0 | G26: =IF('Components Yr 1'!G26=0,0,'Components Yr 1'!G26) -> 0 | H26: =IF('Components Yr 1'!H26=0,0,'Components Yr 1'!H26) -> 0 | I26: =IF('Components Yr 1'!I26=0,0,'Components Yr 1'!I26) -> 0 | J26: =IF('Components Yr 1'!J26=0,0,'Components Yr 1'!J26) -> 0 | R26: =IF(SUMPRODUCT((E26:Q26)*1)=0,0,E26*INDEX(Hours!M:M,MATCH(C26,Hours!$A:$A,0))+F26*INDEX(Hours!B:B,MATCH(C26,Hours!$A:$A,0))+G26*INDEX(Hours!C:C,MATCH(C26,Hours!$A:$A,0))+H26*INDEX(Hours!D:D,MATCH(C26,Hours!$A:$A,0))+I26*INDEX(Hours!E:E,MATCH(C26,Hours!$A:$A,0))+J26*INDEX(Hours!F:F,MATCH(C26,Hours!$A:$A,0))) -> 0 | S26: =MAX(E26+F26,G26,H26,I26,J26,K26,L26,M26,N26,O26,P26,Q26) -> 0
A27: ='Bldgs & Rooms'!$A$2 -> Main Bldg. | B27: ='Bldgs & Rooms'!$B$2 -> 0 | C27: =Hours!$A$27 -> Automatic Transfer Switch (ATS) > 100A | D27: =MAX(E27+F27,G27,H27,I27,J27,K27,L27,M27,N27,O27,P27,Q27) -> 0 | E27: =IF('Components Yr 1'!E27=0,0,'Components Yr 1'!E27) -> 0 | F27: =IF('Components Yr 1'!F27=0,0,'Components Yr 1'!F27) -> 0 | G27: =IF('Components Yr 1'!G27=0,0,'Components Yr 1'!G27) -> 0 | H27: =IF('Components Yr 1'!H27=0,0,'Components Yr 1'!H27) -> 0 | I27: =IF('Components Yr 1'!I27=0,0,'Components Yr 1'!I27) -> 0 | J27: =IF('Components Yr 1'!J27=0,0,'Components Yr 1'!J27) -> 0 | R27: =IF(SUMPRODUCT((E27:Q27)*1)=0,0,E27*INDEX(Hours!M:M,MATCH(C27,Hours!$A:$A,0))+F27*INDEX(Hours!B:B,MATCH(C27,Hours!$A:$A,0))+G27*INDEX(Hours!C:C,MATCH(C27,Hours!$A:$A,0))+H27*INDEX(Hours!D:D,MATCH(C27,Hours!$A:$A,0))+I27*INDEX(Hours!E:E,MATCH(C27,Hours!$A:$A,0))+J27*INDEX(Hours!F:F,MATCH(C27,Hours!$A:$A,0))) -> 0 | S27: =MAX(E27+F27,G27,H27,I27,J27,K27,L27,M27,N27,O27,P27,Q27) -> 0
A28: ='Bldgs & Rooms'!$A$2 -> Main Bldg. | B28: ='Bldgs & Rooms'!$B$2 -> 0 | C28: =Hours!$A$28 -> Manual Transfer Switch (MTS) > 100A | D28: =MAX(E28+F28,G28,H28,I28,J28,K28,L28,M28,N28,O28,P28,Q28) -> 0 | E28: =IF('Components Yr 1'!E28=0,0,'Components Yr 1'!E28) -> 0 | F28: =IF('Components Yr 1'!F28=0,0,'Components Yr 1'!F28) -> 0 | G28: =IF('Components Yr 1'!G28=0,0,'Components Yr 1'!G28) -> 0 | H28: =IF('Components Yr 1'!H28=0,0,'Components Yr 1'!H28) -> 0 | I28: =IF('Components Yr 1'!I28=0,0,'Components Yr 1'!I28) -> 0 | J28: =IF('Components Yr 1'!J28=0,0,'Components Yr 1'!J28) -> 0 | R28: =IF(SUMPRODUCT((E28:Q28)*1)=0,0,E28*INDEX(Hours!M:M,MATCH(C28,Hours!$A:$A,0))+F28*INDEX(Hours!B:B,MATCH(C28,Hours!$A:$A,0))+G28*INDEX(Hours!C:C,MATCH(C28,Hours!$A:$A,0))+H28*INDEX(Hours!D:D,MATCH(C28,Hours!$A:$A,0))+I28*INDEX(Hours!E:E,MATCH(C28,Hours!$A:$A,0))+J28*INDEX(Hours!F:F,MATCH(C28,Hours!$A:$A,0))) -> 0 | S28: =MAX(E28+F28,G28,H28,I28,J28,K28,L28,M28,N28,O28,P28,Q28) -> 0
A29: ='Bldgs & Rooms'!$A$2 -> Main Bldg. | B29: ='Bldgs & Rooms'!$B$2 -> 0 | C29: =Hours!$A$29 -> Variable Frequency Drives (VFD) < 50 HP | D29: =MAX(E29+F29,G29,H29,I29,J29,K29,L29,M29,N29,O29,P29,Q29) -> 0 | E29: =IF('Components Yr 1'!E29=0,0,'Components Yr 1'!E29) -> 0 | F29: =IF('Components Yr 1'!F29=0,0,'Components Yr 1'!F29) -> 0 | G29: =IF('Components Yr 1'!G29=0,0,'Components Yr 1'!G29) -> 0 | H29: =IF('Components Yr 1'!H29=0,0,'Components Yr 1'!H29) -> 0 | I29: =IF('Components Yr 1'!I29=0,0,'Components Yr 1'!I29) -> 0 | J29: =IF('Components Yr 1'!J29=0,0,'Components Yr 1'!J29) -> 0 | R29: =IF(SUMPRODUCT((E29:Q29)*1)=0,0,E29*INDEX(Hours!M:M,MATCH(C29,Hours!$A:$A,0))+F29*INDEX(Hours!B:B,MATCH(C29,Hours!$A:$A,0))+G29*INDEX(Hours!C:C,MATCH(C29,Hours!$A:$A,0))+H29*INDEX(Hours!D:D,MATCH(C29,Hours!$A:$A,0))+I29*INDEX(Hours!E:E,MATCH(C29,Hours!$A:$A,0))+J29*INDEX(Hours!F:F,MATCH(C29,Hours!$A:$A,0))) -> 0 | S29: =MAX(E29+F29,G29,H29,I29,J29,K29,L29,M29,N29,O29,P29,Q29) -> 0
A30: ='Bldgs & Rooms'!$A$2 -> Main Bldg. | B30: ='Bldgs & Rooms'!$B$2 -> 0 | C30: =Hours!$A$30 -> Variable Frequency Drives (VFD) 51-200 HP | D30: =MAX(E30+F30,G30,H30,I30,J30,K30,L30,M30,N30,O30,P30,Q30) -> 0 | E30: =IF('Components Yr 1'!E30=0,0,'Components Yr 1'!E30) -> 0 | F30: =IF('Components Yr 1'!F30=0,0,'Components Yr 1'!F30) -> 0 | G30: =IF('Components Yr 1'!G30=0,0,'Components Yr 1'!G30) -> 0 | H30: =IF('Components Yr 1'!H30=0,0,'Components Yr 1'!H30) -> 0 | I30: =IF('Components Yr 1'!I30=0,0,'Components Yr 1'!I30) -> 0 | J30: =IF('Components Yr 1'!J30=0,0,'Components Yr 1'!J30) -> 0 | R30: =IF(SUMPRODUCT((E30:Q30)*1)=0,0,E30*INDEX(Hours!M:M,MATCH(C30,Hours!$A:$A,0))+F30*INDEX(Hours!B:B,MATCH(C30,Hours!$A:$A,0))+G30*INDEX(Hours!C:C,MATCH(C30,Hours!$A:$A,0))+H30*INDEX(Hours!D:D,MATCH(C30,Hours!$A:$A,0))+I30*INDEX(Hours!E:E,MATCH(C30,Hours!$A:$A,0))+J30*INDEX(Hours!F:F,MATCH(C30,Hours!$A:$A,0))) -> 0 | S30: =MAX(E30+F30,G30,H30,I30,J30,K30,L30,M30,N30,O30,P30,Q30) -> 0
A31: ='Bldgs & Rooms'!$A$2 -> Main Bldg. | B31: ='Bldgs & Rooms'!$B$2 -> 0 | C31: =Hours!$A$31 -> Motors < 50 HP | D31: =MAX(E31+F31,G31,H31,I31,J31,K31,L31,M31,N31,O31,P31,Q31) -> 0 | E31: =IF('Components Yr 1'!E31=0,0,'Components Yr 1'!E31) -> 0 | F31: =IF('Components Yr 1'!F31=0,0,'Components Yr 1'!F31) -> 0 | G31: =IF('Components Yr 1'!G31=0,0,'Components Yr 1'!G31) -> 0 | H31: =IF('Components Yr 1'!H31=0,0,'Components Yr 1'!H31) -> 0 | I31: =IF('Components Yr 1'!I31=0,0,'Components Yr 1'!I31) -> 0 | J31: =IF('Components Yr 1'!J31=0,0,'Components Yr 1'!J31) -> 0 | R31: =IF(SUMPRODUCT((E31:Q31)*1)=0,0,E31*INDEX(Hours!M:M,MATCH(C31,Hours!$A:$A,0))+F31*INDEX(Hours!B:B,MATCH(C31,Hours!$A:$A,0))+G31*INDEX(Hours!C:C,MATCH(C31,Hours!$A:$A,0))+H31*INDEX(Hours!D:D,MATCH(C31,Hours!$A:$A,0))+I31*INDEX(Hours!E:E,MATCH(C31,Hours!$A:$A,0))+J31*INDEX(Hours!F:F,MATCH(C31,Hours!$A:$A,0))) -> 0 | S31: =MAX(E31+F31,G31,H31,I31,J31,K31,L31,M31,N31,O31,P31,Q31) -> 0
A32: ='Bldgs & Rooms'!$A$2 -> Main Bldg. | B32: ='Bldgs & Rooms'!$B$2 -> 0 | C32: =Hours!$A$32 -> Motors 51-200 HP | D32: =MAX(E32+F32,G32,H32,I32,J32,K32,L32,M32,N32,O32,P32,Q32) -> 0 | E32: =IF('Components Yr 1'!E32=0,0,'Components Yr 1'!E32) -> 0 | F32: =IF('Components Yr 1'!F32=0,0,'Components Yr 1'!F32) -> 0 | G32: =IF('Components Yr 1'!G32=0,0,'Components Yr 1'!G32) -> 0 | H32: =IF('Components Yr 1'!H32=0,0,'Components Yr 1'!H32) -> 0 | I32: =IF('Components Yr 1'!I32=0,0,'Components Yr 1'!I32) -> 0 | J32: =IF('Components Yr 1'!J32=0,0,'Components Yr 1'!J32) -> 0 | R32: =IF(SUMPRODUCT((E32:Q32)*1)=0,0,E32*INDEX(Hours!M:M,MATCH(C32,Hours!$A:$A,0))+F32*INDEX(Hours!B:B,MATCH(C32,Hours!$A:$A,0))+G32*INDEX(Hours!C:C,MATCH(C32,Hours!$A:$A,0))+H32*INDEX(Hours!D:D,MATCH(C32,Hours!$A:$A,0))+I32*INDEX(Hours!E:E,MATCH(C32,Hours!$A:$A,0))+J32*INDEX(Hours!F:F,MATCH(C32,Hours!$A:$A,0))) -> 0 | S32: =MAX(E32+F32,G32,H32,I32,J32,K32,L32,M32,N32,O32,P32,Q32) -> 0
A33: ='Bldgs & Rooms'!$A$2 -> Main Bldg. | B33: ='Bldgs & Rooms'!$B$2 -> 0 | C33: =Hours!$A$33 -> Motors 201-500 HP | D33: =MAX(E33+F33,G33,H33,I33,J33,K33,L33,M33,N33,O33,P33,Q33) -> 0 | E33: =IF('Components Yr 1'!E33=0,0,'Components Yr 1'!E33) -> 0 | F33: =IF('Components Yr 1'!F33=0,0,'Components Yr 1'!F33) -> 0 | G33: =IF('Components Yr 1'!G33=0,0,'Components Yr 1'!G33) -> 0 | H33: =IF('Components Yr 1'!H33=0,0,'Components Yr 1'!H33) -> 0 | I33: =IF('Components Yr 1'!I33=0,0,'Components Yr 1'!I33) -> 0 | J33: =IF('Components Yr 1'!J33=0,0,'Components Yr 1'!J33) -> 0 | R33: =IF(SUMPRODUCT((E33:Q33)*1)=0,0,E33*INDEX(Hours!M:M,MATCH(C33,Hours!$A:$A,0))+F33*INDEX(Hours!B:B,MATCH(C33,Hours!$A:$A,0))+G33*INDEX(Hours!C:C,MATCH(C33,Hours!$A:$A,0))+H33*INDEX(Hours!D:D,MATCH(C33,Hours!$A:$A,0))+I33*INDEX(Hours!E:E,MATCH(C33,Hours!$A:$A,0))+J33*INDEX(Hours!F:F,MATCH(C33,Hours!$A:$A,0))) -> 0 | S33: =MAX(E33+F33,G33,H33,I33,J33,K33,L33,M33,N33,O33,P33,Q33) -> 0
A34: ='Bldgs & Rooms'!$A$2 -> Main Bldg. | B34: ='Bldgs & Rooms'!$B$2 -> 0 | C34: =Hours!$A$34 -> Compressed Air Equipment | D34: =MAX(E34+F34,G34,H34,I34,J34,K34,L34,M34,N34,O34,P34,Q34) -> 0 | E34: =IF('Components Yr 1'!E34=0,0,'Components Yr 1'!E34) -> 0 | F34: =IF('Components Yr 1'!F34=0,0,'Components Yr 1'!F34) -> 0 | G34: =IF('Components Yr 1'!G34=0,0,'Components Yr 1'!G34) -> 0 | H34: =IF('Components Yr 1'!H34=0,0,'Components Yr 1'!H34) -> 0 | I34: =IF('Components Yr 1'!I34=0,0,'Components Yr 1'!I34) -> 0 | J34: =IF('Components Yr 1'!J34=0,0,'Components Yr 1'!J34) -> 0 | R34: =IF(SUMPRODUCT((E34:Q34)*1)=0,0,E34*INDEX(Hours!M:M,MATCH(C34,Hours!$A:$A,0))+F34*INDEX(Hours!B:B,MATCH(C34,Hours!$A:$A,0))+G34*INDEX(Hours!C:C,MATCH(C34,Hours!$A:$A,0))+H34*INDEX(Hours!D:D,MATCH(C34,Hours!$A:$A,0))+I34*INDEX(Hours!E:E,MATCH(C34,Hours!$A:$A,0))+J34*INDEX(Hours!F:F,MATCH(C34,Hours!$A:$A,0))) -> 0 | S34: =MAX(E34+F34,G34,H34,I34,J34,K34,L34,M34,N34,O34,P34,Q34) -> 0
A35: ='Bldgs & Rooms'!$A$2 -> Main Bldg. | B35: ='Bldgs & Rooms'!$B$2 -> 0 | C35: =Hours!$A$35 -> HVAC Equipment (Large) | D35: =MAX(E35+F35,G35,H35,I35,J35,K35,L35,M35,N35,O35,P35,Q35) -> 0 | E35: =IF('Components Yr 1'!E35=0,0,'Components Yr 1'!E35) -> 0 | F35: =IF('Components Yr 1'!F35=0,0,'Components Yr 1'!F35) -> 0 | G35: =IF('Components Yr 1'!G35=0,0,'Components Yr 1'!G35) -> 0 | H35: =IF('Components Yr 1'!H35=0,0,'Components Yr 1'!H35) -> 0 | I35: =IF('Components Yr 1'!I35=0,0,'Components Yr 1'!I35) -> 0 | J35: =IF('Components Yr 1'!J35=0,0,'Components Yr 1'!J35) -> 0 | R35: =IF(SUMPRODUCT((E35:Q35)*1)=0,0,E35*INDEX(Hours!M:M,MATCH(C35,Hours!$A:$A,0))+F35*INDEX(Hours!B:B,MATCH(C35,Hours!$A:$A,0))+G35*INDEX(Hours!C:C,MATCH(C35,Hours!$A:$A,0))+H35*INDEX(Hours!D:D,MATCH(C35,Hours!$A:$A,0))+I35*INDEX(Hours!E:E,MATCH(C35,Hours!$A:$A,0))+J35*INDEX(Hours!F:F,MATCH(C35,Hours!$A:$A,0))) -> 0 | S35: =MAX(E35+F35,G35,H35,I35,J35,K35,L35,M35,N35,O35,P35,Q35) -> 0
A36: ='Bldgs & Rooms'!$A$2 -> Main Bldg. | B36: ='Bldgs & Rooms'!$B$2 -> 0 | C36: =Hours!$A$36 -> HVAC Equipment (Small) | D36: =MAX(E36+F36,G36,H36,I36,J36,K36,L36,M36,N36,O36,P36,Q36) -> 0 | E36: =IF('Components Yr 1'!E36=0,0,'Components Yr 1'!E36) -> 0 | F36: =IF('Components Yr 1'!F36=0,0,'Components Yr 1'!F36) -> 0 | G36: =IF('Components Yr 1'!G36=0,0,'Components Yr 1'!G36) -> 0 | H36: =IF('Components Yr 1'!H36=0,0,'Components Yr 1'!H36) -> 0 | I36: =IF('Components Yr 1'!I36=0,0,'Components Yr 1'!I36) -> 0 | J36: =IF('Components Yr 1'!J36=0,0,'Components Yr 1'!J36) -> 0 | R36: =IF(SUMPRODUCT((E36:Q36)*1)=0,0,E36*INDEX(Hours!M:M,MATCH(C36,Hours!$A:$A,0))+F36*INDEX(Hours!B:B,MATCH(C36,Hours!$A:$A,0))+G36*INDEX(Hours!C:C,MATCH(C36,Hours!$A:$A,0))+H36*INDEX(Hours!D:D,MATCH(C36,Hours!$A:$A,0))+I36*INDEX(Hours!E:E,MATCH(C36,Hours!$A:$A,0))+J36*INDEX(Hours!F:F,MATCH(C36,Hours!$A:$A,0))) -> 0 | S36: =MAX(E36+F36,G36,H36,I36,J36,K36,L36,M36,N36,O36,P36,Q36) -> 0
A37: ='Bldgs & Rooms'!$A$2 -> Main Bldg. | B37: ='Bldgs & Rooms'!$B$2 -> 0 | C37: =Hours!$A$37 -> Uninterruptible Power Supply (UPS) < 50kVA | D37: =MAX(E37+F37,G37,H37,I37,J37,K37,L37,M37,N37,O37,P37,Q37) -> 0 | E37: =IF('Components Yr 1'!E37=0,0,'Components Yr 1'!E37) -> 0 | F37: =IF('Components Yr 1'!F37=0,0,'Components Yr 1'!F37) -> 0 | G37: =IF('Components Yr 1'!G37=0,0,'Components Yr 1'!G37) -> 0 | H37: =IF('Components Yr 1'!H37=0,0,'Components Yr 1'!H37) -> 0 | I37: =IF('Components Yr 1'!I37=0,0,'Components Yr 1'!I37) -> 0 | J37: =IF('Components Yr 1'!J37=0,0,'Components Yr 1'!J37) -> 0 | R37: =IF(SUMPRODUCT((E37:Q37)*1)=0,0,E37*INDEX(Hours!M:M,MATCH(C37,Hours!$A:$A,0))+F37*INDEX(Hours!B:B,MATCH(C37,Hours!$A:$A,0))+G37*INDEX(Hours!C:C,MATCH(C37,Hours!$A:$A,0))+H37*INDEX(Hours!D:D,MATCH(C37,Hours!$A:$A,0))+I37*INDEX(Hours!E:E,MATCH(C37,Hours!$A:$A,0))+J37*INDEX(Hours!F:F,MATCH(C37,Hours!$A:$A,0))) -> 0 | S37: =MAX(E37+F37,G37,H37,I37,J37,K37,L37,M37,N37,O37,P37,Q37) -> 0
A38: ='Bldgs & Rooms'!$A$2 -> Main Bldg. | B38: ='Bldgs & Rooms'!$B$2 -> 0 | C38: =Hours!$A$38 -> Uninterruptible Power Supply (UPS) > 50kVA | D38: =MAX(E38+F38,G38,H38,I38,J38,K38,L38,M38,N38,O38,P38,Q38) -> 0 | E38: =IF('Components Yr 1'!E38=0,0,'Components Yr 1'!E38) -> 0 | F38: =IF('Components Yr 1'!F38=0,0,'Components Yr 1'!F38) -> 0 | G38: =IF('Components Yr 1'!G38=0,0,'Components Yr 1'!G38) -> 0 | H38: =IF('Components Yr 1'!H38=0,0,'Components Yr 1'!H38) -> 0 | I38: =IF('Components Yr 1'!I38=0,0,'Components Yr 1'!I38) -> 0 | J38: =IF('Components Yr 1'!J38=0,0,'Components Yr 1'!J38) -> 0 | R38: =IF(SUMPRODUCT((E38:Q38)*1)=0,0,E38*INDEX(Hours!M:M,MATCH(C38,Hours!$A:$A,0))+F38*INDEX(Hours!B:B,MATCH(C38,Hours!$A:$A,0))+G38*INDEX(Hours!C:C,MATCH(C38,Hours!$A:$A,0))+H38*INDEX(Hours!D:D,MATCH(C38,Hours!$A:$A,0))+I38*INDEX(Hours!E:E,MATCH(C38,Hours!$A:$A,0))+J38*INDEX(Hours!F:F,MATCH(C38,Hours!$A:$A,0))) -> 0 | S38: =MAX(E38+F38,G38,H38,I38,J38,K38,L38,M38,N38,O38,P38,Q38) -> 0
A39: ='Bldgs & Rooms'!$A$3 -> Main Bldg. | B39: ='Bldgs & Rooms'!$B$3 -> 0 | C39: =Hours!$A$2 -> Switchgear - Incoming Main Service (Per Section) | D39: =MAX(E39+F39,G39,H39,I39,J39,K39,L39,M39,N39,O39,P39,Q39) -> 0 | E39: =IF('Components Yr 1'!E39=0,0,'Components Yr 1'!E39) -> 0 | F39: =IF('Components Yr 1'!F39=0,0,'Components Yr 1'!F39) -> 0 | G39: =IF('Components Yr 1'!G39=0,0,'Components Yr 1'!G39) -> 0 | H39: =IF('Components Yr 1'!H39=0,0,'Components Yr 1'!H39) -> 0 | I39: =IF('Components Yr 1'!I39=0,0,'Components Yr 1'!I39) -> 0 | J39: =IF('Components Yr 1'!J39=0,0,'Components Yr 1'!J39) -> 0 | K39: =IF('Components Yr 1'!K39=0,0,'Components Yr 1'!K39) -> 0 | L39: =IF('Components Yr 1'!L39=0,0,'Components Yr 1'!L39) -> 0 | O39: =IF('Components Yr 1'!O39=0,0,'Components Yr 1'!O39) -> 0 | R39: =IF(SUMPRODUCT((E39:Q39)*1)=0,0,E39*INDEX(Hours!M:M,MATCH(C39,Hours!$A:$A,0))+F39*INDEX(Hours!B:B,MATCH(C39,Hours!$A:$A,0))+G39*INDEX(Hours!C:C,MATCH(C39,Hours!$A:$A,0))+H39*INDEX(Hours!D:D,MATCH(C39,Hours!$A:$A,0))+I39*INDEX(Hours!E:E,MATCH(C39,Hours!$A:$A,0))+J39*INDEX(Hours!F:F,MATCH(C39,Hours!$A:$A,0))+K39*INDEX(Hours!G:G,MATCH(C39,Hours!$A:$A,0))+L39*INDEX(Hours!H:H,MATCH(C39,Hours!$A:$A,0))+O39*INDEX(Hours!K:K,MATCH(C39,Hours!$A:$A,0))) -> 0 | S39: =MAX(E39+F39,G39,H39,I39,J39,K39,L39,M39,N39,O39,P39,Q39) -> 0
A40: ='Bldgs & Rooms'!$A$3 -> Main Bldg. | B40: ='Bldgs & Rooms'!$B$3 -> 0 | C40: =Hours!$A$3 -> Switchgear Insulated Case Breakers (Bus Mounted) | D40: =MAX(E40+F40,G40,H40,I40,J40,K40,L40,M40,N40,O40,P40,Q40) -> 0 | E40: =IF('Components Yr 1'!E40=0,0,'Components Yr 1'!E40) -> 0 | F40: =IF('Components Yr 1'!F40=0,0,'Components Yr 1'!F40) -> 0 | G40: =IF('Components Yr 1'!G40=0,0,'Components Yr 1'!G40) -> 0 | H40: =IF('Components Yr 1'!H40=0,0,'Components Yr 1'!H40) -> 0 | I40: =IF('Components Yr 1'!I40=0,0,'Components Yr 1'!I40) -> 0 | J40: =IF('Components Yr 1'!J40=0,0,'Components Yr 1'!J40) -> 0 | K40: =IF('Components Yr 1'!K40=0,0,'Components Yr 1'!K40) -> 0 | R40: =IF(SUMPRODUCT((E40:Q40)*1)=0,0,E40*INDEX(Hours!M:M,MATCH(C40,Hours!$A:$A,0))+F40*INDEX(Hours!B:B,MATCH(C40,Hours!$A:$A,0))+G40*INDEX(Hours!C:C,MATCH(C40,Hours!$A:$A,0))+H40*INDEX(Hours!D:D,MATCH(C40,Hours!$A:$A,0))+I40*INDEX(Hours!E:E,MATCH(C40,Hours!$A:$A,0))+J40*INDEX(Hours!F:F,MATCH(C40,Hours!$A:$A,0))+K40*INDEX(Hours!G:G,MATCH(C40,Hours!$A:$A,0))) -> 0 | S40: =MAX(E40+F40,G40,H40,I40,J40,K40,L40,M40,N40,O40,P40,Q40) -> 0
A41: ='Bldgs & Rooms'!$A$3 -> Main Bldg. | B41: ='Bldgs & Rooms'!$B$3 -> 0 | C41: =Hours!$A$4 -> SwitchGear Drawout Breakers | D41: =MAX(E41+F41,G41,H41,I41,J41,K41,L41,M41,N41,O41,P41,Q41) -> 0 | E41: =IF('Components Yr 1'!E41=0,0,'Components Yr 1'!E41) -> 0 | F41: =IF('Components Yr 1'!F41=0,0,'Components Yr 1'!F41) -> 0 | G41: =IF('Components Yr 1'!G41=0,0,'Components Yr 1'!G41) -> 0 | H41: =IF('Components Yr 1'!H41=0,0,'Components Yr 1'!H41) -> 0 | I41: =IF('Components Yr 1'!I41=0,0,'Components Yr 1'!I41) -> 0 | J41: =IF('Components Yr 1'!J41=0,0,'Components Yr 1'!J41) -> 0 | L41: =IF('Components Yr 1'!L41=0,0,'Components Yr 1'!L41) -> 0 | R41: =IF(SUMPRODUCT((E41:Q41)*1)=0,0,E41*INDEX(Hours!M:M,MATCH(C41,Hours!$A:$A,0))+F41*INDEX(Hours!B:B,MATCH(C41,Hours!$A:$A,0))+G41*INDEX(Hours!C:C,MATCH(C41,Hours!$A:$A,0))+H41*INDEX(Hours!D:D,MATCH(C41,Hours!$A:$A,0))+I41*INDEX(Hours!E:E,MATCH(C41,Hours!$A:$A,0))+J41*INDEX(Hours!F:F,MATCH(C41,Hours!$A:$A,0))+L41*INDEX(Hours!H:H,MATCH(C41,Hours!$A:$A,0))) -> 0 | S41: =MAX(E41+F41,G41,H41,I41,J41,K41,L41,M41,N41,O41,P41,Q41) -> 0
A42: ='Bldgs & Rooms'!$A$3 -> Main Bldg. | B42: ='Bldgs & Rooms'!$B$3 -> 0 | C42: =Hours!$A$5 -> Distribution Switchboard Multi Cover (Per Section) | D42: =MAX(E42+F42,G42,H42,I42,J42,K42,L42,M42,N42,O42,P42,Q42) -> 0 | E42: =IF('Components Yr 1'!E42=0,0,'Components Yr 1'!E42) -> 0 | F42: =IF('Components Yr 1'!F42=0,0,'Components Yr 1'!F42) -> 0 | G42: =IF('Components Yr 1'!G42=0,0,'Components Yr 1'!G42) -> 0 | H42: =IF('Components Yr 1'!H42=0,0,'Components Yr 1'!H42) -> 0 | I42: =IF('Components Yr 1'!I42=0,0,'Components Yr 1'!I42) -> 0 | J42: =IF('Components Yr 1'!J42=0,0,'Components Yr 1'!J42) -> 0 | K42: =IF('Components Yr 1'!K42=0,0,'Components Yr 1'!K42) -> 0 | O42: =IF('Components Yr 1'!O42=0,0,'Components Yr 1'!O42) -> 0 | R42: =IF(SUMPRODUCT((E42:Q42)*1)=0,0,E42*INDEX(Hours!M:M,MATCH(C42,Hours!$A:$A,0))+F42*INDEX(Hours!B:B,MATCH(C42,Hours!$A:$A,0))+G42*INDEX(Hours!C:C,MATCH(C42,Hours!$A:$A,0))+H42*INDEX(Hours!D:D,MATCH(C42,Hours!$A:$A,0))+I42*INDEX(Hours!E:E,MATCH(C42,Hours!$A:$A,0))+J42*INDEX(Hours!F:F,MATCH(C42,Hours!$A:$A,0))+K42*INDEX(Hours!G:G,MATCH(C42,Hours!$A:$A,0))+O42*INDEX(Hours!K:K,MATCH(C42,Hours!$A:$A,0))) -> 0 | S42: =MAX(E42+F42,G42,H42,I42,J42,K42,L42,M42,N42,O42,P42,Q42) -> 0
A43: ='Bldgs & Rooms'!$A$3 -> Main Bldg. | B43: ='Bldgs & Rooms'!$B$3 -> 0 | C43: =Hours!$A$6 -> Switchboard Disconnects | D43: =MAX(E43+F43,G43,H43,I43,J43,K43,L43,M43,N43,O43,P43,Q43) -> 0 | E43: =IF('Components Yr 1'!E43=0,0,'Components Yr 1'!E43) -> 0 | F43: =IF('Components Yr 1'!F43=0,0,'Components Yr 1'!F43) -> 0 | G43: =IF('Components Yr 1'!G43=0,0,'Components Yr 1'!G43) -> 0 | H43: =IF('Components Yr 1'!H43=0,0,'Components Yr 1'!H43) -> 0 | I43: =IF('Components Yr 1'!I43=0,0,'Components Yr 1'!I43) -> 0 | J43: =IF('Components Yr 1'!J43=0,0,'Components Yr 1'!J43) -> 0 | R43: =IF(SUMPRODUCT((E43:Q43)*1)=0,0,E43*INDEX(Hours!M:M,MATCH(C43,Hours!$A:$A,0))+F43*INDEX(Hours!B:B,MATCH(C43,Hours!$A:$A,0))+G43*INDEX(Hours!C:C,MATCH(C43,Hours!$A:$A,0))+H43*INDEX(Hours!D:D,MATCH(C43,Hours!$A:$A,0))+I43*INDEX(Hours!E:E,MATCH(C43,Hours!$A:$A,0))+J43*INDEX(Hours!F:F,MATCH(C43,Hours!$A:$A,0))) -> 0 | S43: =MAX(E43+F43,G43,H43,I43,J43,K43,L43,M43,N43,O43,P43,Q43) -> 0
A44: ='Bldgs & Rooms'!$A$3 -> Main Bldg. | B44: ='Bldgs & Rooms'!$B$3 -> 0 | C44: =Hours!$A$7 -> Switchboard Molded Case Breakers | D44: =MAX(E44+F44,G44,H44,I44,J44,K44,L44,M44,N44,O44,P44,Q44) -> 0 | E44: =IF('Components Yr 1'!E44=0,0,'Components Yr 1'!E44) -> 0 | F44: =IF('Components Yr 1'!F44=0,0,'Components Yr 1'!F44) -> 0 | G44: =IF('Components Yr 1'!G44=0,0,'Components Yr 1'!G44) -> 0 | H44: =IF('Components Yr 1'!H44=0,0,'Components Yr 1'!H44) -> 0 | I44: =IF('Components Yr 1'!I44=0,0,'Components Yr 1'!I44) -> 0 | J44: =IF('Components Yr 1'!J44=0,0,'Components Yr 1'!J44) -> 0 | K44: =IF('Components Yr 1'!K44=0,0,'Components Yr 1'!K44) -> 0 | R44: =IF(SUMPRODUCT((E44:Q44)*1)=0,0,E44*INDEX(Hours!M:M,MATCH(C44,Hours!$A:$A,0))+F44*INDEX(Hours!B:B,MATCH(C44,Hours!$A:$A,0))+G44*INDEX(Hours!C:C,MATCH(C44,Hours!$A:$A,0))+H44*INDEX(Hours!D:D,MATCH(C44,Hours!$A:$A,0))+I44*INDEX(Hours!E:E,MATCH(C44,Hours!$A:$A,0))+J44*INDEX(Hours!F:F,MATCH(C44,Hours!$A:$A,0))+K44*INDEX(Hours!G:G,MATCH(C44,Hours!$A:$A,0))) -> 0 | S44: =MAX(E44+F44,G44,H44,I44,J44,K44,L44,M44,N44,O44,P44,Q44) -> 0
A45: ='Bldgs & Rooms'!$A$3 -> Main Bldg. | B45: ='Bldgs & Rooms'!$B$3 -> 0 | C45: =Hours!$A$8 -> Panelboard-Single Cover > 400A (Distribution Panel) | D45: =MAX(E45+F45,G45,H45,I45,J45,K45,L45,M45,N45,O45,P45,Q45) -> 0 | E45: =IF('Components Yr 1'!E45=0,0,'Components Yr 1'!E45) -> 0 | F45: =IF('Components Yr 1'!F45=0,0,'Components Yr 1'!F45) -> 0 | G45: =IF('Components Yr 1'!G45=0,0,'Components Yr 1'!G45) -> 0 | H45: =IF('Components Yr 1'!H45=0,0,'Components Yr 1'!H45) -> 0 | I45: =IF('Components Yr 1'!I45=0,0,'Components Yr 1'!I45) -> 0 | J45: =IF('Components Yr 1'!J45=0,0,'Components Yr 1'!J45) -> 0 | K45: =IF('Components Yr 1'!K45=0,0,'Components Yr 1'!K45) -> 0 | O45: =IF('Components Yr 1'!O45=0,0,'Components Yr 1'!O45) -> 0 | R45: =IF(SUMPRODUCT((E45:Q45)*1)=0,0,E45*INDEX(Hours!M:M,MATCH(C45,Hours!$A:$A,0))+F45*INDEX(Hours!B:B,MATCH(C45,Hours!$A:$A,0))+G45*INDEX(Hours!C:C,MATCH(C45,Hours!$A:$A,0))+H45*INDEX(Hours!D:D,MATCH(C45,Hours!$A:$A,0))+I45*INDEX(Hours!E:E,MATCH(C45,Hours!$A:$A,0))+J45*INDEX(Hours!F:F,MATCH(C45,Hours!$A:$A,0))+K45*INDEX(Hours!G:G,MATCH(C45,Hours!$A:$A,0))+O45*INDEX(Hours!K:K,MATCH(C45,Hours!$A:$A,0))) -> 0 | S45: =MAX(E45+F45,G45,H45,I45,J45,K45,L45,M45,N45,O45,P45,Q45) -> 0
A46: ='Bldgs & Rooms'!$A$3 -> Main Bldg. | B46: ='Bldgs & Rooms'!$B$3 -> 0 | C46: =Hours!$A$9 -> Panelboard-Single Cover < 400A (Branch Ckt Panel) | D46: =MAX(E46+F46,G46,H46,I46,J46,K46,L46,M46,N46,O46,P46,Q46) -> 0 | E46: =IF('Components Yr 1'!E46=0,0,'Components Yr 1'!E46) -> 0 | F46: =IF('Components Yr 1'!F46=0,0,'Components Yr 1'!F46) -> 0 | G46: =IF('Components Yr 1'!G46=0,0,'Components Yr 1'!G46) -> 0 | H46: =IF('Components Yr 1'!H46=0,0,'Components Yr 1'!H46) -> 0 | I46: =IF('Components Yr 1'!I46=0,0,'Components Yr 1'!I46) -> 0 | J46: =IF('Components Yr 1'!J46=0,0,'Components Yr 1'!J46) -> 0 | O46: =IF('Components Yr 1'!O46=0,0,'Components Yr 1'!O46) -> 0 | R46: =IF(SUMPRODUCT((E46:Q46)*1)=0,0,E46*INDEX(Hours!M:M,MATCH(C46,Hours!$A:$A,0))+F46*INDEX(Hours!B:B,MATCH(C46,Hours!$A:$A,0))+G46*INDEX(Hours!C:C,MATCH(C46,Hours!$A:$A,0))+H46*INDEX(Hours!D:D,MATCH(C46,Hours!$A:$A,0))+I46*INDEX(Hours!E:E,MATCH(C46,Hours!$A:$A,0))+J46*INDEX(Hours!F:F,MATCH(C46,Hours!$A:$A,0))+O46*INDEX(Hours!K:K,MATCH(C46,Hours!$A:$A,0))) -> 0 | S46: =MAX(E46+F46,G46,H46,I46,J46,K46,L46,M46,N46,O46,P46,Q46) -> 0
A47: ='Bldgs & Rooms'!$A$3 -> Main Bldg. | B47: ='Bldgs & Rooms'!$B$3 -> 0 | C47: =Hours!$A$10 -> Motor Control Center (MCC-Per Vertical Section) | D47: =MAX(E47+F47,G47,H47,I47,J47,K47,L47,M47,N47,O47,P47,Q47) -> 0 | E47: =IF('Components Yr 1'!E47=0,0,'Components Yr 1'!E47) -> 0 | F47: =IF('Components Yr 1'!F47=0,0,'Components Yr 1'!F47) -> 0 | G47: =IF('Components Yr 1'!G47=0,0,'Components Yr 1'!G47) -> 0 | H47: =IF('Components Yr 1'!H47=0,0,'Components Yr 1'!H47) -> 0 | I47: =IF('Components Yr 1'!I47=0,0,'Components Yr 1'!I47) -> 0 | J47: =IF('Components Yr 1'!J47=0,0,'Components Yr 1'!J47) -> 0 | O47: =IF('Components Yr 1'!O47=0,0,'Components Yr 1'!O47) -> 0 | R47: =IF(SUMPRODUCT((E47:Q47)*1)=0,0,E47*INDEX(Hours!M:M,MATCH(C47,Hours!$A:$A,0))+F47*INDEX(Hours!B:B,MATCH(C47,Hours!$A:$A,0))+G47*INDEX(Hours!C:C,MATCH(C47,Hours!$A:$A,0))+H47*INDEX(Hours!D:D,MATCH(C47,Hours!$A:$A,0))+I47*INDEX(Hours!E:E,MATCH(C47,Hours!$A:$A,0))+J47*INDEX(Hours!F:F,MATCH(C47,Hours!$A:$A,0))+O47*INDEX(Hours!K:K,MATCH(C47,Hours!$A:$A,0))) -> 0 | S47: =MAX(E47+F47,G47,H47,I47,J47,K47,L47,M47,N47,O47,P47,Q47) -> 0
A48: ='Bldgs & Rooms'!$A$3 -> Main Bldg. | B48: ='Bldgs & Rooms'!$B$3 -> 0 | C48: =Hours!$A$11 -> MCC: Combination Motor Starters | D48: =MAX(E48+F48,G48,H48,I48,J48,K48,L48,M48,N48,O48,P48,Q48) -> 0 | E48: =IF('Components Yr 1'!E48=0,0,'Components Yr 1'!E48) -> 0 | F48: =IF('Components Yr 1'!F48=0,0,'Components Yr 1'!F48) -> 0 | G48: =IF('Components Yr 1'!G48=0,0,'Components Yr 1'!G48) -> 0 | H48: =IF('Components Yr 1'!H48=0,0,'Components Yr 1'!H48) -> 0 | I48: =IF('Components Yr 1'!I48=0,0,'Components Yr 1'!I48) -> 0 | J48: =IF('Components Yr 1'!J48=0,0,'Components Yr 1'!J48) -> 0 | K48: =IF('Components Yr 1'!K48=0,0,'Components Yr 1'!K48) -> 0 | O48: =IF('Components Yr 1'!O48=0,0,'Components Yr 1'!O48) -> 0 | R48: =IF(SUMPRODUCT((E48:Q48)*1)=0,0,E48*INDEX(Hours!M:M,MATCH(C48,Hours!$A:$A,0))+F48*INDEX(Hours!B:B,MATCH(C48,Hours!$A:$A,0))+G48*INDEX(Hours!C:C,MATCH(C48,Hours!$A:$A,0))+H48*INDEX(Hours!D:D,MATCH(C48,Hours!$A:$A,0))+I48*INDEX(Hours!E:E,MATCH(C48,Hours!$A:$A,0))+J48*INDEX(Hours!F:F,MATCH(C48,Hours!$A:$A,0))+K48*INDEX(Hours!G:G,MATCH(C48,Hours!$A:$A,0))+O48*INDEX(Hours!K:K,MATCH(C48,Hours!$A:$A,0))) -> 0 | S48: =MAX(E48+F48,G48,H48,I48,J48,K48,L48,M48,N48,O48,P48,Q48) -> 0
A49: ='Bldgs & Rooms'!$A$3 -> Main Bldg. | B49: ='Bldgs & Rooms'!$B$3 -> 0 | C49: =Hours!$A$12 -> MCC: Molded Case Breaker | D49: =MAX(E49+F49,G49,H49,I49,J49,K49,L49,M49,N49,O49,P49,Q49) -> 0 | E49: =IF('Components Yr 1'!E49=0,0,'Components Yr 1'!E49) -> 0 | F49: =IF('Components Yr 1'!F49=0,0,'Components Yr 1'!F49) -> 0 | G49: =IF('Components Yr 1'!G49=0,0,'Components Yr 1'!G49) -> 0 | H49: =IF('Components Yr 1'!H49=0,0,'Components Yr 1'!H49) -> 0 | I49: =IF('Components Yr 1'!I49=0,0,'Components Yr 1'!I49) -> 0 | J49: =IF('Components Yr 1'!J49=0,0,'Components Yr 1'!J49) -> 0 | K49: =IF('Components Yr 1'!K49=0,0,'Components Yr 1'!K49) -> 0 | R49: =IF(SUMPRODUCT((E49:Q49)*1)=0,0,E49*INDEX(Hours!M:M,MATCH(C49,Hours!$A:$A,0))+F49*INDEX(Hours!B:B,MATCH(C49,Hours!$A:$A,0))+G49*INDEX(Hours!C:C,MATCH(C49,Hours!$A:$A,0))+H49*INDEX(Hours!D:D,MATCH(C49,Hours!$A:$A,0))+I49*INDEX(Hours!E:E,MATCH(C49,Hours!$A:$A,0))+J49*INDEX(Hours!F:F,MATCH(C49,Hours!$A:$A,0))+K49*INDEX(Hours!G:G,MATCH(C49,Hours!$A:$A,0))) -> 0 | S49: =MAX(E49+F49,G49,H49,I49,J49,K49,L49,M49,N49,O49,P49,Q49) -> 0
A50: ='Bldgs & Rooms'!$A$3 -> Main Bldg. | B50: ='Bldgs & Rooms'!$B$3 -> 0 | C50: =Hours!$A$13 -> MCC: Individual Disconnect Switch | D50: =MAX(E50+F50,G50,H50,I50,J50,K50,L50,M50,N50,O50,P50,Q50) -> 0 | E50: =IF('Components Yr 1'!E50=0,0,'Components Yr 1'!E50) -> 0 | F50: =IF('Components Yr 1'!F50=0,0,'Components Yr 1'!F50) -> 0 | G50: =IF('Components Yr 1'!G50=0,0,'Components Yr 1'!G50) -> 0 | H50: =IF('Components Yr 1'!H50=0,0,'Components Yr 1'!H50) -> 0 | I50: =IF('Components Yr 1'!I50=0,0,'Components Yr 1'!I50) -> 0 | J50: =IF('Components Yr 1'!J50=0,0,'Components Yr 1'!J50) -> 0 | R50: =IF(SUMPRODUCT((E50:Q50)*1)=0,0,E50*INDEX(Hours!M:M,MATCH(C50,Hours!$A:$A,0))+F50*INDEX(Hours!B:B,MATCH(C50,Hours!$A:$A,0))+G50*INDEX(Hours!C:C,MATCH(C50,Hours!$A:$A,0))+H50*INDEX(Hours!D:D,MATCH(C50,Hours!$A:$A,0))+I50*INDEX(Hours!E:E,MATCH(C50,Hours!$A:$A,0))+J50*INDEX(Hours!F:F,MATCH(C50,Hours!$A:$A,0))) -> 0 | S50: =MAX(E50+F50,G50,H50,I50,J50,K50,L50,M50,N50,O50,P50,Q50) -> 0
A51: ='Bldgs & Rooms'!$A$3 -> Main Bldg. | B51: ='Bldgs & Rooms'!$B$3 -> 0 | C51: =Hours!$A$14 -> Motor Control Panel (MCP) | D51: =MAX(E51+F51,G51,H51,I51,J51,K51,L51,M51,N51,O51,P51,Q51) -> 0 | E51: =IF('Components Yr 1'!E51=0,0,'Components Yr 1'!E51) -> 0 | F51: =IF('Components Yr 1'!F51=0,0,'Components Yr 1'!F51) -> 0 | G51: =IF('Components Yr 1'!G51=0,0,'Components Yr 1'!G51) -> 0 | H51: =IF('Components Yr 1'!H51=0,0,'Components Yr 1'!H51) -> 0 | I51: =IF('Components Yr 1'!I51=0,0,'Components Yr 1'!I51) -> 0 | J51: =IF('Components Yr 1'!J51=0,0,'Components Yr 1'!J51) -> 0 | O51: =IF('Components Yr 1'!O51=0,0,'Components Yr 1'!O51) -> 0 | R51: =IF(SUMPRODUCT((E51:Q51)*1)=0,0,E51*INDEX(Hours!M:M,MATCH(C51,Hours!$A:$A,0))+F51*INDEX(Hours!B:B,MATCH(C51,Hours!$A:$A,0))+G51*INDEX(Hours!C:C,MATCH(C51,Hours!$A:$A,0))+H51*INDEX(Hours!D:D,MATCH(C51,Hours!$A:$A,0))+I51*INDEX(Hours!E:E,MATCH(C51,Hours!$A:$A,0))+J51*INDEX(Hours!F:F,MATCH(C51,Hours!$A:$A,0))+O51*INDEX(Hours!K:K,MATCH(C51,Hours!$A:$A,0))) -> 0 | S51: =MAX(E51+F51,G51,H51,I51,J51,K51,L51,M51,N51,O51,P51,Q51) -> 0
A52: ='Bldgs & Rooms'!$A$3 -> Main Bldg. | B52: ='Bldgs & Rooms'!$B$3 -> 0 | C52: =Hours!$A$15 -> VFD Motor Control Panel (VFD-MCP) | D52: =MAX(E52+F52,G52,H52,I52,J52,K52,L52,M52,N52,O52,P52,Q52) -> 0 | E52: =IF('Components Yr 1'!E52=0,0,'Components Yr 1'!E52) -> 0 | F52: =IF('Components Yr 1'!F52=0,0,'Components Yr 1'!F52) -> 0 | G52: =IF('Components Yr 1'!G52=0,0,'Components Yr 1'!G52) -> 0 | H52: =IF('Components Yr 1'!H52=0,0,'Components Yr 1'!H52) -> 0 | I52: =IF('Components Yr 1'!I52=0,0,'Components Yr 1'!I52) -> 0 | J52: =IF('Components Yr 1'!J52=0,0,'Components Yr 1'!J52) -> 0 | O52: =IF('Components Yr 1'!O52=0,0,'Components Yr 1'!O52) -> 0 | R52: =IF(SUMPRODUCT((E52:Q52)*1)=0,0,E52*INDEX(Hours!M:M,MATCH(C52,Hours!$A:$A,0))+F52*INDEX(Hours!B:B,MATCH(C52,Hours!$A:$A,0))+G52*INDEX(Hours!C:C,MATCH(C52,Hours!$A:$A,0))+H52*INDEX(Hours!D:D,MATCH(C52,Hours!$A:$A,0))+I52*INDEX(Hours!E:E,MATCH(C52,Hours!$A:$A,0))+J52*INDEX(Hours!F:F,MATCH(C52,Hours!$A:$A,0))+O52*INDEX(Hours!K:K,MATCH(C52,Hours!$A:$A,0))) -> 0 | S52: =MAX(E52+F52,G52,H52,I52,J52,K52,L52,M52,N52,O52,P52,Q52) -> 0
A53: ='Bldgs & Rooms'!$A$3 -> Main Bldg. | B53: ='Bldgs & Rooms'!$B$3 -> 0 | C53: =Hours!$A$16 -> Individual Disconnect Switch > 100A | D53: =MAX(E53+F53,G53,H53,I53,J53,K53,L53,M53,N53,O53,P53,Q53) -> 0 | E53: =IF('Components Yr 1'!E53=0,0,'Components Yr 1'!E53) -> 0 | F53: =IF('Components Yr 1'!F53=0,0,'Components Yr 1'!F53) -> 0 | G53: =IF('Components Yr 1'!G53=0,0,'Components Yr 1'!G53) -> 0 | H53: =IF('Components Yr 1'!H53=0,0,'Components Yr 1'!H53) -> 0 | I53: =IF('Components Yr 1'!I53=0,0,'Components Yr 1'!I53) -> 0 | J53: =IF('Components Yr 1'!J53=0,0,'Components Yr 1'!J53) -> 0 | K53: =IF('Components Yr 1'!K53=0,0,'Components Yr 1'!K53) -> 0 | R53: =IF(SUMPRODUCT((E53:Q53)*1)=0,0,E53*INDEX(Hours!M:M,MATCH(C53,Hours!$A:$A,0))+F53*INDEX(Hours!B:B,MATCH(C53,Hours!$A:$A,0))+G53*INDEX(Hours!C:C,MATCH(C53,Hours!$A:$A,0))+H53*INDEX(Hours!D:D,MATCH(C53,Hours!$A:$A,0))+I53*INDEX(Hours!E:E,MATCH(C53,Hours!$A:$A,0))+J53*INDEX(Hours!F:F,MATCH(C53,Hours!$A:$A,0))+K53*INDEX(Hours!G:G,MATCH(C53,Hours!$A:$A,0))) -> 0 | S53: =MAX(E53+F53,G53,H53,I53,J53,K53,L53,M53,N53,O53,P53,Q53) -> 0
A54: ='Bldgs & Rooms'!$A$3 -> Main Bldg. | B54: ='Bldgs & Rooms'!$B$3 -> 0 | C54: =Hours!$A$17 -> Individual Molded Case Breaker > 100A | D54: =MAX(E54+F54,G54,H54,I54,J54,K54,L54,M54,N54,O54,P54,Q54) -> 0 | E54: =IF('Components Yr 1'!E54=0,0,'Components Yr 1'!E54) -> 0 | F54: =IF('Components Yr 1'!F54=0,0,'Components Yr 1'!F54) -> 0 | G54: =IF('Components Yr 1'!G54=0,0,'Components Yr 1'!G54) -> 0 | H54: =IF('Components Yr 1'!H54=0,0,'Components Yr 1'!H54) -> 0 | I54: =IF('Components Yr 1'!I54=0,0,'Components Yr 1'!I54) -> 0 | J54: =IF('Components Yr 1'!J54=0,0,'Components Yr 1'!J54) -> 0 | K54: =IF('Components Yr 1'!K54=0,0,'Components Yr 1'!K54) -> 0 | R54: =IF(SUMPRODUCT((E54:Q54)*1)=0,0,E54*INDEX(Hours!M:M,MATCH(C54,Hours!$A:$A,0))+F54*INDEX(Hours!B:B,MATCH(C54,Hours!$A:$A,0))+G54*INDEX(Hours!C:C,MATCH(C54,Hours!$A:$A,0))+H54*INDEX(Hours!D:D,MATCH(C54,Hours!$A:$A,0))+I54*INDEX(Hours!E:E,MATCH(C54,Hours!$A:$A,0))+J54*INDEX(Hours!F:F,MATCH(C54,Hours!$A:$A,0))+K54*INDEX(Hours!G:G,MATCH(C54,Hours!$A:$A,0))) -> 0 | S54: =MAX(E54+F54,G54,H54,I54,J54,K54,L54,M54,N54,O54,P54,Q54) -> 0
A55: ='Bldgs & Rooms'!$A$3 -> Main Bldg. | B55: ='Bldgs & Rooms'!$B$3 -> 0 | C55: =Hours!$A$18 -> Individual Combination Motor Starter > 100A | D55: =MAX(E55+F55,G55,H55,I55,J55,K55,L55,M55,N55,O55,P55,Q55) -> 0 | E55: =IF('Components Yr 1'!E55=0,0,'Components Yr 1'!E55) -> 0 | F55: =IF('Components Yr 1'!F55=0,0,'Components Yr 1'!F55) -> 0 | G55: =IF('Components Yr 1'!G55=0,0,'Components Yr 1'!G55) -> 0 | H55: =IF('Components Yr 1'!H55=0,0,'Components Yr 1'!H55) -> 0 | I55: =IF('Components Yr 1'!I55=0,0,'Components Yr 1'!I55) -> 0 | J55: =IF('Components Yr 1'!J55=0,0,'Components Yr 1'!J55) -> 0 | K55: =IF('Components Yr 1'!K55=0,0,'Components Yr 1'!K55) -> 0 | R55: =IF(SUMPRODUCT((E55:Q55)*1)=0,0,E55*INDEX(Hours!M:M,MATCH(C55,Hours!$A:$A,0))+F55*INDEX(Hours!B:B,MATCH(C55,Hours!$A:$A,0))+G55*INDEX(Hours!C:C,MATCH(C55,Hours!$A:$A,0))+H55*INDEX(Hours!D:D,MATCH(C55,Hours!$A:$A,0))+I55*INDEX(Hours!E:E,MATCH(C55,Hours!$A:$A,0))+J55*INDEX(Hours!F:F,MATCH(C55,Hours!$A:$A,0))+K55*INDEX(Hours!G:G,MATCH(C55,Hours!$A:$A,0))) -> 0 | S55: =MAX(E55+F55,G55,H55,I55,J55,K55,L55,M55,N55,O55,P55,Q55) -> 0
A56: ='Bldgs & Rooms'!$A$3 -> Main Bldg. | B56: ='Bldgs & Rooms'!$B$3 -> 0 | C56: =Hours!$A$19 -> Oil Filled Transformer - 5kV-15kV Primary - Any Size (Pad Mounted) | D56: =MAX(E56+F56,G56,H56,I56,J56,K56,L56,M56,N56,O56,P56,Q56) -> 0 | E56: =IF('Components Yr 1'!E56=0,0,'Components Yr 1'!E56) -> 0 | F56: =IF('Components Yr 1'!F56=0,0,'Components Yr 1'!F56) -> 0 | G56: =IF('Components Yr 1'!G56=0,0,'Components Yr 1'!G56) -> 0 | H56: =IF('Components Yr 1'!H56=0,0,'Components Yr 1'!H56) -> 0 | I56: =IF('Components Yr 1'!I56=0,0,'Components Yr 1'!I56) -> 0 | J56: =IF('Components Yr 1'!J56=0,0,'Components Yr 1'!J56) -> 0 | M56: =IF('Components Yr 1'!M56=0,0,'Components Yr 1'!M56) -> 0 | N56: =IF('Components Yr 1'!N56=0,0,'Components Yr 1'!N56) -> 0 | P56: =IF('Components Yr 1'!P56=0,0,'Components Yr 1'!P56) -> 0 | R56: =IF(SUMPRODUCT((E56:Q56)*1)=0,0,E56*INDEX(Hours!M:M,MATCH(C56,Hours!$A:$A,0))+F56*INDEX(Hours!B:B,MATCH(C56,Hours!$A:$A,0))+G56*INDEX(Hours!C:C,MATCH(C56,Hours!$A:$A,0))+H56*INDEX(Hours!D:D,MATCH(C56,Hours!$A:$A,0))+I56*INDEX(Hours!E:E,MATCH(C56,Hours!$A:$A,0))+J56*INDEX(Hours!F:F,MATCH(C56,Hours!$A:$A,0))+M56*INDEX(Hours!I:I,MATCH(C56,Hours!$A:$A,0))+N56*INDEX(Hours!J:J,MATCH(C56,Hours!$A:$A,0))+P56*INDEX(Hours!L:L,MATCH(C56,Hours!$A:$A,0))) -> 0 | S56: =MAX(E56+F56,G56,H56,I56,J56,K56,L56,M56,N56,O56,P56,Q56) -> 0
A57: ='Bldgs & Rooms'!$A$3 -> Main Bldg. | B57: ='Bldgs & Rooms'!$B$3 -> 0 | C57: =Hours!$A$20 -> Oil Filled Transformer - > 15kV Primary (Substation Class) | D57: =MAX(E57+F57,G57,H57,I57,J57,K57,L57,M57,N57,O57,P57,Q57) -> 0 | E57: =IF('Components Yr 1'!E57=0,0,'Components Yr 1'!E57) -> 0 | F57: =IF('Components Yr 1'!F57=0,0,'Components Yr 1'!F57) -> 0 | G57: =IF('Components Yr 1'!G57=0,0,'Components Yr 1'!G57) -> 0 | H57: =IF('Components Yr 1'!H57=0,0,'Components Yr 1'!H57) -> 0 | I57: =IF('Components Yr 1'!I57=0,0,'Components Yr 1'!I57) -> 0 | J57: =IF('Components Yr 1'!J57=0,0,'Components Yr 1'!J57) -> 0 | M57: =IF('Components Yr 1'!M57=0,0,'Components Yr 1'!M57) -> 0 | N57: =IF('Components Yr 1'!N57=0,0,'Components Yr 1'!N57) -> 0 | P57: =IF('Components Yr 1'!P57=0,0,'Components Yr 1'!P57) -> 0 | R57: =IF(SUMPRODUCT((E57:Q57)*1)=0,0,E57*INDEX(Hours!M:M,MATCH(C57,Hours!$A:$A,0))+F57*INDEX(Hours!B:B,MATCH(C57,Hours!$A:$A,0))+G57*INDEX(Hours!C:C,MATCH(C57,Hours!$A:$A,0))+H57*INDEX(Hours!D:D,MATCH(C57,Hours!$A:$A,0))+I57*INDEX(Hours!E:E,MATCH(C57,Hours!$A:$A,0))+J57*INDEX(Hours!F:F,MATCH(C57,Hours!$A:$A,0))+M57*INDEX(Hours!I:I,MATCH(C57,Hours!$A:$A,0))+N57*INDEX(Hours!J:J,MATCH(C57,Hours!$A:$A,0))+P57*INDEX(Hours!L:L,MATCH(C57,Hours!$A:$A,0))) -> 0 | S57: =MAX(E57+F57,G57,H57,I57,J57,K57,L57,M57,N57,O57,P57,Q57) -> 0
A58: ='Bldgs & Rooms'!$A$3 -> Main Bldg. | B58: ='Bldgs & Rooms'!$B$3 -> 0 | C58: =Hours!$A$21 -> Dry Type Transformer - < 480V Primary - Any Size kVA | D58: =MAX(E58+F58,G58,H58,I58,J58,K58,L58,M58,N58,O58,P58,Q58) -> 0 | E58: =IF('Components Yr 1'!E58=0,0,'Components Yr 1'!E58) -> 0 | F58: =IF('Components Yr 1'!F58=0,0,'Components Yr 1'!F58) -> 0 | G58: =IF('Components Yr 1'!G58=0,0,'Components Yr 1'!G58) -> 0 | H58: =IF('Components Yr 1'!H58=0,0,'Components Yr 1'!H58) -> 0 | I58: =IF('Components Yr 1'!I58=0,0,'Components Yr 1'!I58) -> 0 | J58: =IF('Components Yr 1'!J58=0,0,'Components Yr 1'!J58) -> 0 | M58: =IF('Components Yr 1'!M58=0,0,'Components Yr 1'!M58) -> 0 | N58: =IF('Components Yr 1'!N58=0,0,'Components Yr 1'!N58) -> 0 | R58: =IF(SUMPRODUCT((E58:Q58)*1)=0,0,E58*INDEX(Hours!M:M,MATCH(C58,Hours!$A:$A,0))+F58*INDEX(Hours!B:B,MATCH(C58,Hours!$A:$A,0))+G58*INDEX(Hours!C:C,MATCH(C58,Hours!$A:$A,0))+H58*INDEX(Hours!D:D,MATCH(C58,Hours!$A:$A,0))+I58*INDEX(Hours!E:E,MATCH(C58,Hours!$A:$A,0))+J58*INDEX(Hours!F:F,MATCH(C58,Hours!$A:$A,0))+M58*INDEX(Hours!I:I,MATCH(C58,Hours!$A:$A,0))+N58*INDEX(Hours!J:J,MATCH(C58,Hours!$A:$A,0))) -> 0 | S58: =MAX(E58+F58,G58,H58,I58,J58,K58,L58,M58,N58,O58,P58,Q58) -> 0
A59: ='Bldgs & Rooms'!$A$3 -> Main Bldg. | B59: ='Bldgs & Rooms'!$B$3 -> 0 | C59: =Hours!$A$22 -> Power Factor Correction Capacitors | D59: =MAX(E59+F59,G59,H59,I59,J59,K59,L59,M59,N59,O59,P59,Q59) -> 0 | E59: =IF('Components Yr 1'!E59=0,0,'Components Yr 1'!E59) -> 0 | F59: =IF('Components Yr 1'!F59=0,0,'Components Yr 1'!F59) -> 0 | G59: =IF('Components Yr 1'!G59=0,0,'Components Yr 1'!G59) -> 0 | H59: =IF('Components Yr 1'!H59=0,0,'Components Yr 1'!H59) -> 0 | I59: =IF('Components Yr 1'!I59=0,0,'Components Yr 1'!I59) -> 0 | J59: =IF('Components Yr 1'!J59=0,0,'Components Yr 1'!J59) -> 0 | R59: =IF(SUMPRODUCT((E59:Q59)*1)=0,0,E59*INDEX(Hours!M:M,MATCH(C59,Hours!$A:$A,0))+F59*INDEX(Hours!B:B,MATCH(C59,Hours!$A:$A,0))+G59*INDEX(Hours!C:C,MATCH(C59,Hours!$A:$A,0))+H59*INDEX(Hours!D:D,MATCH(C59,Hours!$A:$A,0))+I59*INDEX(Hours!E:E,MATCH(C59,Hours!$A:$A,0))+J59*INDEX(Hours!F:F,MATCH(C59,Hours!$A:$A,0))) -> 0 | S59: =MAX(E59+F59,G59,H59,I59,J59,K59,L59,M59,N59,O59,P59,Q59) -> 0
A60: ='Bldgs & Rooms'!$A$3 -> Main Bldg. | B60: ='Bldgs & Rooms'!$B$3 -> 0 | C60: =Hours!$A$23 -> Lighting Contactor > 100A | D60: =MAX(E60+F60,G60,H60,I60,J60,K60,L60,M60,N60,O60,P60,Q60) -> 0 | E60: =IF('Components Yr 1'!E60=0,0,'Components Yr 1'!E60) -> 0 | F60: =IF('Components Yr 1'!F60=0,0,'Components Yr 1'!F60) -> 0 | G60: =IF('Components Yr 1'!G60=0,0,'Components Yr 1'!G60) -> 0 | H60: =IF('Components Yr 1'!H60=0,0,'Components Yr 1'!H60) -> 0 | I60: =IF('Components Yr 1'!I60=0,0,'Components Yr 1'!I60) -> 0 | J60: =IF('Components Yr 1'!J60=0,0,'Components Yr 1'!J60) -> 0 | R60: =IF(SUMPRODUCT((E60:Q60)*1)=0,0,E60*INDEX(Hours!M:M,MATCH(C60,Hours!$A:$A,0))+F60*INDEX(Hours!B:B,MATCH(C60,Hours!$A:$A,0))+G60*INDEX(Hours!C:C,MATCH(C60,Hours!$A:$A,0))+H60*INDEX(Hours!D:D,MATCH(C60,Hours!$A:$A,0))+I60*INDEX(Hours!E:E,MATCH(C60,Hours!$A:$A,0))+J60*INDEX(Hours!F:F,MATCH(C60,Hours!$A:$A,0))) -> 0 | S60: =MAX(E60+F60,G60,H60,I60,J60,K60,L60,M60,N60,O60,P60,Q60) -> 0
A61: ='Bldgs & Rooms'!$A$3 -> Main Bldg. | B61: ='Bldgs & Rooms'!$B$3 -> 0 | C61: =Hours!$A$24 -> Power Distribution Unit (PDU) | D61: =MAX(E61+F61,G61,H61,I61,J61,K61,L61,M61,N61,O61,P61,Q61) -> 0 | E61: =IF('Components Yr 1'!E61=0,0,'Components Yr 1'!E61) -> 0 | F61: =IF('Components Yr 1'!F61=0,0,'Components Yr 1'!F61) -> 0 | G61: =IF('Components Yr 1'!G61=0,0,'Components Yr 1'!G61) -> 0 | H61: =IF('Components Yr 1'!H61=0,0,'Components Yr 1'!H61) -> 0 | I61: =IF('Components Yr 1'!I61=0,0,'Components Yr 1'!I61) -> 0 | J61: =IF('Components Yr 1'!J61=0,0,'Components Yr 1'!J61) -> 0 | R61: =IF(SUMPRODUCT((E61:Q61)*1)=0,0,E61*INDEX(Hours!M:M,MATCH(C61,Hours!$A:$A,0))+F61*INDEX(Hours!B:B,MATCH(C61,Hours!$A:$A,0))+G61*INDEX(Hours!C:C,MATCH(C61,Hours!$A:$A,0))+H61*INDEX(Hours!D:D,MATCH(C61,Hours!$A:$A,0))+I61*INDEX(Hours!E:E,MATCH(C61,Hours!$A:$A,0))+J61*INDEX(Hours!F:F,MATCH(C61,Hours!$A:$A,0))) -> 0 | S61: =MAX(E61+F61,G61,H61,I61,J61,K61,L61,M61,N61,O61,P61,Q61) -> 0
A62: ='Bldgs & Rooms'!$A$3 -> Main Bldg. | B62: ='Bldgs & Rooms'!$B$3 -> 0 | C62: =Hours!$A$25 -> Wire Trough, Gutter, or Large Junction Boxes | D62: =MAX(E62+F62,G62,H62,I62,J62,K62,L62,M62,N62,O62,P62,Q62) -> 0 | E62: =IF('Components Yr 1'!E62=0,0,'Components Yr 1'!E62) -> 0 | F62: =IF('Components Yr 1'!F62=0,0,'Components Yr 1'!F62) -> 0 | G62: =IF('Components Yr 1'!G62=0,0,'Components Yr 1'!G62) -> 0 | H62: =IF('Components Yr 1'!H62=0,0,'Components Yr 1'!H62) -> 0 | I62: =IF('Components Yr 1'!I62=0,0,'Components Yr 1'!I62) -> 0 | J62: =IF('Components Yr 1'!J62=0,0,'Components Yr 1'!J62) -> 0 | R62: =IF(SUMPRODUCT((E62:Q62)*1)=0,0,E62*INDEX(Hours!M:M,MATCH(C62,Hours!$A:$A,0))+F62*INDEX(Hours!B:B,MATCH(C62,Hours!$A:$A,0))+G62*INDEX(Hours!C:C,MATCH(C62,Hours!$A:$A,0))+H62*INDEX(Hours!D:D,MATCH(C62,Hours!$A:$A,0))+I62*INDEX(Hours!E:E,MATCH(C62,Hours!$A:$A,0))+J62*INDEX(Hours!F:F,MATCH(C62,Hours!$A:$A,0))) -> 0 | S62: =MAX(E62+F62,G62,H62,I62,J62,K62,L62,M62,N62,O62,P62,Q62) -> 0
A63: ='Bldgs & Rooms'!$A$3 -> Main Bldg. | B63: ='Bldgs & Rooms'!$B$3 -> 0 | C63: =Hours!$A$26 -> Bus Duct - Vertical or Horizontal (Per 10' section) | D63: =MAX(E63+F63,G63,H63,I63,J63,K63,L63,M63,N63,O63,P63,Q63) -> 0 | E63: =IF('Components Yr 1'!E63=0,0,'Components Yr 1'!E63) -> 0 | F63: =IF('Components Yr 1'!F63=0,0,'Components Yr 1'!F63) -> 0 | G63: =IF('Components Yr 1'!G63=0,0,'Components Yr 1'!G63) -> 0 | H63: =IF('Components Yr 1'!H63=0,0,'Components Yr 1'!H63) -> 0 | I63: =IF('Components Yr 1'!I63=0,0,'Components Yr 1'!I63) -> 0 | J63: =IF('Components Yr 1'!J63=0,0,'Components Yr 1'!J63) -> 0 | R63: =IF(SUMPRODUCT((E63:Q63)*1)=0,0,E63*INDEX(Hours!M:M,MATCH(C63,Hours!$A:$A,0))+F63*INDEX(Hours!B:B,MATCH(C63,Hours!$A:$A,0))+G63*INDEX(Hours!C:C,MATCH(C63,Hours!$A:$A,0))+H63*INDEX(Hours!D:D,MATCH(C63,Hours!$A:$A,0))+I63*INDEX(Hours!E:E,MATCH(C63,Hours!$A:$A,0))+J63*INDEX(Hours!F:F,MATCH(C63,Hours!$A:$A,0))) -> 0 | S63: =MAX(E63+F63,G63,H63,I63,J63,K63,L63,M63,N63,O63,P63,Q63) -> 0
A64: ='Bldgs & Rooms'!$A$3 -> Main Bldg. | B64: ='Bldgs & Rooms'!$B$3 -> 0 | C64: =Hours!$A$27 -> Automatic Transfer Switch (ATS) > 100A | D64: =MAX(E64+F64,G64,H64,I64,J64,K64,L64,M64,N64,O64,P64,Q64) -> 0 | E64: =IF('Components Yr 1'!E64=0,0,'Components Yr 1'!E64) -> 0 | F64: =IF('Components Yr 1'!F64=0,0,'Components Yr 1'!F64) -> 0 | G64: =IF('Components Yr 1'!G64=0,0,'Components Yr 1'!G64) -> 0 | H64: =IF('Components Yr 1'!H64=0,0,'Components Yr 1'!H64) -> 0 | I64: =IF('Components Yr 1'!I64=0,0,'Components Yr 1'!I64) -> 0 | J64: =IF('Components Yr 1'!J64=0,0,'Components Yr 1'!J64) -> 0 | R64: =IF(SUMPRODUCT((E64:Q64)*1)=0,0,E64*INDEX(Hours!M:M,MATCH(C64,Hours!$A:$A,0))+F64*INDEX(Hours!B:B,MATCH(C64,Hours!$A:$A,0))+G64*INDEX(Hours!C:C,MATCH(C64,Hours!$A:$A,0))+H64*INDEX(Hours!D:D,MATCH(C64,Hours!$A:$A,0))+I64*INDEX(Hours!E:E,MATCH(C64,Hours!$A:$A,0))+J64*INDEX(Hours!F:F,MATCH(C64,Hours!$A:$A,0))) -> 0 | S64: =MAX(E64+F64,G64,H64,I64,J64,K64,L64,M64,N64,O64,P64,Q64) -> 0
A65: ='Bldgs & Rooms'!$A$3 -> Main Bldg. | B65: ='Bldgs & Rooms'!$B$3 -> 0 | C65: =Hours!$A$28 -> Manual Transfer Switch (MTS) > 100A | D65: =MAX(E65+F65,G65,H65,I65,J65,K65,L65,M65,N65,O65,P65,Q65) -> 0 | E65: =IF('Components Yr 1'!E65=0,0,'Components Yr 1'!E65) -> 0 | F65: =IF('Components Yr 1'!F65=0,0,'Components Yr 1'!F65) -> 0 | G65: =IF('Components Yr 1'!G65=0,0,'Components Yr 1'!G65) -> 0 | H65: =IF('Components Yr 1'!H65=0,0,'Components Yr 1'!H65) -> 0 | I65: =IF('Components Yr 1'!I65=0,0,'Components Yr 1'!I65) -> 0 | J65: =IF('Components Yr 1'!J65=0,0,'Components Yr 1'!J65) -> 0 | R65: =IF(SUMPRODUCT((E65:Q65)*1)=0,0,E65*INDEX(Hours!M:M,MATCH(C65,Hours!$A:$A,0))+F65*INDEX(Hours!B:B,MATCH(C65,Hours!$A:$A,0))+G65*INDEX(Hours!C:C,MATCH(C65,Hours!$A:$A,0))+H65*INDEX(Hours!D:D,MATCH(C65,Hours!$A:$A,0))+I65*INDEX(Hours!E:E,MATCH(C65,Hours!$A:$A,0))+J65*INDEX(Hours!F:F,MATCH(C65,Hours!$A:$A,0))) -> 0 | S65: =MAX(E65+F65,G65,H65,I65,J65,K65,L65,M65,N65,O65,P65,Q65) -> 0
A66: ='Bldgs & Rooms'!$A$3 -> Main Bldg. | B66: ='Bldgs & Rooms'!$B$3 -> 0 | C66: =Hours!$A$29 -> Variable Frequency Drives (VFD) < 50 HP | D66: =MAX(E66+F66,G66,H66,I66,J66,K66,L66,M66,N66,O66,P66,Q66) -> 0 | E66: =IF('Components Yr 1'!E66=0,0,'Components Yr 1'!E66) -> 0 | F66: =IF('Components Yr 1'!F66=0,0,'Components Yr 1'!F66) -> 0 | G66: =IF('Components Yr 1'!G66=0,0,'Components Yr 1'!G66) -> 0 | H66: =IF('Components Yr 1'!H66=0,0,'Components Yr 1'!H66) -> 0 | I66: =IF('Components Yr 1'!I66=0,0,'Components Yr 1'!I66) -> 0 | J66: =IF('Components Yr 1'!J66=0,0,'Components Yr 1'!J66) -> 0 | R66: =IF(SUMPRODUCT((E66:Q66)*1)=0,0,E66*INDEX(Hours!M:M,MATCH(C66,Hours!$A:$A,0))+F66*INDEX(Hours!B:B,MATCH(C66,Hours!$A:$A,0))+G66*INDEX(Hours!C:C,MATCH(C66,Hours!$A:$A,0))+H66*INDEX(Hours!D:D,MATCH(C66,Hours!$A:$A,0))+I66*INDEX(Hours!E:E,MATCH(C66,Hours!$A:$A,0))+J66*INDEX(Hours!F:F,MATCH(C66,Hours!$A:$A,0))) -> 0 | S66: =MAX(E66+F66,G66,H66,I66,J66,K66,L66,M66,N66,O66,P66,Q66) -> 0
A67: ='Bldgs & Rooms'!$A$3 -> Main Bldg. | B67: ='Bldgs & Rooms'!$B$3 -> 0 | C67: =Hours!$A$30 -> Variable Frequency Drives (VFD) 51-200 HP | D67: =MAX(E67+F67,G67,H67,I67,J67,K67,L67,M67,N67,O67,P67,Q67) -> 0 | E67: =IF('Components Yr 1'!E67=0,0,'Components Yr 1'!E67) -> 0 | F67: =IF('Components Yr 1'!F67=0,0,'Components Yr 1'!F67) -> 0 | G67: =IF('Components Yr 1'!G67=0,0,'Components Yr 1'!G67) -> 0 | H67: =IF('Components Yr 1'!H67=0,0,'Components Yr 1'!H67) -> 0 | I67: =IF('Components Yr 1'!I67=0,0,'Components Yr 1'!I67) -> 0 | J67: =IF('Components Yr 1'!J67=0,0,'Components Yr 1'!J67) -> 0 | R67: =IF(SUMPRODUCT((E67:Q67)*1)=0,0,E67*INDEX(Hours!M:M,MATCH(C67,Hours!$A:$A,0))+F67*INDEX(Hours!B:B,MATCH(C67,Hours!$A:$A,0))+G67*INDEX(Hours!C:C,MATCH(C67,Hours!$A:$A,0))+H67*INDEX(Hours!D:D,MATCH(C67,Hours!$A:$A,0))+I67*INDEX(Hours!E:E,MATCH(C67,Hours!$A:$A,0))+J67*INDEX(Hours!F:F,MATCH(C67,Hours!$A:$A,0))) -> 0 | S67: =MAX(E67+F67,G67,H67,I67,J67,K67,L67,M67,N67,O67,P67,Q67) -> 0
A68: ='Bldgs & Rooms'!$A$3 -> Main Bldg. | B68: ='Bldgs & Rooms'!$B$3 -> 0 | C68: =Hours!$A$31 -> Motors < 50 HP | D68: =MAX(E68+F68,G68,H68,I68,J68,K68,L68,M68,N68,O68,P68,Q68) -> 0 | E68: =IF('Components Yr 1'!E68=0,0,'Components Yr 1'!E68) -> 0 | F68: =IF('Components Yr 1'!F68=0,0,'Components Yr 1'!F68) -> 0 | G68: =IF('Components Yr 1'!G68=0,0,'Components Yr 1'!G68) -> 0 | H68: =IF('Components Yr 1'!H68=0,0,'Components Yr 1'!H68) -> 0 | I68: =IF('Components Yr 1'!I68=0,0,'Components Yr 1'!I68) -> 0 | J68: =IF('Components Yr 1'!J68=0,0,'Components Yr 1'!J68) -> 0 | R68: =IF(SUMPRODUCT((E68:Q68)*1)=0,0,E68*INDEX(Hours!M:M,MATCH(C68,Hours!$A:$A,0))+F68*INDEX(Hours!B:B,MATCH(C68,Hours!$A:$A,0))+G68*INDEX(Hours!C:C,MATCH(C68,Hours!$A:$A,0))+H68*INDEX(Hours!D:D,MATCH(C68,Hours!$A:$A,0))+I68*INDEX(Hours!E:E,MATCH(C68,Hours!$A:$A,0))+J68*INDEX(Hours!F:F,MATCH(C68,Hours!$A:$A,0))) -> 0 | S68: =MAX(E68+F68,G68,H68,I68,J68,K68,L68,M68,N68,O68,P68,Q68) -> 0
A69: ='Bldgs & Rooms'!$A$3 -> Main Bldg. | B69: ='Bldgs & Rooms'!$B$3 -> 0 | C69: =Hours!$A$32 -> Motors 51-200 HP | D69: =MAX(E69+F69,G69,H69,I69,J69,K69,L69,M69,N69,O69,P69,Q69) -> 0 | E69: =IF('Components Yr 1'!E69=0,0,'Components Yr 1'!E69) -> 0 | F69: =IF('Components Yr 1'!F69=0,0,'Components Yr 1'!F69) -> 0 | G69: =IF('Components Yr 1'!G69=0,0,'Components Yr 1'!G69) -> 0 | H69: =IF('Components Yr 1'!H69=0,0,'Components Yr 1'!H69) -> 0 | I69: =IF('Components Yr 1'!I69=0,0,'Components Yr 1'!I69) -> 0 | J69: =IF('Components Yr 1'!J69=0,0,'Components Yr 1'!J69) -> 0 | R69: =IF(SUMPRODUCT((E69:Q69)*1)=0,0,E69*INDEX(Hours!M:M,MATCH(C69,Hours!$A:$A,0))+F69*INDEX(Hours!B:B,MATCH(C69,Hours!$A:$A,0))+G69*INDEX(Hours!C:C,MATCH(C69,Hours!$A:$A,0))+H69*INDEX(Hours!D:D,MATCH(C69,Hours!$A:$A,0))+I69*INDEX(Hours!E:E,MATCH(C69,Hours!$A:$A,0))+J69*INDEX(Hours!F:F,MATCH(C69,Hours!$A:$A,0))) -> 0 | S69: =MAX(E69+F69,G69,H69,I69,J69,K69,L69,M69,N69,O69,P69,Q69) -> 0
A70: ='Bldgs & Rooms'!$A$3 -> Main Bldg. | B70: ='Bldgs & Rooms'!$B$3 -> 0 | C70: =Hours!$A$33 -> Motors 201-500 HP | D70: =MAX(E70+F70,G70,H70,I70,J70,K70,L70,M70,N70,O70,P70,Q70) -> 0 | E70: =IF('Components Yr 1'!E70=0,0,'Components Yr 1'!E70) -> 0 | F70: =IF('Components Yr 1'!F70=0,0,'Components Yr 1'!F70) -> 0 | G70: =IF('Components Yr 1'!G70=0,0,'Components Yr 1'!G70) -> 0 | H70: =IF('Components Yr 1'!H70=0,0,'Components Yr 1'!H70) -> 0 | I70: =IF('Components Yr 1'!I70=0,0,'Components Yr 1'!I70) -> 0 | J70: =IF('Components Yr 1'!J70=0,0,'Components Yr 1'!J70) -> 0 | R70: =IF(SUMPRODUCT((E70:Q70)*1)=0,0,E70*INDEX(Hours!M:M,MATCH(C70,Hours!$A:$A,0))+F70*INDEX(Hours!B:B,MATCH(C70,Hours!$A:$A,0))+G70*INDEX(Hours!C:C,MATCH(C70,Hours!$A:$A,0))+H70*INDEX(Hours!D:D,MATCH(C70,Hours!$A:$A,0))+I70*INDEX(Hours!E:E,MATCH(C70,Hours!$A:$A,0))+J70*INDEX(Hours!F:F,MATCH(C70,Hours!$A:$A,0))) -> 0 | S70: =MAX(E70+F70,G70,H70,I70,J70,K70,L70,M70,N70,O70,P70,Q70) -> 0
A71: ='Bldgs & Rooms'!$A$3 -> Main Bldg. | B71: ='Bldgs & Rooms'!$B$3 -> 0 | C71: =Hours!$A$34 -> Compressed Air Equipment | D71: =MAX(E71+F71,G71,H71,I71,J71,K71,L71,M71,N71,O71,P71,Q71) -> 0 | E71: =IF('Components Yr 1'!E71=0,0,'Components Yr 1'!E71) -> 0 | F71: =IF('Components Yr 1'!F71=0,0,'Components Yr 1'!F71) -> 0 | G71: =IF('Components Yr 1'!G71=0,0,'Components Yr 1'!G71) -> 0 | H71: =IF('Components Yr 1'!H71=0,0,'Components Yr 1'!H71) -> 0 | I71: =IF('Components Yr 1'!I71=0,0,'Components Yr 1'!I71) -> 0 | J71: =IF('Components Yr 1'!J71=0,0,'Components Yr 1'!J71) -> 0 | R71: =IF(SUMPRODUCT((E71:Q71)*1)=0,0,E71*INDEX(Hours!M:M,MATCH(C71,Hours!$A:$A,0))+F71*INDEX(Hours!B:B,MATCH(C71,Hours!$A:$A,0))+G71*INDEX(Hours!C:C,MATCH(C71,Hours!$A:$A,0))+H71*INDEX(Hours!D:D,MATCH(C71,Hours!$A:$A,0))+I71*INDEX(Hours!E:E,MATCH(C71,Hours!$A:$A,0))+J71*INDEX(Hours!F:F,MATCH(C71,Hours!$A:$A,0))) -> 0 | S71: =MAX(E71+F71,G71,H71,I71,J71,K71,L71,M71,N71,O71,P71,Q71) -> 0
A72: ='Bldgs & Rooms'!$A$3 -> Main Bldg. | B72: ='Bldgs & Rooms'!$B$3 -> 0 | C72: =Hours!$A$35 -> HVAC Equipment (Large) | D72: =MAX(E72+F72,G72,H72,I72,J72,K72,L72,M72,N72,O72,P72,Q72) -> 0 | E72: =IF('Components Yr 1'!E72=0,0,'Components Yr 1'!E72) -> 0 | F72: =IF('Components Yr 1'!F72=0,0,'Components Yr 1'!F72) -> 0 | G72: =IF('Components Yr 1'!G72=0,0,'Components Yr 1'!G72) -> 0 | H72: =IF('Components Yr 1'!H72=0,0,'Components Yr 1'!H72) -> 0 | I72: =IF('Components Yr 1'!I72=0,0,'Components Yr 1'!I72) -> 0 | J72: =IF('Components Yr 1'!J72=0,0,'Components Yr 1'!J72) -> 0 | R72: =IF(SUMPRODUCT((E72:Q72)*1)=0,0,E72*INDEX(Hours!M:M,MATCH(C72,Hours!$A:$A,0))+F72*INDEX(Hours!B:B,MATCH(C72,Hours!$A:$A,0))+G72*INDEX(Hours!C:C,MATCH(C72,Hours!$A:$A,0))+H72*INDEX(Hours!D:D,MATCH(C72,Hours!$A:$A,0))+I72*INDEX(Hours!E:E,MATCH(C72,Hours!$A:$A,0))+J72*INDEX(Hours!F:F,MATCH(C72,Hours!$A:$A,0))) -> 0 | S72: =MAX(E72+F72,G72,H72,I72,J72,K72,L72,M72,N72,O72,P72,Q72) -> 0
A73: ='Bldgs & Rooms'!$A$3 -> Main Bldg. | B73: ='Bldgs & Rooms'!$B$3 -> 0 | C73: =Hours!$A$36 -> HVAC Equipment (Small) | D73: =MAX(E73+F73,G73,H73,I73,J73,K73,L73,M73,N73,O73,P73,Q73) -> 0 | E73: =IF('Components Yr 1'!E73=0,0,'Components Yr 1'!E73) -> 0 | F73: =IF('Components Yr 1'!F73=0,0,'Components Yr 1'!F73) -> 0 | G73: =IF('Components Yr 1'!G73=0,0,'Components Yr 1'!G73) -> 0 | H73: =IF('Components Yr 1'!H73=0,0,'Components Yr 1'!H73) -> 0 | I73: =IF('Components Yr 1'!I73=0,0,'Components Yr 1'!I73) -> 0 | J73: =IF('Components Yr 1'!J73=0,0,'Components Yr 1'!J73) -> 0 | R73: =IF(SUMPRODUCT((E73:Q73)*1)=0,0,E73*INDEX(Hours!M:M,MATCH(C73,Hours!$A:$A,0))+F73*INDEX(Hours!B:B,MATCH(C73,Hours!$A:$A,0))+G73*INDEX(Hours!C:C,MATCH(C73,Hours!$A:$A,0))+H73*INDEX(Hours!D:D,MATCH(C73,Hours!$A:$A,0))+I73*INDEX(Hours!E:E,MATCH(C73,Hours!$A:$A,0))+J73*INDEX(Hours!F:F,MATCH(C73,Hours!$A:$A,0))) -> 0 | S73: =MAX(E73+F73,G73,H73,I73,J73,K73,L73,M73,N73,O73,P73,Q73) -> 0
A74: ='Bldgs & Rooms'!$A$3 -> Main Bldg. | B74: ='Bldgs & Rooms'!$B$3 -> 0 | C74: =Hours!$A$37 -> Uninterruptible Power Supply (UPS) < 50kVA | D74: =MAX(E74+F74,G74,H74,I74,J74,K74,L74,M74,N74,O74,P74,Q74) -> 0 | E74: =IF('Components Yr 1'!E74=0,0,'Components Yr 1'!E74) -> 0 | F74: =IF('Components Yr 1'!F74=0,0,'Components Yr 1'!F74) -> 0 | G74: =IF('Components Yr 1'!G74=0,0,'Components Yr 1'!G74) -> 0 | H74: =IF('Components Yr 1'!H74=0,0,'Components Yr 1'!H74) -> 0 | I74: =IF('Components Yr 1'!I74=0,0,'Components Yr 1'!I74) -> 0 | J74: =IF('Components Yr 1'!J74=0,0,'Components Yr 1'!J74) -> 0 | R74: =IF(SUMPRODUCT((E74:Q74)*1)=0,0,E74*INDEX(Hours!M:M,MATCH(C74,Hours!$A:$A,0))+F74*INDEX(Hours!B:B,MATCH(C74,Hours!$A:$A,0))+G74*INDEX(Hours!C:C,MATCH(C74,Hours!$A:$A,0))+H74*INDEX(Hours!D:D,MATCH(C74,Hours!$A:$A,0))+I74*INDEX(Hours!E:E,MATCH(C74,Hours!$A:$A,0))+J74*INDEX(Hours!F:F,MATCH(C74,Hours!$A:$A,0))) -> 0 | S74: =MAX(E74+F74,G74,H74,I74,J74,K74,L74,M74,N74,O74,P74,Q74) -> 0
A75: ='Bldgs & Rooms'!$A$3 -> Main Bldg. | B75: ='Bldgs & Rooms'!$B$3 -> 0 | C75: =Hours!$A$38 -> Uninterruptible Power Supply (UPS) > 50kVA | D75: =MAX(E75+F75,G75,H75,I75,J75,K75,L75,M75,N75,O75,P75,Q75) -> 0 | E75: =IF('Components Yr 1'!E75=0,0,'Components Yr 1'!E75) -> 0 | F75: =IF('Components Yr 1'!F75=0,0,'Components Yr 1'!F75) -> 0 | G75: =IF('Components Yr 1'!G75=0,0,'Components Yr 1'!G75) -> 0 | H75: =IF('Components Yr 1'!H75=0,0,'Components Yr 1'!H75) -> 0 | I75: =IF('Components Yr 1'!I75=0,0,'Components Yr 1'!I75) -> 0 | J75: =IF('Components Yr 1'!J75=0,0,'Components Yr 1'!J75) -> 0 | R75: =IF(SUMPRODUCT((E75:Q75)*1)=0,0,E75*INDEX(Hours!M:M,MATCH(C75,Hours!$A:$A,0))+F75*INDEX(Hours!B:B,MATCH(C75,Hours!$A:$A,0))+G75*INDEX(Hours!C:C,MATCH(C75,Hours!$A:$A,0))+H75*INDEX(Hours!D:D,MATCH(C75,Hours!$A:$A,0))+I75*INDEX(Hours!E:E,MATCH(C75,Hours!$A:$A,0))+J75*INDEX(Hours!F:F,MATCH(C75,Hours!$A:$A,0))) -> 0 | S75: =MAX(E75+F75,G75,H75,I75,J75,K75,L75,M75,N75,O75,P75,Q75) -> 0
A76: ='Bldgs & Rooms'!$A$4 -> Main Bldg. | B76: ='Bldgs & Rooms'!$B$4 -> 0 | C76: =Hours!$A$2 -> Switchgear - Incoming Main Service (Per Section) | D76: =MAX(E76+F76,G76,H76,I76,J76,K76,L76,M76,N76,O76,P76,Q76) -> 0 | E76: =IF('Components Yr 1'!E76=0,0,'Components Yr 1'!E76) -> 0 | F76: =IF('Components Yr 1'!F76=0,0,'Components Yr 1'!F76) -> 0 | G76: =IF('Components Yr 1'!G76=0,0,'Components Yr 1'!G76) -> 0 | H76: =IF('Components Yr 1'!H76=0,0,'Components Yr 1'!H76) -> 0 | I76: =IF('Components Yr 1'!I76=0,0,'Components Yr 1'!I76) -> 0 | J76: =IF('Components Yr 1'!J76=0,0,'Components Yr 1'!J76) -> 0 | K76: =IF('Components Yr 1'!K76=0,0,'Components Yr 1'!K76) -> 0 | L76: =IF('Components Yr 1'!L76=0,0,'Components Yr 1'!L76) -> 0 | O76: =IF('Components Yr 1'!O76=0,0,'Components Yr 1'!O76) -> 0 | R76: =IF(SUMPRODUCT((E76:Q76)*1)=0,0,E76*INDEX(Hours!M:M,MATCH(C76,Hours!$A:$A,0))+F76*INDEX(Hours!B:B,MATCH(C76,Hours!$A:$A,0))+G76*INDEX(Hours!C:C,MATCH(C76,Hours!$A:$A,0))+H76*INDEX(Hours!D:D,MATCH(C76,Hours!$A:$A,0))+I76*INDEX(Hours!E:E,MATCH(C76,Hours!$A:$A,0))+J76*INDEX(Hours!F:F,MATCH(C76,Hours!$A:$A,0))+K76*INDEX(Hours!G:G,MATCH(C76,Hours!$A:$A,0))+L76*INDEX(Hours!H:H,MATCH(C76,Hours!$A:$A,0))+O76*INDEX(Hours!K:K,MATCH(C76,Hours!$A:$A,0))) -> 0 | S76: =MAX(E76+F76,G76,H76,I76,J76,K76,L76,M76,N76,O76,P76,Q76) -> 0
A77: ='Bldgs & Rooms'!$A$4 -> Main Bldg. | B77: ='Bldgs & Rooms'!$B$4 -> 0 | C77: =Hours!$A$3 -> Switchgear Insulated Case Breakers (Bus Mounted) | D77: =MAX(E77+F77,G77,H77,I77,J77,K77,L77,M77,N77,O77,P77,Q77) -> 0 | E77: =IF('Components Yr 1'!E77=0,0,'Components Yr 1'!E77) -> 0 | F77: =IF('Components Yr 1'!F77=0,0,'Components Yr 1'!F77) -> 0 | G77: =IF('Components Yr 1'!G77=0,0,'Components Yr 1'!G77) -> 0 | H77: =IF('Components Yr 1'!H77=0,0,'Components Yr 1'!H77) -> 0 | I77: =IF('Components Yr 1'!I77=0,0,'Components Yr 1'!I77) -> 0 | J77: =IF('Components Yr 1'!J77=0,0,'Components Yr 1'!J77) -> 0 | K77: =IF('Components Yr 1'!K77=0,0,'Components Yr 1'!K77) -> 0 | R77: =IF(SUMPRODUCT((E77:Q77)*1)=0,0,E77*INDEX(Hours!M:M,MATCH(C77,Hours!$A:$A,0))+F77*INDEX(Hours!B:B,MATCH(C77,Hours!$A:$A,0))+G77*INDEX(Hours!C:C,MATCH(C77,Hours!$A:$A,0))+H77*INDEX(Hours!D:D,MATCH(C77,Hours!$A:$A,0))+I77*INDEX(Hours!E:E,MATCH(C77,Hours!$A:$A,0))+J77*INDEX(Hours!F:F,MATCH(C77,Hours!$A:$A,0))+K77*INDEX(Hours!G:G,MATCH(C77,Hours!$A:$A,0))) -> 0 | S77: =MAX(E77+F77,G77,H77,I77,J77,K77,L77,M77,N77,O77,P77,Q77) -> 0
A78: ='Bldgs & Rooms'!$A$4 -> Main Bldg. | B78: ='Bldgs & Rooms'!$B$4 -> 0 | C78: =Hours!$A$4 -> SwitchGear Drawout Breakers | D78: =MAX(E78+F78,G78,H78,I78,J78,K78,L78,M78,N78,O78,P78,Q78) -> 0 | E78: =IF('Components Yr 1'!E78=0,0,'Components Yr 1'!E78) -> 0 | F78: =IF('Components Yr 1'!F78=0,0,'Components Yr 1'!F78) -> 0 | G78: =IF('Components Yr 1'!G78=0,0,'Components Yr 1'!G78) -> 0 | H78: =IF('Components Yr 1'!H78=0,0,'Components Yr 1'!H78) -> 0 | I78: =IF('Components Yr 1'!I78=0,0,'Components Yr 1'!I78) -> 0 | J78: =IF('Components Yr 1'!J78=0,0,'Components Yr 1'!J78) -> 0 | L78: =IF('Components Yr 1'!L78=0,0,'Components Yr 1'!L78) -> 0 | R78: =IF(SUMPRODUCT((E78:Q78)*1)=0,0,E78*INDEX(Hours!M:M,MATCH(C78,Hours!$A:$A,0))+F78*INDEX(Hours!B:B,MATCH(C78,Hours!$A:$A,0))+G78*INDEX(Hours!C:C,MATCH(C78,Hours!$A:$A,0))+H78*INDEX(Hours!D:D,MATCH(C78,Hours!$A:$A,0))+I78*INDEX(Hours!E:E,MATCH(C78,Hours!$A:$A,0))+J78*INDEX(Hours!F:F,MATCH(C78,Hours!$A:$A,0))+L78*INDEX(Hours!H:H,MATCH(C78,Hours!$A:$A,0))) -> 0 | S78: =MAX(E78+F78,G78,H78,I78,J78,K78,L78,M78,N78,O78,P78,Q78) -> 0
A79: ='Bldgs & Rooms'!$A$4 -> Main Bldg. | B79: ='Bldgs & Rooms'!$B$4 -> 0 | C79: =Hours!$A$5 -> Distribution Switchboard Multi Cover (Per Section) | D79: =MAX(E79+F79,G79,H79,I79,J79,K79,L79,M79,N79,O79,P79,Q79) -> 0 | E79: =IF('Components Yr 1'!E79=0,0,'Components Yr 1'!E79) -> 0 | F79: =IF('Components Yr 1'!F79=0,0,'Components Yr 1'!F79) -> 0 | G79: =IF('Components Yr 1'!G79=0,0,'Components Yr 1'!G79) -> 0 | H79: =IF('Components Yr 1'!H79=0,0,'Components Yr 1'!H79) -> 0 | I79: =IF('Components Yr 1'!I79=0,0,'Components Yr 1'!I79) -> 0 | J79: =IF('Components Yr 1'!J79=0,0,'Components Yr 1'!J79) -> 0 | K79: =IF('Components Yr 1'!K79=0,0,'Components Yr 1'!K79) -> 0 | O79: =IF('Components Yr 1'!O79=0,0,'Components Yr 1'!O79) -> 0 | R79: =IF(SUMPRODUCT((E79:Q79)*1)=0,0,E79*INDEX(Hours!M:M,MATCH(C79,Hours!$A:$A,0))+F79*INDEX(Hours!B:B,MATCH(C79,Hours!$A:$A,0))+G79*INDEX(Hours!C:C,MATCH(C79,Hours!$A:$A,0))+H79*INDEX(Hours!D:D,MATCH(C79,Hours!$A:$A,0))+I79*INDEX(Hours!E:E,MATCH(C79,Hours!$A:$A,0))+J79*INDEX(Hours!F:F,MATCH(C79,Hours!$A:$A,0))+K79*INDEX(Hours!G:G,MATCH(C79,Hours!$A:$A,0))+O79*INDEX(Hours!K:K,MATCH(C79,Hours!$A:$A,0))) -> 0 | S79: =MAX(E79+F79,G79,H79,I79,J79,K79,L79,M79,N79,O79,P79,Q79) -> 0
A80: ='Bldgs & Rooms'!$A$4 -> Main Bldg. | B80: ='Bldgs & Rooms'!$B$4 -> 0 | C80: =Hours!$A$6 -> Switchboard Disconnects | D80: =MAX(E80+F80,G80,H80,I80,J80,K80,L80,M80,N80,O80,P80,Q80) -> 0 | E80: =IF('Components Yr 1'!E80=0,0,'Components Yr 1'!E80) -> 0 | F80: =IF('Components Yr 1'!F80=0,0,'Components Yr 1'!F80) -> 0 | G80: =IF('Components Yr 1'!G80=0,0,'Components Yr 1'!G80) -> 0 | H80: =IF('Components Yr 1'!H80=0,0,'Components Yr 1'!H80) -> 0 | I80: =IF('Components Yr 1'!I80=0,0,'Components Yr 1'!I80) -> 0 | J80: =IF('Components Yr 1'!J80=0,0,'Components Yr 1'!J80) -> 0 | R80: =IF(SUMPRODUCT((E80:Q80)*1)=0,0,E80*INDEX(Hours!M:M,MATCH(C80,Hours!$A:$A,0))+F80*INDEX(Hours!B:B,MATCH(C80,Hours!$A:$A,0))+G80*INDEX(Hours!C:C,MATCH(C80,Hours!$A:$A,0))+H80*INDEX(Hours!D:D,MATCH(C80,Hours!$A:$A,0))+I80*INDEX(Hours!E:E,MATCH(C80,Hours!$A:$A,0))+J80*INDEX(Hours!F:F,MATCH(C80,Hours!$A:$A,0))) -> 0 | S80: =MAX(E80+F80,G80,H80,I80,J80,K80,L80,M80,N80,O80,P80,Q80) -> 0
A81: ='Bldgs & Rooms'!$A$4 -> Main Bldg. | B81: ='Bldgs & Rooms'!$B$4 -> 0 | C81: =Hours!$A$7 -> Switchboard Molded Case Breakers | D81: =MAX(E81+F81,G81,H81,I81,J81,K81,L81,M81,N81,O81,P81,Q81) -> 0 | E81: =IF('Components Yr 1'!E81=0,0,'Components Yr 1'!E81) -> 0 | F81: =IF('Components Yr 1'!F81=0,0,'Components Yr 1'!F81) -> 0 | G81: =IF('Components Yr 1'!G81=0,0,'Components Yr 1'!G81) -> 0 | H81: =IF('Components Yr 1'!H81=0,0,'Components Yr 1'!H81) -> 0 | I81: =IF('Components Yr 1'!I81=0,0,'Components Yr 1'!I81) -> 0 | J81: =IF('Components Yr 1'!J81=0,0,'Components Yr 1'!J81) -> 0 | K81: =IF('Components Yr 1'!K81=0,0,'Components Yr 1'!K81) -> 0 | R81: =IF(SUMPRODUCT((E81:Q81)*1)=0,0,E81*INDEX(Hours!M:M,MATCH(C81,Hours!$A:$A,0))+F81*INDEX(Hours!B:B,MATCH(C81,Hours!$A:$A,0))+G81*INDEX(Hours!C:C,MATCH(C81,Hours!$A:$A,0))+H81*INDEX(Hours!D:D,MATCH(C81,Hours!$A:$A,0))+I81*INDEX(Hours!E:E,MATCH(C81,Hours!$A:$A,0))+J81*INDEX(Hours!F:F,MATCH(C81,Hours!$A:$A,0))+K81*INDEX(Hours!G:G,MATCH(C81,Hours!$A:$A,0))) -> 0 | S81: =MAX(E81+F81,G81,H81,I81,J81,K81,L81,M81,N81,O81,P81,Q81) -> 0
A82: ='Bldgs & Rooms'!$A$4 -> Main Bldg. | B82: ='Bldgs & Rooms'!$B$4 -> 0 | C82: =Hours!$A$8 -> Panelboard-Single Cover > 400A (Distribution Panel) | D82: =MAX(E82+F82,G82,H82,I82,J82,K82,L82,M82,N82,O82,P82,Q82) -> 0 | E82: =IF('Components Yr 1'!E82=0,0,'Components Yr 1'!E82) -> 0 | F82: =IF('Components Yr 1'!F82=0,0,'Components Yr 1'!F82) -> 0 | G82: =IF('Components Yr 1'!G82=0,0,'Components Yr 1'!G82) -> 0 | H82: =IF('Components Yr 1'!H82=0,0,'Components Yr 1'!H82) -> 0 | I82: =IF('Components Yr 1'!I82=0,0,'Components Yr 1'!I82) -> 0 | J82: =IF('Components Yr 1'!J82=0,0,'Components Yr 1'!J82) -> 0 | K82: =IF('Components Yr 1'!K82=0,0,'Components Yr 1'!K82) -> 0 | O82: =IF('Components Yr 1'!O82=0,0,'Components Yr 1'!O82) -> 0 | R82: =IF(SUMPRODUCT((E82:Q82)*1)=0,0,E82*INDEX(Hours!M:M,MATCH(C82,Hours!$A:$A,0))+F82*INDEX(Hours!B:B,MATCH(C82,Hours!$A:$A,0))+G82*INDEX(Hours!C:C,MATCH(C82,Hours!$A:$A,0))+H82*INDEX(Hours!D:D,MATCH(C82,Hours!$A:$A,0))+I82*INDEX(Hours!E:E,MATCH(C82,Hours!$A:$A,0))+J82*INDEX(Hours!F:F,MATCH(C82,Hours!$A:$A,0))+K82*INDEX(Hours!G:G,MATCH(C82,Hours!$A:$A,0))+O82*INDEX(Hours!K:K,MATCH(C82,Hours!$A:$A,0))) -> 0 | S82: =MAX(E82+F82,G82,H82,I82,J82,K82,L82,M82,N82,O82,P82,Q82) -> 0
A83: ='Bldgs & Rooms'!$A$4 -> Main Bldg. | B83: ='Bldgs & Rooms'!$B$4 -> 0 | C83: =Hours!$A$9 -> Panelboard-Single Cover < 400A (Branch Ckt Panel) | D83: =MAX(E83+F83,G83,H83,I83,J83,K83,L83,M83,N83,O83,P83,Q83) -> 0 | E83: =IF('Components Yr 1'!E83=0,0,'Components Yr 1'!E83) -> 0 | F83: =IF('Components Yr 1'!F83=0,0,'Components Yr 1'!F83) -> 0 | G83: =IF('Components Yr 1'!G83=0,0,'Components Yr 1'!G83) -> 0 | H83: =IF('Components Yr 1'!H83=0,0,'Components Yr 1'!H83) -> 0 | I83: =IF('Components Yr 1'!I83=0,0,'Components Yr 1'!I83) -> 0 | J83: =IF('Components Yr 1'!J83=0,0,'Components Yr 1'!J83) -> 0 | O83: =IF('Components Yr 1'!O83=0,0,'Components Yr 1'!O83) -> 0 | R83: =IF(SUMPRODUCT((E83:Q83)*1)=0,0,E83*INDEX(Hours!M:M,MATCH(C83,Hours!$A:$A,0))+F83*INDEX(Hours!B:B,MATCH(C83,Hours!$A:$A,0))+G83*INDEX(Hours!C:C,MATCH(C83,Hours!$A:$A,0))+H83*INDEX(Hours!D:D,MATCH(C83,Hours!$A:$A,0))+I83*INDEX(Hours!E:E,MATCH(C83,Hours!$A:$A,0))+J83*INDEX(Hours!F:F,MATCH(C83,Hours!$A:$A,0))+O83*INDEX(Hours!K:K,MATCH(C83,Hours!$A:$A,0))) -> 0 | S83: =MAX(E83+F83,G83,H83,I83,J83,K83,L83,M83,N83,O83,P83,Q83) -> 0
A84: ='Bldgs & Rooms'!$A$4 -> Main Bldg. | B84: ='Bldgs & Rooms'!$B$4 -> 0 | C84: =Hours!$A$10 -> Motor Control Center (MCC-Per Vertical Section) | D84: =MAX(E84+F84,G84,H84,I84,J84,K84,L84,M84,N84,O84,P84,Q84) -> 0 | E84: =IF('Components Yr 1'!E84=0,0,'Components Yr 1'!E84) -> 0 | F84: =IF('Components Yr 1'!F84=0,0,'Components Yr 1'!F84) -> 0 | G84: =IF('Components Yr 1'!G84=0,0,'Components Yr 1'!G84) -> 0 | H84: =IF('Components Yr 1'!H84=0,0,'Components Yr 1'!H84) -> 0 | I84: =IF('Components Yr 1'!I84=0,0,'Components Yr 1'!I84) -> 0 | J84: =IF('Components Yr 1'!J84=0,0,'Components Yr 1'!J84) -> 0 | O84: =IF('Components Yr 1'!O84=0,0,'Components Yr 1'!O84) -> 0 | R84: =IF(SUMPRODUCT((E84:Q84)*1)=0,0,E84*INDEX(Hours!M:M,MATCH(C84,Hours!$A:$A,0))+F84*INDEX(Hours!B:B,MATCH(C84,Hours!$A:$A,0))+G84*INDEX(Hours!C:C,MATCH(C84,Hours!$A:$A,0))+H84*INDEX(Hours!D:D,MATCH(C84,Hours!$A:$A,0))+I84*INDEX(Hours!E:E,MATCH(C84,Hours!$A:$A,0))+J84*INDEX(Hours!F:F,MATCH(C84,Hours!$A:$A,0))+O84*INDEX(Hours!K:K,MATCH(C84,Hours!$A:$A,0))) -> 0 | S84: =MAX(E84+F84,G84,H84,I84,J84,K84,L84,M84,N84,O84,P84,Q84) -> 0
A85: ='Bldgs & Rooms'!$A$4 -> Main Bldg. | B85: ='Bldgs & Rooms'!$B$4 -> 0 | C85: =Hours!$A$11 -> MCC: Combination Motor Starters | D85: =MAX(E85+F85,G85,H85,I85,J85,K85,L85,M85,N85,O85,P85,Q85) -> 0 | E85: =IF('Components Yr 1'!E85=0,0,'Components Yr 1'!E85) -> 0 | F85: =IF('Components Yr 1'!F85=0,0,'Components Yr 1'!F85) -> 0 | G85: =IF('Components Yr 1'!G85=0,0,'Components Yr 1'!G85) -> 0 | H85: =IF('Components Yr 1'!H85=0,0,'Components Yr 1'!H85) -> 0 | I85: =IF('Components Yr 1'!I85=0,0,'Components Yr 1'!I85) -> 0 | J85: =IF('Components Yr 1'!J85=0,0,'Components Yr 1'!J85) -> 0 | K85: =IF('Components Yr 1'!K85=0,0,'Components Yr 1'!K85) -> 0 | O85: =IF('Components Yr 1'!O85=0,0,'Components Yr 1'!O85) -> 0 | R85: =IF(SUMPRODUCT((E85:Q85)*1)=0,0,E85*INDEX(Hours!M:M,MATCH(C85,Hours!$A:$A,0))+F85*INDEX(Hours!B:B,MATCH(C85,Hours!$A:$A,0))+G85*INDEX(Hours!C:C,MATCH(C85,Hours!$A:$A,0))+H85*INDEX(Hours!D:D,MATCH(C85,Hours!$A:$A,0))+I85*INDEX(Hours!E:E,MATCH(C85,Hours!$A:$A,0))+J85*INDEX(Hours!F:F,MATCH(C85,Hours!$A:$A,0))+K85*INDEX(Hours!G:G,MATCH(C85,Hours!$A:$A,0))+O85*INDEX(Hours!K:K,MATCH(C85,Hours!$A:$A,0))) -> 0 | S85: =MAX(E85+F85,G85,H85,I85,J85,K85,L85,M85,N85,O85,P85,Q85) -> 0
A86: ='Bldgs & Rooms'!$A$4 -> Main Bldg. | B86: ='Bldgs & Rooms'!$B$4 -> 0 | C86: =Hours!$A$12 -> MCC: Molded Case Breaker | D86: =MAX(E86+F86,G86,H86,I86,J86,K86,L86,M86,N86,O86,P86,Q86) -> 0 | E86: =IF('Components Yr 1'!E86=0,0,'Components Yr 1'!E86) -> 0 | F86: =IF('Components Yr 1'!F86=0,0,'Components Yr 1'!F86) -> 0 | G86: =IF('Components Yr 1'!G86=0,0,'Components Yr 1'!G86) -> 0 | H86: =IF('Components Yr 1'!H86=0,0,'Components Yr 1'!H86) -> 0 | I86: =IF('Components Yr 1'!I86=0,0,'Components Yr 1'!I86) -> 0 | J86: =IF('Components Yr 1'!J86=0,0,'Components Yr 1'!J86) -> 0 | K86: =IF('Components Yr 1'!K86=0,0,'Components Yr 1'!K86) -> 0 | R86: =IF(SUMPRODUCT((E86:Q86)*1)=0,0,E86*INDEX(Hours!M:M,MATCH(C86,Hours!$A:$A,0))+F86*INDEX(Hours!B:B,MATCH(C86,Hours!$A:$A,0))+G86*INDEX(Hours!C:C,MATCH(C86,Hours!$A:$A,0))+H86*INDEX(Hours!D:D,MATCH(C86,Hours!$A:$A,0))+I86*INDEX(Hours!E:E,MATCH(C86,Hours!$A:$A,0))+J86*INDEX(Hours!F:F,MATCH(C86,Hours!$A:$A,0))+K86*INDEX(Hours!G:G,MATCH(C86,Hours!$A:$A,0))) -> 0 | S86: =MAX(E86+F86,G86,H86,I86,J86,K86,L86,M86,N86,O86,P86,Q86) -> 0
A87: ='Bldgs & Rooms'!$A$4 -> Main Bldg. | B87: ='Bldgs & Rooms'!$B$4 -> 0 | C87: =Hours!$A$13 -> MCC: Individual Disconnect Switch | D87: =MAX(E87+F87,G87,H87,I87,J87,K87,L87,M87,N87,O87,P87,Q87) -> 0 | E87: =IF('Components Yr 1'!E87=0,0,'Components Yr 1'!E87) -> 0 | F87: =IF('Components Yr 1'!F87=0,0,'Components Yr 1'!F87) -> 0 | G87: =IF('Components Yr 1'!G87=0,0,'Components Yr 1'!G87) -> 0 | H87: =IF('Components Yr 1'!H87=0,0,'Components Yr 1'!H87) -> 0 | I87: =IF('Components Yr 1'!I87=0,0,'Components Yr 1'!I87) -> 0 | J87: =IF('Components Yr 1'!J87=0,0,'Components Yr 1'!J87) -> 0 | R87: =IF(SUMPRODUCT((E87:Q87)*1)=0,0,E87*INDEX(Hours!M:M,MATCH(C87,Hours!$A:$A,0))+F87*INDEX(Hours!B:B,MATCH(C87,Hours!$A:$A,0))+G87*INDEX(Hours!C:C,MATCH(C87,Hours!$A:$A,0))+H87*INDEX(Hours!D:D,MATCH(C87,Hours!$A:$A,0))+I87*INDEX(Hours!E:E,MATCH(C87,Hours!$A:$A,0))+J87*INDEX(Hours!F:F,MATCH(C87,Hours!$A:$A,0))) -> 0 | S87: =MAX(E87+F87,G87,H87,I87,J87,K87,L87,M87,N87,O87,P87,Q87) -> 0
A88: ='Bldgs & Rooms'!$A$4 -> Main Bldg. | B88: ='Bldgs & Rooms'!$B$4 -> 0 | C88: =Hours!$A$14 -> Motor Control Panel (MCP) | D88: =MAX(E88+F88,G88,H88,I88,J88,K88,L88,M88,N88,O88,P88,Q88) -> 0 | E88: =IF('Components Yr 1'!E88=0,0,'Components Yr 1'!E88) -> 0 | F88: =IF('Components Yr 1'!F88=0,0,'Components Yr 1'!F88) -> 0 | G88: =IF('Components Yr 1'!G88=0,0,'Components Yr 1'!G88) -> 0 | H88: =IF('Components Yr 1'!H88=0,0,'Components Yr 1'!H88) -> 0 | I88: =IF('Components Yr 1'!I88=0,0,'Components Yr 1'!I88) -> 0 | J88: =IF('Components Yr 1'!J88=0,0,'Components Yr 1'!J88) -> 0 | O88: =IF('Components Yr 1'!O88=0,0,'Components Yr 1'!O88) -> 0 | R88: =IF(SUMPRODUCT((E88:Q88)*1)=0,0,E88*INDEX(Hours!M:M,MATCH(C88,Hours!$A:$A,0))+F88*INDEX(Hours!B:B,MATCH(C88,Hours!$A:$A,0))+G88*INDEX(Hours!C:C,MATCH(C88,Hours!$A:$A,0))+H88*INDEX(Hours!D:D,MATCH(C88,Hours!$A:$A,0))+I88*INDEX(Hours!E:E,MATCH(C88,Hours!$A:$A,0))+J88*INDEX(Hours!F:F,MATCH(C88,Hours!$A:$A,0))+O88*INDEX(Hours!K:K,MATCH(C88,Hours!$A:$A,0))) -> 0 | S88: =MAX(E88+F88,G88,H88,I88,J88,K88,L88,M88,N88,O88,P88,Q88) -> 0
A89: ='Bldgs & Rooms'!$A$4 -> Main Bldg. | B89: ='Bldgs & Rooms'!$B$4 -> 0 | C89: =Hours!$A$15 -> VFD Motor Control Panel (VFD-MCP) | D89: =MAX(E89+F89,G89,H89,I89,J89,K89,L89,M89,N89,O89,P89,Q89) -> 0 | E89: =IF('Components Yr 1'!E89=0,0,'Components Yr 1'!E89) -> 0 | F89: =IF('Components Yr 1'!F89=0,0,'Components Yr 1'!F89) -> 0 | G89: =IF('Components Yr 1'!G89=0,0,'Components Yr 1'!G89) -> 0 | H89: =IF('Components Yr 1'!H89=0,0,'Components Yr 1'!H89) -> 0 | I89: =IF('Components Yr 1'!I89=0,0,'Components Yr 1'!I89) -> 0 | J89: =IF('Components Yr 1'!J89=0,0,'Components Yr 1'!J89) -> 0 | O89: =IF('Components Yr 1'!O89=0,0,'Components Yr 1'!O89) -> 0 | R89: =IF(SUMPRODUCT((E89:Q89)*1)=0,0,E89*INDEX(Hours!M:M,MATCH(C89,Hours!$A:$A,0))+F89*INDEX(Hours!B:B,MATCH(C89,Hours!$A:$A,0))+G89*INDEX(Hours!C:C,MATCH(C89,Hours!$A:$A,0))+H89*INDEX(Hours!D:D,MATCH(C89,Hours!$A:$A,0))+I89*INDEX(Hours!E:E,MATCH(C89,Hours!$A:$A,0))+J89*INDEX(Hours!F:F,MATCH(C89,Hours!$A:$A,0))+O89*INDEX(Hours!K:K,MATCH(C89,Hours!$A:$A,0))) -> 0 | S89: =MAX(E89+F89,G89,H89,I89,J89,K89,L89,M89,N89,O89,P89,Q89) -> 0
A90: ='Bldgs & Rooms'!$A$4 -> Main Bldg. | B90: ='Bldgs & Rooms'!$B$4 -> 0 | C90: =Hours!$A$16 -> Individual Disconnect Switch > 100A | D90: =MAX(E90+F90,G90,H90,I90,J90,K90,L90,M90,N90,O90,P90,Q90) -> 0 | E90: =IF('Components Yr 1'!E90=0,0,'Components Yr 1'!E90) -> 0 | F90: =IF('Components Yr 1'!F90=0,0,'Components Yr 1'!F90) -> 0 | G90: =IF('Components Yr 1'!G90=0,0,'Components Yr 1'!G90) -> 0 | H90: =IF('Components Yr 1'!H90=0,0,'Components Yr 1'!H90) -> 0 | I90: =IF('Components Yr 1'!I90=0,0,'Components Yr 1'!I90) -> 0 | J90: =IF('Components Yr 1'!J90=0,0,'Components Yr 1'!J90) -> 0 | K90: =IF('Components Yr 1'!K90=0,0,'Components Yr 1'!K90) -> 0 | R90: =IF(SUMPRODUCT((E90:Q90)*1)=0,0,E90*INDEX(Hours!M:M,MATCH(C90,Hours!$A:$A,0))+F90*INDEX(Hours!B:B,MATCH(C90,Hours!$A:$A,0))+G90*INDEX(Hours!C:C,MATCH(C90,Hours!$A:$A,0))+H90*INDEX(Hours!D:D,MATCH(C90,Hours!$A:$A,0))+I90*INDEX(Hours!E:E,MATCH(C90,Hours!$A:$A,0))+J90*INDEX(Hours!F:F,MATCH(C90,Hours!$A:$A,0))+K90*INDEX(Hours!G:G,MATCH(C90,Hours!$A:$A,0))) -> 0 | S90: =MAX(E90+F90,G90,H90,I90,J90,K90,L90,M90,N90,O90,P90,Q90) -> 0
A91: ='Bldgs & Rooms'!$A$4 -> Main Bldg. | B91: ='Bldgs & Rooms'!$B$4 -> 0 | C91: =Hours!$A$17 -> Individual Molded Case Breaker > 100A | D91: =MAX(E91+F91,G91,H91,I91,J91,K91,L91,M91,N91,O91,P91,Q91) -> 0 | E91: =IF('Components Yr 1'!E91=0,0,'Components Yr 1'!E91) -> 0 | F91: =IF('Components Yr 1'!F91=0,0,'Components Yr 1'!F91) -> 0 | G91: =IF('Components Yr 1'!G91=0,0,'Components Yr 1'!G91) -> 0 | H91: =IF('Components Yr 1'!H91=0,0,'Components Yr 1'!H91) -> 0 | I91: =IF('Components Yr 1'!I91=0,0,'Components Yr 1'!I91) -> 0 | J91: =IF('Components Yr 1'!J91=0,0,'Components Yr 1'!J91) -> 0 | K91: =IF('Components Yr 1'!K91=0,0,'Components Yr 1'!K91) -> 0 | R91: =IF(SUMPRODUCT((E91:Q91)*1)=0,0,E91*INDEX(Hours!M:M,MATCH(C91,Hours!$A:$A,0))+F91*INDEX(Hours!B:B,MATCH(C91,Hours!$A:$A,0))+G91*INDEX(Hours!C:C,MATCH(C91,Hours!$A:$A,0))+H91*INDEX(Hours!D:D,MATCH(C91,Hours!$A:$A,0))+I91*INDEX(Hours!E:E,MATCH(C91,Hours!$A:$A,0))+J91*INDEX(Hours!F:F,MATCH(C91,Hours!$A:$A,0))+K91*INDEX(Hours!G:G,MATCH(C91,Hours!$A:$A,0))) -> 0 | S91: =MAX(E91+F91,G91,H91,I91,J91,K91,L91,M91,N91,O91,P91,Q91) -> 0
A92: ='Bldgs & Rooms'!$A$4 -> Main Bldg. | B92: ='Bldgs & Rooms'!$B$4 -> 0 | C92: =Hours!$A$18 -> Individual Combination Motor Starter > 100A | D92: =MAX(E92+F92,G92,H92,I92,J92,K92,L92,M92,N92,O92,P92,Q92) -> 0 | E92: =IF('Components Yr 1'!E92=0,0,'Components Yr 1'!E92) -> 0 | F92: =IF('Components Yr 1'!F92=0,0,'Components Yr 1'!F92) -> 0 | G92: =IF('Components Yr 1'!G92=0,0,'Components Yr 1'!G92) -> 0 | H92: =IF('Components Yr 1'!H92=0,0,'Components Yr 1'!H92) -> 0 | I92: =IF('Components Yr 1'!I92=0,0,'Components Yr 1'!I92) -> 0 | J92: =IF('Components Yr 1'!J92=0,0,'Components Yr 1'!J92) -> 0 | K92: =IF('Components Yr 1'!K92=0,0,'Components Yr 1'!K92) -> 0 | R92: =IF(SUMPRODUCT((E92:Q92)*1)=0,0,E92*INDEX(Hours!M:M,MATCH(C92,Hours!$A:$A,0))+F92*INDEX(Hours!B:B,MATCH(C92,Hours!$A:$A,0))+G92*INDEX(Hours!C:C,MATCH(C92,Hours!$A:$A,0))+H92*INDEX(Hours!D:D,MATCH(C92,Hours!$A:$A,0))+I92*INDEX(Hours!E:E,MATCH(C92,Hours!$A:$A,0))+J92*INDEX(Hours!F:F,MATCH(C92,Hours!$A:$A,0))+K92*INDEX(Hours!G:G,MATCH(C92,Hours!$A:$A,0))) -> 0 | S92: =MAX(E92+F92,G92,H92,I92,J92,K92,L92,M92,N92,O92,P92,Q92) -> 0
A93: ='Bldgs & Rooms'!$A$4 -> Main Bldg. | B93: ='Bldgs & Rooms'!$B$4 -> 0 | C93: =Hours!$A$19 -> Oil Filled Transformer - 5kV-15kV Primary - Any Size (Pad Mounted) | D93: =MAX(E93+F93,G93,H93,I93,J93,K93,L93,M93,N93,O93,P93,Q93) -> 0 | E93: =IF('Components Yr 1'!E93=0,0,'Components Yr 1'!E93) -> 0 | F93: =IF('Components Yr 1'!F93=0,0,'Components Yr 1'!F93) -> 0 | G93: =IF('Components Yr 1'!G93=0,0,'Components Yr 1'!G93) -> 0 | H93: =IF('Components Yr 1'!H93=0,0,'Components Yr 1'!H93) -> 0 | I93: =IF('Components Yr 1'!I93=0,0,'Components Yr 1'!I93) -> 0 | J93: =IF('Components Yr 1'!J93=0,0,'Components Yr 1'!J93) -> 0 | M93: =IF('Components Yr 1'!M93=0,0,'Components Yr 1'!M93) -> 0 | N93: =IF('Components Yr 1'!N93=0,0,'Components Yr 1'!N93) -> 0 | P93: =IF('Components Yr 1'!P93=0,0,'Components Yr 1'!P93) -> 0 | R93: =IF(SUMPRODUCT((E93:Q93)*1)=0,0,E93*INDEX(Hours!M:M,MATCH(C93,Hours!$A:$A,0))+F93*INDEX(Hours!B:B,MATCH(C93,Hours!$A:$A,0))+G93*INDEX(Hours!C:C,MATCH(C93,Hours!$A:$A,0))+H93*INDEX(Hours!D:D,MATCH(C93,Hours!$A:$A,0))+I93*INDEX(Hours!E:E,MATCH(C93,Hours!$A:$A,0))+J93*INDEX(Hours!F:F,MATCH(C93,Hours!$A:$A,0))+M93*INDEX(Hours!I:I,MATCH(C93,Hours!$A:$A,0))+N93*INDEX(Hours!J:J,MATCH(C93,Hours!$A:$A,0))+P93*INDEX(Hours!L:L,MATCH(C93,Hours!$A:$A,0))) -> 0 | S93: =MAX(E93+F93,G93,H93,I93,J93,K93,L93,M93,N93,O93,P93,Q93) -> 0
A94: ='Bldgs & Rooms'!$A$4 -> Main Bldg. | B94: ='Bldgs & Rooms'!$B$4 -> 0 | C94: =Hours!$A$20 -> Oil Filled Transformer - > 15kV Primary (Substation Class) | D94: =MAX(E94+F94,G94,H94,I94,J94,K94,L94,M94,N94,O94,P94,Q94) -> 0 | E94: =IF('Components Yr 1'!E94=0,0,'Components Yr 1'!E94) -> 0 | F94: =IF('Components Yr 1'!F94=0,0,'Components Yr 1'!F94) -> 0 | G94: =IF('Components Yr 1'!G94=0,0,'Components Yr 1'!G94) -> 0 | H94: =IF('Components Yr 1'!H94=0,0,'Components Yr 1'!H94) -> 0 | I94: =IF('Components Yr 1'!I94=0,0,'Components Yr 1'!I94) -> 0 | J94: =IF('Components Yr 1'!J94=0,0,'Components Yr 1'!J94) -> 0 | M94: =IF('Components Yr 1'!M94=0,0,'Components Yr 1'!M94) -> 0 | N94: =IF('Components Yr 1'!N94=0,0,'Components Yr 1'!N94) -> 0 | P94: =IF('Components Yr 1'!P94=0,0,'Components Yr 1'!P94) -> 0 | R94: =IF(SUMPRODUCT((E94:Q94)*1)=0,0,E94*INDEX(Hours!M:M,MATCH(C94,Hours!$A:$A,0))+F94*INDEX(Hours!B:B,MATCH(C94,Hours!$A:$A,0))+G94*INDEX(Hours!C:C,MATCH(C94,Hours!$A:$A,0))+H94*INDEX(Hours!D:D,MATCH(C94,Hours!$A:$A,0))+I94*INDEX(Hours!E:E,MATCH(C94,Hours!$A:$A,0))+J94*INDEX(Hours!F:F,MATCH(C94,Hours!$A:$A,0))+M94*INDEX(Hours!I:I,MATCH(C94,Hours!$A:$A,0))+N94*INDEX(Hours!J:J,MATCH(C94,Hours!$A:$A,0))+P94*INDEX(Hours!L:L,MATCH(C94,Hours!$A:$A,0))) -> 0 | S94: =MAX(E94+F94,G94,H94,I94,J94,K94,L94,M94,N94,O94,P94,Q94) -> 0
A95: ='Bldgs & Rooms'!$A$4 -> Main Bldg. | B95: ='Bldgs & Rooms'!$B$4 -> 0 | C95: =Hours!$A$21 -> Dry Type Transformer - < 480V Primary - Any Size kVA | D95: =MAX(E95+F95,G95,H95,I95,J95,K95,L95,M95,N95,O95,P95,Q95) -> 0 | E95: =IF('Components Yr 1'!E95=0,0,'Components Yr 1'!E95) -> 0 | F95: =IF('Components Yr 1'!F95=0,0,'Components Yr 1'!F95) -> 0 | G95: =IF('Components Yr 1'!G95=0,0,'Components Yr 1'!G95) -> 0 | H95: =IF('Components Yr 1'!H95=0,0,'Components Yr 1'!H95) -> 0 | I95: =IF('Components Yr 1'!I95=0,0,'Components Yr 1'!I95) -> 0 | J95: =IF('Components Yr 1'!J95=0,0,'Components Yr 1'!J95) -> 0 | M95: =IF('Components Yr 1'!M95=0,0,'Components Yr 1'!M95) -> 0 | N95: =IF('Components Yr 1'!N95=0,0,'Components Yr 1'!N95) -> 0 | R95: =IF(SUMPRODUCT((E95:Q95)*1)=0,0,E95*INDEX(Hours!M:M,MATCH(C95,Hours!$A:$A,0))+F95*INDEX(Hours!B:B,MATCH(C95,Hours!$A:$A,0))+G95*INDEX(Hours!C:C,MATCH(C95,Hours!$A:$A,0))+H95*INDEX(Hours!D:D,MATCH(C95,Hours!$A:$A,0))+I95*INDEX(Hours!E:E,MATCH(C95,Hours!$A:$A,0))+J95*INDEX(Hours!F:F,MATCH(C95,Hours!$A:$A,0))+M95*INDEX(Hours!I:I,MATCH(C95,Hours!$A:$A,0))+N95*INDEX(Hours!J:J,MATCH(C95,Hours!$A:$A,0))) -> 0 | S95: =MAX(E95+F95,G95,H95,I95,J95,K95,L95,M95,N95,O95,P95,Q95) -> 0
A96: ='Bldgs & Rooms'!$A$4 -> Main Bldg. | B96: ='Bldgs & Rooms'!$B$4 -> 0 | C96: =Hours!$A$22 -> Power Factor Correction Capacitors | D96: =MAX(E96+F96,G96,H96,I96,J96,K96,L96,M96,N96,O96,P96,Q96) -> 0 | E96: =IF('Components Yr 1'!E96=0,0,'Components Yr 1'!E96) -> 0 | F96: =IF('Components Yr 1'!F96=0,0,'Components Yr 1'!F96) -> 0 | G96: =IF('Components Yr 1'!G96=0,0,'Components Yr 1'!G96) -> 0 | H96: =IF('Components Yr 1'!H96=0,0,'Components Yr 1'!H96) -> 0 | I96: =IF('Components Yr 1'!I96=0,0,'Components Yr 1'!I96) -> 0 | J96: =IF('Components Yr 1'!J96=0,0,'Components Yr 1'!J96) -> 0 | R96: =IF(SUMPRODUCT((E96:Q96)*1)=0,0,E96*INDEX(Hours!M:M,MATCH(C96,Hours!$A:$A,0))+F96*INDEX(Hours!B:B,MATCH(C96,Hours!$A:$A,0))+G96*INDEX(Hours!C:C,MATCH(C96,Hours!$A:$A,0))+H96*INDEX(Hours!D:D,MATCH(C96,Hours!$A:$A,0))+I96*INDEX(Hours!E:E,MATCH(C96,Hours!$A:$A,0))+J96*INDEX(Hours!F:F,MATCH(C96,Hours!$A:$A,0))) -> 0 | S96: =MAX(E96+F96,G96,H96,I96,J96,K96,L96,M96,N96,O96,P96,Q96) -> 0
A97: ='Bldgs & Rooms'!$A$4 -> Main Bldg. | B97: ='Bldgs & Rooms'!$B$4 -> 0 | C97: =Hours!$A$23 -> Lighting Contactor > 100A | D97: =MAX(E97+F97,G97,H97,I97,J97,K97,L97,M97,N97,O97,P97,Q97) -> 0 | E97: =IF('Components Yr 1'!E97=0,0,'Components Yr 1'!E97) -> 0 | F97: =IF('Components Yr 1'!F97=0,0,'Components Yr 1'!F97) -> 0 | G97: =IF('Components Yr 1'!G97=0,0,'Components Yr 1'!G97) -> 0 | H97: =IF('Components Yr 1'!H97=0,0,'Components Yr 1'!H97) -> 0 | I97: =IF('Components Yr 1'!I97=0,0,'Components Yr 1'!I97) -> 0 | J97: =IF('Components Yr 1'!J97=0,0,'Components Yr 1'!J97) -> 0 | R97: =IF(SUMPRODUCT((E97:Q97)*1)=0,0,E97*INDEX(Hours!M:M,MATCH(C97,Hours!$A:$A,0))+F97*INDEX(Hours!B:B,MATCH(C97,Hours!$A:$A,0))+G97*INDEX(Hours!C:C,MATCH(C97,Hours!$A:$A,0))+H97*INDEX(Hours!D:D,MATCH(C97,Hours!$A:$A,0))+I97*INDEX(Hours!E:E,MATCH(C97,Hours!$A:$A,0))+J97*INDEX(Hours!F:F,MATCH(C97,Hours!$A:$A,0))) -> 0 | S97: =MAX(E97+F97,G97,H97,I97,J97,K97,L97,M97,N97,O97,P97,Q97) -> 0
A98: ='Bldgs & Rooms'!$A$4 -> Main Bldg. | B98: ='Bldgs & Rooms'!$B$4 -> 0 | C98: =Hours!$A$24 -> Power Distribution Unit (PDU) | D98: =MAX(E98+F98,G98,H98,I98,J98,K98,L98,M98,N98,O98,P98,Q98) -> 0 | E98: =IF('Components Yr 1'!E98=0,0,'Components Yr 1'!E98) -> 0 | F98: =IF('Components Yr 1'!F98=0,0,'Components Yr 1'!F98) -> 0 | G98: =IF('Components Yr 1'!G98=0,0,'Components Yr 1'!G98) -> 0 | H98: =IF('Components Yr 1'!H98=0,0,'Components Yr 1'!H98) -> 0 | I98: =IF('Components Yr 1'!I98=0,0,'Components Yr 1'!I98) -> 0 | J98: =IF('Components Yr 1'!J98=0,0,'Components Yr 1'!J98) -> 0 | R98: =IF(SUMPRODUCT((E98:Q98)*1)=0,0,E98*INDEX(Hours!M:M,MATCH(C98,Hours!$A:$A,0))+F98*INDEX(Hours!B:B,MATCH(C98,Hours!$A:$A,0))+G98*INDEX(Hours!C:C,MATCH(C98,Hours!$A:$A,0))+H98*INDEX(Hours!D:D,MATCH(C98,Hours!$A:$A,0))+I98*INDEX(Hours!E:E,MATCH(C98,Hours!$A:$A,0))+J98*INDEX(Hours!F:F,MATCH(C98,Hours!$A:$A,0))) -> 0 | S98: =MAX(E98+F98,G98,H98,I98,J98,K98,L98,M98,N98,O98,P98,Q98) -> 0
A99: ='Bldgs & Rooms'!$A$4 -> Main Bldg. | B99: ='Bldgs & Rooms'!$B$4 -> 0 | C99: =Hours!$A$25 -> Wire Trough, Gutter, or Large Junction Boxes | D99: =MAX(E99+F99,G99,H99,I99,J99,K99,L99,M99,N99,O99,P99,Q99) -> 0 | E99: =IF('Components Yr 1'!E99=0,0,'Components Yr 1'!E99) -> 0 | F99: =IF('Components Yr 1'!F99=0,0,'Components Yr 1'!F99) -> 0 | G99: =IF('Components Yr 1'!G99=0,0,'Components Yr 1'!G99) -> 0 | H99: =IF('Components Yr 1'!H99=0,0,'Components Yr 1'!H99) -> 0 | I99: =IF('Components Yr 1'!I99=0,0,'Components Yr 1'!I99) -> 0 | J99: =IF('Components Yr 1'!J99=0,0,'Components Yr 1'!J99) -> 0 | R99: =IF(SUMPRODUCT((E99:Q99)*1)=0,0,E99*INDEX(Hours!M:M,MATCH(C99,Hours!$A:$A,0))+F99*INDEX(Hours!B:B,MATCH(C99,Hours!$A:$A,0))+G99*INDEX(Hours!C:C,MATCH(C99,Hours!$A:$A,0))+H99*INDEX(Hours!D:D,MATCH(C99,Hours!$A:$A,0))+I99*INDEX(Hours!E:E,MATCH(C99,Hours!$A:$A,0))+J99*INDEX(Hours!F:F,MATCH(C99,Hours!$A:$A,0))) -> 0 | S99: =MAX(E99+F99,G99,H99,I99,J99,K99,L99,M99,N99,O99,P99,Q99) -> 0
A100: ='Bldgs & Rooms'!$A$4 -> Main Bldg. | B100: ='Bldgs & Rooms'!$B$4 -> 0 | C100: =Hours!$A$26 -> Bus Duct - Vertical or Horizontal (Per 10' section) | D100: =MAX(E100+F100,G100,H100,I100,J100,K100,L100,M100,N100,O100,P100,Q100) -> 0 | E100: =IF('Components Yr 1'!E100=0,0,'Components Yr 1'!E100) -> 0 | F100: =IF('Components Yr 1'!F100=0,0,'Components Yr 1'!F100) -> 0 | G100: =IF('Components Yr 1'!G100=0,0,'Components Yr 1'!G100) -> 0 | H100: =IF('Components Yr 1'!H100=0,0,'Components Yr 1'!H100) -> 0 | I100: =IF('Components Yr 1'!I100=0,0,'Components Yr 1'!I100) -> 0 | J100: =IF('Components Yr 1'!J100=0,0,'Components Yr 1'!J100) -> 0 | R100: =IF(SUMPRODUCT((E100:Q100)*1)=0,0,E100*INDEX(Hours!M:M,MATCH(C100,Hours!$A:$A,0))+F100*INDEX(Hours!B:B,MATCH(C100,Hours!$A:$A,0))+G100*INDEX(Hours!C:C,MATCH(C100,Hours!$A:$A,0))+H100*INDEX(Hours!D:D,MATCH(C100,Hours!$A:$A,0))+I100*INDEX(Hours!E:E,MATCH(C100,Hours!$A:$A,0))+J100*INDEX(Hours!F:F,MATCH(C100,Hours!$A:$A,0))) -> 0 | S100: =MAX(E100+F100,G100,H100,I100,J100,K100,L100,M100,N100,O100,P100,Q100) -> 0
...

Sheet Components Yr 3
A1: Building | B1: Room | C1: 600 Volt and below | D1: Total Counted | E1: Basic EPM | F1: Full EPM | G1: De-Energized | H1: IR | I1: Ultrasonic | J1: A-F Collection | K1: Pri.Breaker | L1: Sec. Breaker | M1: PwrFact (partial) | N1: PwrFact (xfmr/CB) | O1: Panel Schd. | P1: Oil Sample | Q1: ESA | R1: Total Hours | S1: Total pcs. priced
A2: ='Bldgs & Rooms'!$A$2 -> Main Bldg. | B2: ='Bldgs & Rooms'!$B$2 -> 0 | C2: =Hours!$A$2 -> Switchgear - Incoming Main Service (Per Section) | D2: =MAX(E2+F2,G2,H2,I2,J2,K2,L2,M2,N2,O2,P2,Q2) -> 0 | E2: =IF('Components Yr 1'!E2=0,0,'Components Yr 1'!E2) -> 0 | F2: =IF('Components Yr 1'!F2=0,0,'Components Yr 1'!F2) -> 0 | G2: =IF('Components Yr 1'!G2=0,0,'Components Yr 1'!G2) -> 0 | H2: =IF('Components Yr 1'!H2=0,0,'Components Yr 1'!H2) -> 0 | I2: =IF('Components Yr 1'!I2=0,0,'Components Yr 1'!I2) -> 0 | J2: =IF('Components Yr 1'!J2=0,0,'Components Yr 1'!J2) -> 0 | K2: =IF('Components Yr 1'!K2=0,0,'Components Yr 1'!K2) -> 0 | L2: =IF('Components Yr 1'!L2=0,0,'Components Yr 1'!L2) -> 0 | O2: =IF('Components Yr 1'!O2=0,0,'Components Yr 1'!O2) -> 0 | R2: =IF(SUMPRODUCT((E2:Q2)*1)=0,0,E2*INDEX(Hours!M:M,MATCH(C2,Hours!$A:$A,0))+F2*INDEX(Hours!B:B,MATCH(C2,Hours!$A:$A,0))+G2*INDEX(Hours!C:C,MATCH(C2,Hours!$A:$A,0))+H2*INDEX(Hours!D:D,MATCH(C2,Hours!$A:$A,0))+I2*INDEX(Hours!E:E,MATCH(C2,Hours!$A:$A,0))+J2*INDEX(Hours!F:F,MATCH(C2,Hours!$A:$A,0))+K2*INDEX(Hours!G:G,MATCH(C2,Hours!$A:$A,0))+L2*INDEX(Hours!H:H,MATCH(C2,Hours!$A:$A,0))+O2*INDEX(Hours!K:K,MATCH(C2,Hours!$A:$A,0))) -> 0 | S2: =MAX(E2+F2,G2,H2,I2,J2,K2,L2,M2,N2,O2,P2,Q2) -> 0
A3: ='Bldgs & Rooms'!$A$2 -> Main Bldg. | B3: ='Bldgs & Rooms'!$B$2 -> 0 | C3: =Hours!$A$3 -> Switchgear Insulated Case Breakers (Bus Mounted) | D3: =MAX(E3+F3,G3,H3,I3,J3,K3,L3,M3,N3,O3,P3,Q3) -> 0 | E3: =IF('Components Yr 1'!E3=0,0,'Components Yr 1'!E3) -> 0 | F3: =IF('Components Yr 1'!F3=0,0,'Components Yr 1'!F3) -> 0 | G3: =IF('Components Yr 1'!G3=0,0,'Components Yr 1'!G3) -> 0 | H3: =IF('Components Yr 1'!H3=0,0,'Components Yr 1'!H3) -> 0 | I3: =IF('Components Yr 1'!I3=0,0,'Components Yr 1'!I3) -> 0 | J3: =IF('Components Yr 1'!J3=0,0,'Components Yr 1'!J3) -> 0 | K3: =IF('Components Yr 1'!K3=0,0,'Components Yr 1'!K3) -> 0 | R3: =IF(SUMPRODUCT((E3:Q3)*1)=0,0,E3*INDEX(Hours!M:M,MATCH(C3,Hours!$A:$A,0))+F3*INDEX(Hours!B:B,MATCH(C3,Hours!$A:$A,0))+G3*INDEX(Hours!C:C,MATCH(C3,Hours!$A:$A,0))+H3*INDEX(Hours!D:D,MATCH(C3,Hours!$A:$A,0))+I3*INDEX(Hours!E:E,MATCH(C3,Hours!$A:$A,0))+J3*INDEX(Hours!F:F,MATCH(C3,Hours!$A:$A,0))+K3*INDEX(Hours!G:G,MATCH(C3,Hours!$A:$A,0))) -> 0 | S3: =MAX(E3+F3,G3,H3,I3,J3,K3,L3,M3,N3,O3,P3,Q3) -> 0
A4: ='Bldgs & Rooms'!$A$2 -> Main Bldg. | B4: ='Bldgs & Rooms'!$B$2 -> 0 | C4: =Hours!$A$4 -> SwitchGear Drawout Breakers | D4: =MAX(E4+F4,G4,H4,I4,J4,K4,L4,M4,N4,O4,P4,Q4) -> 0 | E4: =IF('Components Yr 1'!E4=0,0,'Components Yr 1'!E4) -> 0 | F4: =IF('Components Yr 1'!F4=0,0,'Components Yr 1'!F4) -> 0 | G4: =IF('Components Yr 1'!G4=0,0,'Components Yr 1'!G4) -> 0 | H4: =IF('Components Yr 1'!H4=0,0,'Components Yr 1'!H4) -> 0 | I4: =IF('Components Yr 1'!I4=0,0,'Components Yr 1'!I4) -> 0 | J4: =IF('Components Yr 1'!J4=0,0,'Components Yr 1'!J4) -> 0 | L4: =IF('Components Yr 1'!L4=0,0,'Components Yr 1'!L4) -> 0 | R4: =IF(SUMPRODUCT((E4:Q4)*1)=0,0,E4*INDEX(Hours!M:M,MATCH(C4,Hours!$A:$A,0))+F4*INDEX(Hours!B:B,MATCH(C4,Hours!$A:$A,0))+G4*INDEX(Hours!C:C,MATCH(C4,Hours!$A:$A,0))+H4*INDEX(Hours!D:D,MATCH(C4,Hours!$A:$A,0))+I4*INDEX(Hours!E:E,MATCH(C4,Hours!$A:$A,0))+J4*INDEX(Hours!F:F,MATCH(C4,Hours!$A:$A,0))+L4*INDEX(Hours!H:H,MATCH(C4,Hours!$A:$A,0))) -> 0 | S4: =MAX(E4+F4,G4,H4,I4,J4,K4,L4,M4,N4,O4,P4,Q4) -> 0
A5: ='Bldgs & Rooms'!$A$2 -> Main Bldg. | B5: ='Bldgs & Rooms'!$B$2 -> 0 | C5: =Hours!$A$5 -> Distribution Switchboard Multi Cover (Per Section) | D5: =MAX(E5+F5,G5,H5,I5,J5,K5,L5,M5,N5,O5,P5,Q5) -> 0 | E5: =IF('Components Yr 1'!E5=0,0,'Components Yr 1'!E5) -> 0 | F5: =IF('Components Yr 1'!F5=0,0,'Components Yr 1'!F5) -> 0 | G5: =IF('Components Yr 1'!G5=0,0,'Components Yr 1'!G5) -> 0 | H5: =IF('Components Yr 1'!H5=0,0,'Components Yr 1'!H5) -> 0 | I5: =IF('Components Yr 1'!I5=0,0,'Components Yr 1'!I5) -> 0 | J5: =IF('Components Yr 1'!J5=0,0,'Components Yr 1'!J5) -> 0 | K5: =IF('Components Yr 1'!K5=0,0,'Components Yr 1'!K5) -> 0 | O5: =IF('Components Yr 1'!O5=0,0,'Components Yr 1'!O5) -> 0 | R5: =IF(SUMPRODUCT((E5:Q5)*1)=0,0,E5*INDEX(Hours!M:M,MATCH(C5,Hours!$A:$A,0))+F5*INDEX(Hours!B:B,MATCH(C5,Hours!$A:$A,0))+G5*INDEX(Hours!C:C,MATCH(C5,Hours!$A:$A,0))+H5*INDEX(Hours!D:D,MATCH(C5,Hours!$A:$A,0))+I5*INDEX(Hours!E:E,MATCH(C5,Hours!$A:$A,0))+J5*INDEX(Hours!F:F,MATCH(C5,Hours!$A:$A,0))+K5*INDEX(Hours!G:G,MATCH(C5,Hours!$A:$A,0))+O5*INDEX(Hours!K:K,MATCH(C5,Hours!$A:$A,0))) -> 0 | S5: =MAX(E5+F5,G5,H5,I5,J5,K5,L5,M5,N5,O5,P5,Q5) -> 0
A6: ='Bldgs & Rooms'!$A$2 -> Main Bldg. | B6: ='Bldgs & Rooms'!$B$2 -> 0 | C6: =Hours!$A$6 -> Switchboard Disconnects | D6: =MAX(E6+F6,G6,H6,I6,J6,K6,L6,M6,N6,O6,P6,Q6) -> 0 | E6: =IF('Components Yr 1'!E6=0,0,'Components Yr 1'!E6) -> 0 | F6: =IF('Components Yr 1'!F6=0,0,'Components Yr 1'!F6) -> 0 | G6: =IF('Components Yr 1'!G6=0,0,'Components Yr 1'!G6) -> 0 | H6: =IF('Components Yr 1'!H6=0,0,'Components Yr 1'!H6) -> 0 | I6: =IF('Components Yr 1'!I6=0,0,'Components Yr 1'!I6) -> 0 | J6: =IF('Components Yr 1'!J6=0,0,'Components Yr 1'!J6) -> 0 | R6: =IF(SUMPRODUCT((E6:Q6)*1)=0,0,E6*INDEX(Hours!M:M,MATCH(C6,Hours!$A:$A,0))+F6*INDEX(Hours!B:B,MATCH(C6,Hours!$A:$A,0))+G6*INDEX(Hours!C:C,MATCH(C6,Hours!$A:$A,0))+H6*INDEX(Hours!D:D,MATCH(C6,Hours!$A:$A,0))+I6*INDEX(Hours!E:E,MATCH(C6,Hours!$A:$A,0))+J6*INDEX(Hours!F:F,MATCH(C6,Hours!$A:$A,0))) -> 0 | S6: =MAX(E6+F6,G6,H6,I6,J6,K6,L6,M6,N6,O6,P6,Q6) -> 0
A7: ='Bldgs & Rooms'!$A$2 -> Main Bldg. | B7: ='Bldgs & Rooms'!$B$2 -> 0 | C7: =Hours!$A$7 -> Switchboard Molded Case Breakers | D7: =MAX(E7+F7,G7,H7,I7,J7,K7,L7,M7,N7,O7,P7,Q7) -> 0 | E7: =IF('Components Yr 1'!E7=0,0,'Components Yr 1'!E7) -> 0 | F7: =IF('Components Yr 1'!F7=0,0,'Components Yr 1'!F7) -> 0 | G7: =IF('Components Yr 1'!G7=0,0,'Components Yr 1'!G7) -> 0 | H7: =IF('Components Yr 1'!H7=0,0,'Components Yr 1'!H7) -> 0 | I7: =IF('Components Yr 1'!I7=0,0,'Components Yr 1'!I7) -> 0 | J7: =IF('Components Yr 1'!J7=0,0,'Components Yr 1'!J7) -> 0 | K7: =IF('Components Yr 1'!K7=0,0,'Components Yr 1'!K7) -> 0 | R7: =IF(SUMPRODUCT((E7:Q7)*1)=0,0,E7*INDEX(Hours!M:M,MATCH(C7,Hours!$A:$A,0))+F7*INDEX(Hours!B:B,MATCH(C7,Hours!$A:$A,0))+G7*INDEX(Hours!C:C,MATCH(C7,Hours!$A:$A,0))+H7*INDEX(Hours!D:D,MATCH(C7,Hours!$A:$A,0))+I7*INDEX(Hours!E:E,MATCH(C7,Hours!$A:$A,0))+J7*INDEX(Hours!F:F,MATCH(C7,Hours!$A:$A,0))+K7*INDEX(Hours!G:G,MATCH(C7,Hours!$A:$A,0))) -> 0 | S7: =MAX(E7+F7,G7,H7,I7,J7,K7,L7,M7,N7,O7,P7,Q7) -> 0
A8: ='Bldgs & Rooms'!$A$2 -> Main Bldg. | B8: ='Bldgs & Rooms'!$B$2 -> 0 | C8: =Hours!$A$8 -> Panelboard-Single Cover > 400A (Distribution Panel) | D8: =MAX(E8+F8,G8,H8,I8,J8,K8,L8,M8,N8,O8,P8,Q8) -> 0 | E8: =IF('Components Yr 1'!E8=0,0,'Components Yr 1'!E8) -> 0 | F8: =IF('Components Yr 1'!F8=0,0,'Components Yr 1'!F8) -> 0 | G8: =IF('Components Yr 1'!G8=0,0,'Components Yr 1'!G8) -> 0 | H8: =IF('Components Yr 1'!H8=0,0,'Components Yr 1'!H8) -> 0 | I8: =IF('Components Yr 1'!I8=0,0,'Components Yr 1'!I8) -> 0 | J8: =IF('Components Yr 1'!J8=0,0,'Components Yr 1'!J8) -> 0 | K8: =IF('Components Yr 1'!K8=0,0,'Components Yr 1'!K8) -> 0 | O8: =IF('Components Yr 1'!O8=0,0,'Components Yr 1'!O8) -> 0 | R8: =IF(SUMPRODUCT((E8:Q8)*1)=0,0,E8*INDEX(Hours!M:M,MATCH(C8,Hours!$A:$A,0))+F8*INDEX(Hours!B:B,MATCH(C8,Hours!$A:$A,0))+G8*INDEX(Hours!C:C,MATCH(C8,Hours!$A:$A,0))+H8*INDEX(Hours!D:D,MATCH(C8,Hours!$A:$A,0))+I8*INDEX(Hours!E:E,MATCH(C8,Hours!$A:$A,0))+J8*INDEX(Hours!F:F,MATCH(C8,Hours!$A:$A,0))+K8*INDEX(Hours!G:G,MATCH(C8,Hours!$A:$A,0))+O8*INDEX(Hours!K:K,MATCH(C8,Hours!$A:$A,0))) -> 0 | S8: =MAX(E8+F8,G8,H8,I8,J8,K8,L8,M8,N8,O8,P8,Q8) -> 0
A9: ='Bldgs & Rooms'!$A$2 -> Main Bldg. | B9: ='Bldgs & Rooms'!$B$2 -> 0 | C9: =Hours!$A$9 -> Panelboard-Single Cover < 400A (Branch Ckt Panel) | D9: =MAX(E9+F9,G9,H9,I9,J9,K9,L9,M9,N9,O9,P9,Q9) -> 0 | E9: =IF('Components Yr 1'!E9=0,0,'Components Yr 1'!E9) -> 0 | F9: =IF('Components Yr 1'!F9=0,0,'Components Yr 1'!F9) -> 0 | G9: =IF('Components Yr 1'!G9=0,0,'Components Yr 1'!G9) -> 0 | H9: =IF('Components Yr 1'!H9=0,0,'Components Yr 1'!H9) -> 0 | I9: =IF('Components Yr 1'!I9=0,0,'Components Yr 1'!I9) -> 0 | J9: =IF('Components Yr 1'!J9=0,0,'Components Yr 1'!J9) -> 0 | O9: =IF('Components Yr 1'!O9=0,0,'Components Yr 1'!O9) -> 0 | R9: =IF(SUMPRODUCT((E9:Q9)*1)=0,0,E9*INDEX(Hours!M:M,MATCH(C9,Hours!$A:$A,0))+F9*INDEX(Hours!B:B,MATCH(C9,Hours!$A:$A,0))+G9*INDEX(Hours!C:C,MATCH(C9,Hours!$A:$A,0))+H9*INDEX(Hours!D:D,MATCH(C9,Hours!$A:$A,0))+I9*INDEX(Hours!E:E,MATCH(C9,Hours!$A:$A,0))+J9*INDEX(Hours!F:F,MATCH(C9,Hours!$A:$A,0))+O9*INDEX(Hours!K:K,MATCH(C9,Hours!$A:$A,0))) -> 0 | S9: =MAX(E9+F9,G9,H9,I9,J9,K9,L9,M9,N9,O9,P9,Q9) -> 0
A10: ='Bldgs & Rooms'!$A$2 -> Main Bldg. | B10: ='Bldgs & Rooms'!$B$2 -> 0 | C10: =Hours!$A$10 -> Motor Control Center (MCC-Per Vertical Section) | D10: =MAX(E10+F10,G10,H10,I10,J10,K10,L10,M10,N10,O10,P10,Q10) -> 0 | E10: =IF('Components Yr 1'!E10=0,0,'Components Yr 1'!E10) -> 0 | F10: =IF('Components Yr 1'!F10=0,0,'Components Yr 1'!F10) -> 0 | G10: =IF('Components Yr 1'!G10=0,0,'Components Yr 1'!G10) -> 0 | H10: =IF('Components Yr 1'!H10=0,0,'Components Yr 1'!H10) -> 0 | I10: =IF('Components Yr 1'!I10=0,0,'Components Yr 1'!I10) -> 0 | J10: =IF('Components Yr 1'!J10=0,0,'Components Yr 1'!J10) -> 0 | O10: =IF('Components Yr 1'!O10=0,0,'Components Yr 1'!O10) -> 0 | R10: =IF(SUMPRODUCT((E10:Q10)*1)=0,0,E10*INDEX(Hours!M:M,MATCH(C10,Hours!$A:$A,0))+F10*INDEX(Hours!B:B,MATCH(C10,Hours!$A:$A,0))+G10*INDEX(Hours!C:C,MATCH(C10,Hours!$A:$A,0))+H10*INDEX(Hours!D:D,MATCH(C10,Hours!$A:$A,0))+I10*INDEX(Hours!E:E,MATCH(C10,Hours!$A:$A,0))+J10*INDEX(Hours!F:F,MATCH(C10,Hours!$A:$A,0))+O10*INDEX(Hours!K:K,MATCH(C10,Hours!$A:$A,0))) -> 0 | S10: =MAX(E10+F10,G10,H10,I10,J10,K10,L10,M10,N10,O10,P10,Q10) -> 0
A11: ='Bldgs & Rooms'!$A$2 -> Main Bldg. | B11: ='Bldgs & Rooms'!$B$2 -> 0 | C11: =Hours!$A$11 -> MCC: Combination Motor Starters | D11: =MAX(E11+F11,G11,H11,I11,J11,K11,L11,M11,N11,O11,P11,Q11) -> 0 | E11: =IF('Components Yr 1'!E11=0,0,'Components Yr 1'!E11) -> 0 | F11: =IF('Components Yr 1'!F11=0,0,'Components Yr 1'!F11) -> 0 | G11: =IF('Components Yr 1'!G11=0,0,'Components Yr 1'!G11) -> 0 | H11: =IF('Components Yr 1'!H11=0,0,'Components Yr 1'!H11) -> 0 | I11: =IF('Components Yr 1'!I11=0,0,'Components Yr 1'!I11) -> 0 | J11: =IF('Components Yr 1'!J11=0,0,'Components Yr 1'!J11) -> 0 | K11: =IF('Components Yr 1'!K11=0,0,'Components Yr 1'!K11) -> 0 | O11: =IF('Components Yr 1'!O11=0,0,'Components Yr 1'!O11) -> 0 | R11: =IF(SUMPRODUCT((E11:Q11)*1)=0,0,E11*INDEX(Hours!M:M,MATCH(C11,Hours!$A:$A,0))+F11*INDEX(Hours!B:B,MATCH(C11,Hours!$A:$A,0))+G11*INDEX(Hours!C:C,MATCH(C11,Hours!$A:$A,0))+H11*INDEX(Hours!D:D,MATCH(C11,Hours!$A:$A,0))+I11*INDEX(Hours!E:E,MATCH(C11,Hours!$A:$A,0))+J11*INDEX(Hours!F:F,MATCH(C11,Hours!$A:$A,0))+K11*INDEX(Hours!G:G,MATCH(C11,Hours!$A:$A,0))+O11*INDEX(Hours!K:K,MATCH(C11,Hours!$A:$A,0))) -> 0 | S11: =MAX(E11+F11,G11,H11,I11,J11,K11,L11,M11,N11,O11,P11,Q11) -> 0
A12: ='Bldgs & Rooms'!$A$2 -> Main Bldg. | B12: ='Bldgs & Rooms'!$B$2 -> 0 | C12: =Hours!$A$12 -> MCC: Molded Case Breaker | D12: =MAX(E12+F12,G12,H12,I12,J12,K12,L12,M12,N12,O12,P12,Q12) -> 0 | E12: =IF('Components Yr 1'!E12=0,0,'Components Yr 1'!E12) -> 0 | F12: =IF('Components Yr 1'!F12=0,0,'Components Yr 1'!F12) -> 0 | G12: =IF('Components Yr 1'!G12=0,0,'Components Yr 1'!G12) -> 0 | H12: =IF('Components Yr 1'!H12=0,0,'Components Yr 1'!H12) -> 0 | I12: =IF('Components Yr 1'!I12=0,0,'Components Yr 1'!I12) -> 0 | J12: =IF('Components Yr 1'!J12=0,0,'Components Yr 1'!J12) -> 0 | K12: =IF('Components Yr 1'!K12=0,0,'Components Yr 1'!K12) -> 0 | R12: =IF(SUMPRODUCT((E12:Q12)*1)=0,0,E12*INDEX(Hours!M:M,MATCH(C12,Hours!$A:$A,0))+F12*INDEX(Hours!B:B,MATCH(C12,Hours!$A:$A,0))+G12*INDEX(Hours!C:C,MATCH(C12,Hours!$A:$A,0))+H12*INDEX(Hours!D:D,MATCH(C12,Hours!$A:$A,0))+I12*INDEX(Hours!E:E,MATCH(C12,Hours!$A:$A,0))+J12*INDEX(Hours!F:F,MATCH(C12,Hours!$A:$A,0))+K12*INDEX(Hours!G:G,MATCH(C12,Hours!$A:$A,0))) -> 0 | S12: =MAX(E12+F12,G12,H12,I12,J12,K12,L12,M12,N12,O12,P12,Q12) -> 0
A13: ='Bldgs & Rooms'!$A$2 -> Main Bldg. | B13: ='Bldgs & Rooms'!$B$2 -> 0 | C13: =Hours!$A$13 -> MCC: Individual Disconnect Switch | D13: =MAX(E13+F13,G13,H13,I13,J13,K13,L13,M13,N13,O13,P13,Q13) -> 0 | E13: =IF('Components Yr 1'!E13=0,0,'Components Yr 1'!E13) -> 0 | F13: =IF('Components Yr 1'!F13=0,0,'Components Yr 1'!F13) -> 0 | G13: =IF('Components Yr 1'!G13=0,0,'Components Yr 1'!G13) -> 0 | H13: =IF('Components Yr 1'!H13=0,0,'Components Yr 1'!H13) -> 0 | I13: =IF('Components Yr 1'!I13=0,0,'Components Yr 1'!I13) -> 0 | J13: =IF('Components Yr 1'!J13=0,0,'Components Yr 1'!J13) -> 0 | R13: =IF(SUMPRODUCT((E13:Q13)*1)=0,0,E13*INDEX(Hours!M:M,MATCH(C13,Hours!$A:$A,0))+F13*INDEX(Hours!B:B,MATCH(C13,Hours!$A:$A,0))+G13*INDEX(Hours!C:C,MATCH(C13,Hours!$A:$A,0))+H13*INDEX(Hours!D:D,MATCH(C13,Hours!$A:$A,0))+I13*INDEX(Hours!E:E,MATCH(C13,Hours!$A:$A,0))+J13*INDEX(Hours!F:F,MATCH(C13,Hours!$A:$A,0))) -> 0 | S13: =MAX(E13+F13,G13,H13,I13,J13,K13,L13,M13,N13,O13,P13,Q13) -> 0
A14: ='Bldgs & Rooms'!$A$2 -> Main Bldg. | B14: ='Bldgs & Rooms'!$B$2 -> 0 | C14: =Hours!$A$14 -> Motor Control Panel (MCP) | D14: =MAX(E14+F14,G14,H14,I14,J14,K14,L14,M14,N14,O14,P14,Q14) -> 0 | E14: =IF('Components Yr 1'!E14=0,0,'Components Yr 1'!E14) -> 0 | F14: =IF('Components Yr 1'!F14=0,0,'Components Yr 1'!F14) -> 0 | G14: =IF('Components Yr 1'!G14=0,0,'Components Yr 1'!G14) -> 0 | H14: =IF('Components Yr 1'!H14=0,0,'Components Yr 1'!H14) -> 0 | I14: =IF('Components Yr 1'!I14=0,0,'Components Yr 1'!I14) -> 0 | J14: =IF('Components Yr 1'!J14=0,0,'Components Yr 1'!J14) -> 0 | O14: =IF('Components Yr 1'!O14=0,0,'Components Yr 1'!O14) -> 0 | R14: =IF(SUMPRODUCT((E14:Q14)*1)=0,0,E14*INDEX(Hours!M:M,MATCH(C14,Hours!$A:$A,0))+F14*INDEX(Hours!B:B,MATCH(C14,Hours!$A:$A,0))+G14*INDEX(Hours!C:C,MATCH(C14,Hours!$A:$A,0))+H14*INDEX(Hours!D:D,MATCH(C14,Hours!$A:$A,0))+I14*INDEX(Hours!E:E,MATCH(C14,Hours!$A:$A,0))+J14*INDEX(Hours!F:F,MATCH(C14,Hours!$A:$A,0))+O14*INDEX(Hours!K:K,MATCH(C14,Hours!$A:$A,0))) -> 0 | S14: =MAX(E14+F14,G14,H14,I14,J14,K14,L14,M14,N14,O14,P14,Q14) -> 0
A15: ='Bldgs & Rooms'!$A$2 -> Main Bldg. | B15: ='Bldgs & Rooms'!$B$2 -> 0 | C15: =Hours!$A$15 -> VFD Motor Control Panel (VFD-MCP) | D15: =MAX(E15+F15,G15,H15,I15,J15,K15,L15,M15,N15,O15,P15,Q15) -> 0 | E15: =IF('Components Yr 1'!E15=0,0,'Components Yr 1'!E15) -> 0 | F15: =IF('Components Yr 1'!F15=0,0,'Components Yr 1'!F15) -> 0 | G15: =IF('Components Yr 1'!G15=0,0,'Components Yr 1'!G15) -> 0 | H15: =IF('Components Yr 1'!H15=0,0,'Components Yr 1'!H15) -> 0 | I15: =IF('Components Yr 1'!I15=0,0,'Components Yr 1'!I15) -> 0 | J15: =IF('Components Yr 1'!J15=0,0,'Components Yr 1'!J15) -> 0 | O15: =IF('Components Yr 1'!O15=0,0,'Components Yr 1'!O15) -> 0 | R15: =IF(SUMPRODUCT((E15:Q15)*1)=0,0,E15*INDEX(Hours!M:M,MATCH(C15,Hours!$A:$A,0))+F15*INDEX(Hours!B:B,MATCH(C15,Hours!$A:$A,0))+G15*INDEX(Hours!C:C,MATCH(C15,Hours!$A:$A,0))+H15*INDEX(Hours!D:D,MATCH(C15,Hours!$A:$A,0))+I15*INDEX(Hours!E:E,MATCH(C15,Hours!$A:$A,0))+J15*INDEX(Hours!F:F,MATCH(C15,Hours!$A:$A,0))+O15*INDEX(Hours!K:K,MATCH(C15,Hours!$A:$A,0))) -> 0 | S15: =MAX(E15+F15,G15,H15,I15,J15,K15,L15,M15,N15,O15,P15,Q15) -> 0
A16: ='Bldgs & Rooms'!$A$2 -> Main Bldg. | B16: ='Bldgs & Rooms'!$B$2 -> 0 | C16: =Hours!$A$16 -> Individual Disconnect Switch > 100A | D16: =MAX(E16+F16,G16,H16,I16,J16,K16,L16,M16,N16,O16,P16,Q16) -> 0 | E16: =IF('Components Yr 1'!E16=0,0,'Components Yr 1'!E16) -> 0 | F16: =IF('Components Yr 1'!F16=0,0,'Components Yr 1'!F16) -> 0 | G16: =IF('Components Yr 1'!G16=0,0,'Components Yr 1'!G16) -> 0 | H16: =IF('Components Yr 1'!H16=0,0,'Components Yr 1'!H16) -> 0 | I16: =IF('Components Yr 1'!I16=0,0,'Components Yr 1'!I16) -> 0 | J16: =IF('Components Yr 1'!J16=0,0,'Components Yr 1'!J16) -> 0 | K16: =IF('Components Yr 1'!K16=0,0,'Components Yr 1'!K16) -> 0 | R16: =IF(SUMPRODUCT((E16:Q16)*1)=0,0,E16*INDEX(Hours!M:M,MATCH(C16,Hours!$A:$A,0))+F16*INDEX(Hours!B:B,MATCH(C16,Hours!$A:$A,0))+G16*INDEX(Hours!C:C,MATCH(C16,Hours!$A:$A,0))+H16*INDEX(Hours!D:D,MATCH(C16,Hours!$A:$A,0))+I16*INDEX(Hours!E:E,MATCH(C16,Hours!$A:$A,0))+J16*INDEX(Hours!F:F,MATCH(C16,Hours!$A:$A,0))+K16*INDEX(Hours!G:G,MATCH(C16,Hours!$A:$A,0))) -> 0 | S16: =MAX(E16+F16,G16,H16,I16,J16,K16,L16,M16,N16,O16,P16,Q16) -> 0
A17: ='Bldgs & Rooms'!$A$2 -> Main Bldg. | B17: ='Bldgs & Rooms'!$B$2 -> 0 | C17: =Hours!$A$17 -> Individual Molded Case Breaker > 100A | D17: =MAX(E17+F17,G17,H17,I17,J17,K17,L17,M17,N17,O17,P17,Q17) -> 0 | E17: =IF('Components Yr 1'!E17=0,0,'Components Yr 1'!E17) -> 0 | F17: =IF('Components Yr 1'!F17=0,0,'Components Yr 1'!F17) -> 0 | G17: =IF('Components Yr 1'!G17=0,0,'Components Yr 1'!G17) -> 0 | H17: =IF('Components Yr 1'!H17=0,0,'Components Yr 1'!H17) -> 0 | I17: =IF('Components Yr 1'!I17=0,0,'Components Yr 1'!I17) -> 0 | J17: =IF('Components Yr 1'!J17=0,0,'Components Yr 1'!J17) -> 0 | K17: =IF('Components Yr 1'!K17=0,0,'Components Yr 1'!K17) -> 0 | R17: =IF(SUMPRODUCT((E17:Q17)*1)=0,0,E17*INDEX(Hours!M:M,MATCH(C17,Hours!$A:$A,0))+F17*INDEX(Hours!B:B,MATCH(C17,Hours!$A:$A,0))+G17*INDEX(Hours!C:C,MATCH(C17,Hours!$A:$A,0))+H17*INDEX(Hours!D:D,MATCH(C17,Hours!$A:$A,0))+I17*INDEX(Hours!E:E,MATCH(C17,Hours!$A:$A,0))+J17*INDEX(Hours!F:F,MATCH(C17,Hours!$A:$A,0))+K17*INDEX(Hours!G:G,MATCH(C17,Hours!$A:$A,0))) -> 0 | S17: =MAX(E17+F17,G17,H17,I17,J17,K17,L17,M17,N17,O17,P17,Q17) -> 0
A18: ='Bldgs & Rooms'!$A$2 -> Main Bldg. | B18: ='Bldgs & Rooms'!$B$2 -> 0 | C18: =Hours!$A$18 -> Individual Combination Motor Starter > 100A | D18: =MAX(E18+F18,G18,H18,I18,J18,K18,L18,M18,N18,O18,P18,Q18) -> 0 | E18: =IF('Components Yr 1'!E18=0,0,'Components Yr 1'!E18) -> 0 | F18: =IF('Components Yr 1'!F18=0,0,'Components Yr 1'!F18) -> 0 | G18: =IF('Components Yr 1'!G18=0,0,'Components Yr 1'!G18) -> 0 | H18: =IF('Components Yr 1'!H18=0,0,'Components Yr 1'!H18) -> 0 | I18: =IF('Components Yr 1'!I18=0,0,'Components Yr 1'!I18) -> 0 | J18: =IF('Components Yr 1'!J18=0,0,'Components Yr 1'!J18) -> 0 | K18: =IF('Components Yr 1'!K18=0,0,'Components Yr 1'!K18) -> 0 | R18: =IF(SUMPRODUCT((E18:Q18)*1)=0,0,E18*INDEX(Hours!M:M,MATCH(C18,Hours!$A:$A,0))+F18*INDEX(Hours!B:B,MATCH(C18,Hours!$A:$A,0))+G18*INDEX(Hours!C:C,MATCH(C18,Hours!$A:$A,0))+H18*INDEX(Hours!D:D,MATCH(C18,Hours!$A:$A,0))+I18*INDEX(Hours!E:E,MATCH(C18,Hours!$A:$A,0))+J18*INDEX(Hours!F:F,MATCH(C18,Hours!$A:$A,0))+K18*INDEX(Hours!G:G,MATCH(C18,Hours!$A:$A,0))) -> 0 | S18: =MAX(E18+F18,G18,H18,I18,J18,K18,L18,M18,N18,O18,P18,Q18) -> 0
A19: ='Bldgs & Rooms'!$A$2 -> Main Bldg. | B19: ='Bldgs & Rooms'!$B$2 -> 0 | C19: =Hours!$A$19 -> Oil Filled Transformer - 5kV-15kV Primary - Any Size (Pad Mounted) | D19: =MAX(E19+F19,G19,H19,I19,J19,K19,L19,M19,N19,O19,P19,Q19) -> 0 | E19: =IF('Components Yr 1'!E19=0,0,'Components Yr 1'!E19) -> 0 | F19: =IF('Components Yr 1'!F19=0,0,'Components Yr 1'!F19) -> 0 | G19: =IF('Components Yr 1'!G19=0,0,'Components Yr 1'!G19) -> 0 | H19: =IF('Components Yr 1'!H19=0,0,'Components Yr 1'!H19) -> 0 | I19: =IF('Components Yr 1'!I19=0,0,'Components Yr 1'!I19) -> 0 | J19: =IF('Components Yr 1'!J19=0,0,'Components Yr 1'!J19) -> 0 | M19: =IF('Components Yr 1'!M19=0,0,'Components Yr 1'!M19) -> 0 | N19: =IF('Components Yr 1'!N19=0,0,'Components Yr 1'!N19) -> 0 | P19: =IF('Components Yr 1'!P19=0,0,'Components Yr 1'!P19) -> 0 | R19: =IF(SUMPRODUCT((E19:Q19)*1)=0,0,E19*INDEX(Hours!M:M,MATCH(C19,Hours!$A:$A,0))+F19*INDEX(Hours!B:B,MATCH(C19,Hours!$A:$A,0))+G19*INDEX(Hours!C:C,MATCH(C19,Hours!$A:$A,0))+H19*INDEX(Hours!D:D,MATCH(C19,Hours!$A:$A,0))+I19*INDEX(Hours!E:E,MATCH(C19,Hours!$A:$A,0))+J19*INDEX(Hours!F:F,MATCH(C19,Hours!$A:$A,0))+M19*INDEX(Hours!I:I,MATCH(C19,Hours!$A:$A,0))+N19*INDEX(Hours!J:J,MATCH(C19,Hours!$A:$A,0))+P19*INDEX(Hours!L:L,MATCH(C19,Hours!$A:$A,0))) -> 0 | S19: =MAX(E19+F19,G19,H19,I19,J19,K19,L19,M19,N19,O19,P19,Q19) -> 0
A20: ='Bldgs & Rooms'!$A$2 -> Main Bldg. | B20: ='Bldgs & Rooms'!$B$2 -> 0 | C20: =Hours!$A$20 -> Oil Filled Transformer - > 15kV Primary (Substation Class) | D20: =MAX(E20+F20,G20,H20,I20,J20,K20,L20,M20,N20,O20,P20,Q20) -> 0 | E20: =IF('Components Yr 1'!E20=0,0,'Components Yr 1'!E20) -> 0 | F20: =IF('Components Yr 1'!F20=0,0,'Components Yr 1'!F20) -> 0 | G20: =IF('Components Yr 1'!G20=0,0,'Components Yr 1'!G20) -> 0 | H20: =IF('Components Yr 1'!H20=0,0,'Components Yr 1'!H20) -> 0 | I20: =IF('Components Yr 1'!I20=0,0,'Components Yr 1'!I20) -> 0 | J20: =IF('Components Yr 1'!J20=0,0,'Components Yr 1'!J20) -> 0 | M20: =IF('Components Yr 1'!M20=0,0,'Components Yr 1'!M20) -> 0 | N20: =IF('Components Yr 1'!N20=0,0,'Components Yr 1'!N20) -> 0 | P20: =IF('Components Yr 1'!P20=0,0,'Components Yr 1'!P20) -> 0 | R20: =IF(SUMPRODUCT((E20:Q20)*1)=0,0,E20*INDEX(Hours!M:M,MATCH(C20,Hours!$A:$A,0))+F20*INDEX(Hours!B:B,MATCH(C20,Hours!$A:$A,0))+G20*INDEX(Hours!C:C,MATCH(C20,Hours!$A:$A,0))+H20*INDEX(Hours!D:D,MATCH(C20,Hours!$A:$A,0))+I20*INDEX(Hours!E:E,MATCH(C20,Hours!$A:$A,0))+J20*INDEX(Hours!F:F,MATCH(C20,Hours!$A:$A,0))+M20*INDEX(Hours!I:I,MATCH(C20,Hours!$A:$A,0))+N20*INDEX(Hours!J:J,MATCH(C20,Hours!$A:$A,0))+P20*INDEX(Hours!L:L,MATCH(C20,Hours!$A:$A,0))) -> 0 | S20: =MAX(E20+F20,G20,H20,I20,J20,K20,L20,M20,N20,O20,P20,Q20) -> 0
A21: ='Bldgs & Rooms'!$A$2 -> Main Bldg. | B21: ='Bldgs & Rooms'!$B$2 -> 0 | C21: =Hours!$A$21 -> Dry Type Transformer - < 480V Primary - Any Size kVA | D21: =MAX(E21+F21,G21,H21,I21,J21,K21,L21,M21,N21,O21,P21,Q21) -> 0 | E21: =IF('Components Yr 1'!E21=0,0,'Components Yr 1'!E21) -> 0 | F21: =IF('Components Yr 1'!F21=0,0,'Components Yr 1'!F21) -> 0 | G21: =IF('Components Yr 1'!G21=0,0,'Components Yr 1'!G21) -> 0 | H21: =IF('Components Yr 1'!H21=0,0,'Components Yr 1'!H21) -> 0 | I21: =IF('Components Yr 1'!I21=0,0,'Components Yr 1'!I21) -> 0 | J21: =IF('Components Yr 1'!J21=0,0,'Components Yr 1'!J21) -> 0 | M21: =IF('Components Yr 1'!M21=0,0,'Components Yr 1'!M21) -> 0 | N21: =IF('Components Yr 1'!N21=0,0,'Components Yr 1'!N21) -> 0 | R21: =IF(SUMPRODUCT((E21:Q21)*1)=0,0,E21*INDEX(Hours!M:M,MATCH(C21,Hours!$A:$A,0))+F21*INDEX(Hours!B:B,MATCH(C21,Hours!$A:$A,0))+G21*INDEX(Hours!C:C,MATCH(C21,Hours!$A:$A,0))+H21*INDEX(Hours!D:D,MATCH(C21,Hours!$A:$A,0))+I21*INDEX(Hours!E:E,MATCH(C21,Hours!$A:$A,0))+J21*INDEX(Hours!F:F,MATCH(C21,Hours!$A:$A,0))+M21*INDEX(Hours!I:I,MATCH(C21,Hours!$A:$A,0))+N21*INDEX(Hours!J:J,MATCH(C21,Hours!$A:$A,0))) -> 0 | S21: =MAX(E21+F21,G21,H21,I21,J21,K21,L21,M21,N21,O21,P21,Q21) -> 0
A22: ='Bldgs & Rooms'!$A$2 -> Main Bldg. | B22: ='Bldgs & Rooms'!$B$2 -> 0 | C22: =Hours!$A$22 -> Power Factor Correction Capacitors | D22: =MAX(E22+F22,G22,H22,I22,J22,K22,L22,M22,N22,O22,P22,Q22) -> 0 | E22: =IF('Components Yr 1'!E22=0,0,'Components Yr 1'!E22) -> 0 | F22: =IF('Components Yr 1'!F22=0,0,'Components Yr 1'!F22) -> 0 | G22: =IF('Components Yr 1'!G22=0,0,'Components Yr 1'!G22) -> 0 | H22: =IF('Components Yr 1'!H22=0,0,'Components Yr 1'!H22) -> 0 | I22: =IF('Components Yr 1'!I22=0,0,'Components Yr 1'!I22) -> 0 | J22: =IF('Components Yr 1'!J22=0,0,'Components Yr 1'!J22) -> 0 | R22: =IF(SUMPRODUCT((E22:Q22)*1)=0,0,E22*INDEX(Hours!M:M,MATCH(C22,Hours!$A:$A,0))+F22*INDEX(Hours!B:B,MATCH(C22,Hours!$A:$A,0))+G22*INDEX(Hours!C:C,MATCH(C22,Hours!$A:$A,0))+H22*INDEX(Hours!D:D,MATCH(C22,Hours!$A:$A,0))+I22*INDEX(Hours!E:E,MATCH(C22,Hours!$A:$A,0))+J22*INDEX(Hours!F:F,MATCH(C22,Hours!$A:$A,0))) -> 0 | S22: =MAX(E22+F22,G22,H22,I22,J22,K22,L22,M22,N22,O22,P22,Q22) -> 0
A23: ='Bldgs & Rooms'!$A$2 -> Main Bldg. | B23: ='Bldgs & Rooms'!$B$2 -> 0 | C23: =Hours!$A$23 -> Lighting Contactor > 100A | D23: =MAX(E23+F23,G23,H23,I23,J23,K23,L23,M23,N23,O23,P23,Q23) -> 0 | E23: =IF('Components Yr 1'!E23=0,0,'Components Yr 1'!E23) -> 0 | F23: =IF('Components Yr 1'!F23=0,0,'Components Yr 1'!F23) -> 0 | G23: =IF('Components Yr 1'!G23=0,0,'Components Yr 1'!G23) -> 0 | H23: =IF('Components Yr 1'!H23=0,0,'Components Yr 1'!H23) -> 0 | I23: =IF('Components Yr 1'!I23=0,0,'Components Yr 1'!I23) -> 0 | J23: =IF('Components Yr 1'!J23=0,0,'Components Yr 1'!J23) -> 0 | R23: =IF(SUMPRODUCT((E23:Q23)*1)=0,0,E23*INDEX(Hours!M:M,MATCH(C23,Hours!$A:$A,0))+F23*INDEX(Hours!B:B,MATCH(C23,Hours!$A:$A,0))+G23*INDEX(Hours!C:C,MATCH(C23,Hours!$A:$A,0))+H23*INDEX(Hours!D:D,MATCH(C23,Hours!$A:$A,0))+I23*INDEX(Hours!E:E,MATCH(C23,Hours!$A:$A,0))+J23*INDEX(Hours!F:F,MATCH(C23,Hours!$A:$A,0))) -> 0 | S23: =MAX(E23+F23,G23,H23,I23,J23,K23,L23,M23,N23,O23,P23,Q23) -> 0
